Workbook

Sheet Read Me
A1: Meta Builder: how every stat and talent is calculated
A3: Version | B3: v0.25 (pre-release). Built from the app's own code and data, so the numbers match what the planner uses.
A4: Game data | B4: deepwoken.co (talents, mantras, weapons, equipment, oaths, reference builds; October 2026). Traits: deepwoken.fandom.com/wiki/Traits.
A6: Sheet | B6: What it has
A7: Calculator | B7: Type stats in the yellow cells (blue text) and every result recalculates: Power, points left, talent cap, health and effective health, weapon damage, mantra damage, trait effects.
A8: Formulas | B8: Every calculation the app does, in plain words and as a formula, with where it lives in the code (src/template.html).
A9: Talents | B9: All 622 talents: requirements, cheapest way to meet them, whether they can be taken before the shrine, popularity, take rate given stats, damage/PEN bonus, synergies, exclusives, description.
A10: Mantras | B10: All 230 mantras: attunement, category, requirement, stat scaling, damage at levels 1-5, and live damage with the Calculator stats.
A11: Weapons | B11: All 231 weapons: type, requirement, base damage, PEN, stat scaling, and live hit damage with the Calculator stats.
A12: Outfits | B12: All outfits: physical/elemental armor, durability, requirement, talents they give.
A13: Equipment | B13: All equipment pieces: slot, health/armor, pip slots, requirement, set, talents they give.
A14: Enchants | B14: Weapon enchants and how each is counted.
A15: Oaths | B15: Each oath's stat requirement options and notes.
... A20: Codes | B20: STR Strength, FTD Fortitude, AGL Agility, INT Intelligence, WLL Willpower, CHA Charisma, HVY/MED/LHT Heavy/Medium/Light weapon, FLM Flamecharm, ICE Frostdraw, LTN Thundercall, WND Galebreathe, SDW Shadowcast, IRN Ironsing, BLD Bloodrend, MND = highest of INT/WLL/CHA, BOD = highest of STR/FTD/AGL, PWR = Power.

Sheet Calculator
A1: Calculator
A2: Change the yellow cells. Green cells are formulas. Take the "Before shrine", "Shrine leaves" and "Final" numbers from the app's stats table (Stats tab).
A4: Stats
A5: Code | B5: Stat | C5: Before shrine | D5: Shrine leaves | E5: Final | F5: Added after shrine
A6: STR | B6: Strength | C6: 1 | D6: 22 | E6: 22 | F6: =MAX(0,E6-D6) -> 0
A7: FTD | B7: Fortitude | C7: 50 | D7: 25 | E7: 25 | F7: =MAX(0,E7-D7) -> 0
A8: AGL | B8: Agility | C8: 40 | D8: 22 | E8: 22 | F8: =MAX(0,E8-D8) -> 0
A9: INT | B9: Intelligence | C9: 0 | D9: 0 | E9: 0 | F9: =MAX(0,E9-D9) -> 0
A10: WLL | B10: Willpower | C10: 40 | D10: 22 | E10: 22 | F10: =MAX(0,E10-D10) -> 0
A11: CHA | B11: Charisma | C11: 1 | D11: 22 | E11: 25 | F11: =MAX(0,E11-D11) -> 3
A12: HVY | B12: Heavy weapon | C12: 0 | D12: 0 | E12: 0 | F12: =MAX(0,E12-D12) -> 0
A13: MED | B13: Medium weapon | C13: 1 | D13: 22 | E13: 92 | F13: =MAX(0,E13-D13) -> 70
A14: LHT | B14: Light weapon | C14: 0 | D14: 0 | E14: 0 | F14: =MAX(0,E14-D14) -> 0
A15: FLM | B15: Flamecharm | C15: 0 | D15: 0 | E15: 0 | F15: =MAX(0,E15-D15) -> 0
A16: ICE | B16: Frostdraw | C16: 0 | D16: 0 | E16: 0 | F16: =MAX(0,E16-D16) -> 0
A17: LTN | B17: Thundercall | C17: 50 | D17: 22 | E17: 22 | F17: =MAX(0,E17-D17) -> 0
... A21: BLD | B21: Bloodrend | C21: 0 | D21: 0 | E21: 0 | F21: =MAX(0,E21-D21) -> 0
A22: MND | B22: Mind (highest of INT/WLL/CHA) | E22: =MAX(E9,E10,E11) -> 25
A23: BOD | B23: Body (highest of STR/FTD/AGL) | E23: =MAX(E6,E7,E8) -> 25
A24: Example values are the Iron Samurai example build.
A25: Traits (separate 12-point pool, max 6 each)
A26: Vitality | C26: 4 | D26: +10 health per point
A27: Proficiency | C27: 4 | D27: weapon scaling x(1+6.5%/pt), +2.5% weapon PEN/pt
A28: Songchant | C28: 4 | D28: mantra scaling x(1+6.5%/pt), +2.5% mantra PEN/pt
A29: Erudition | C29: 0 | D29: +30 ether, +5 tempo, +5% tempo gain per point
A30: Trait points left | C30: =Constants!$B$18-SUM(C26:C29) -> 0 | D30: must not go below 0; each trait at most 6
A32: Weapon and damage bonuses
A33: Weapon (name from the Weapons sheet) | C33: Shattered Katana | D33: pick any name in the Weapons sheet
A34: Base damage | C34: =INDEX(Weapons!$D$2:$D$232,MATCH(C33,Weapons!$A$2:$A$232,0)) -> 20
A35: Weapon PEN | C35: =INDEX(Weapons!$E$2:$E$232,MATCH(C33,Weapons!$A$2:$A$232,0)) -> 0.3
A36: Extra PEN from talents | C36: 0 | D36: sum of talent PEN (Talents sheet, PEN column)
A37: Unique damage bonus (not capped) | C37: 0 | D37: talents marked unique add outside the cap
A38: Talent damage bonus (raw sum) | C38: 0.3 | D38: sum of the Damage column of your talents
A39: Enchant hit multiplier | C39: 1 | D39: Enchants sheet: e.g. Deferred 1.07
A40: Enchant PEN | C40: 0 | D40: Enchants sheet: e.g. Sear 0.05
A41: Soulbreaker oath? (1 = yes) | C41: 0 | D41: adds +2.5% damage bonus
A42: PEN cap removed by a talent? (1 = yes) | C42: 0 | D42: some talents lift the 50% cap
A43: Talent damage bonus incl. oath | C43: =C38+Constants!$B$17*C41 -> 0.3
A44: PEN cap | C44: =IF(C42=1,1,Constants!$B$15) -> 0.5
A45: Damage bonus after soft cap | C45: =IF(C43>Constants!$B$13,MIN(Constants!$B$14,Constants!$B$13+(C43-Constants!$B$13)/2),C43) -> 0.275 | D45: full to +25%, half past it, max +50%
A46: Weapon stat scaling sum (h) | C46: =IFERROR(INDEX(Weapons!$G$2:$G$232,MATCH(C33,Weapons!$A$2:$A$232,0))*INDEX($E$6:$E$23,MATCH(INDEX(Weapons!$F$2:$F$232,MATCH(C33,Weapons!$A$2:$A$232,0)),$A$6:$A$23,0)),0)+IFERROR(INDEX(Weapons!$I$2:$I$232,MATCH(C33,Weapons!$A$2:$A$232,0))*INDEX($E$6:$E$23,MATCH(INDEX(Weapons!$H$2:$H$232,MATCH(C33,Weapons!$A$2:$A$232,0)),$A$6:$A$23,0)),0)+IFERROR(INDEX(Weapons!$K$2:$K$232,MATCH(C33,Weapons!$A$2:$A$232,0))*INDEX($E$6:$E$23,MATCH(INDEX(Weapons!$J$2:$J$232,MATCH(C33,Weapons!$A$2:$A$232,0)),$A$6:$A$23,0)),0) -> 644 | D46: sum of scaling coefficient x final stat
A47: Scaled damage | C47: =C34*(1+0.75*C46*(1+Constants!$B$23*C27)/1000) -> 32.1716 | D47: base x (1 + 0.75 x h x (1 + 6.5% x Proficiency) / 1000)
A48: PEN before cap | C48: =C35+E6/10*Constants!$B$16+C36+C40+Constants!$B$24*C27 -> 0.422 | D48: weapon PEN + Strength/10 x 1% + talents + enchant + 2.5% x Proficiency
A49: PEN used | C49: =MIN(C44,MIN(1,C48)) -> 0.422
A50: Weapon hit vs armor | C50: =C47*(1+C45+C37)*C39*(1-(1-C49)*Constants!$B$6) -> 33.906132 | D50: scaled x (1 + bonus) x enchant x (1 - (1 - PEN) x 30% armor)
A52: Mantra damage
A53: Mantra (name from the Mantras sheet) | C53: Rising Thunder | D53: pick a combat mantra
A54: Mantra level (from its attunement) | C54: =IFERROR(INDEX(Mantras!$O$2:$O$231,MATCH(C53,Mantras!$A$2:$A$231,0)),"no damage data") -> 2 | D54: level = 1 + attunement / 20 (1 to 5)
A55: Mantra hit vs armor | C55: =IFERROR(INDEX(Mantras!$P$2:$P$231,MATCH(C53,Mantras!$A$2:$A$231,0)),"no damage data") -> 41.370254 | D55: level damage x (1 + scaling x (1 + 6.5% x Songchant)) x (1 + bonus) x (1 - (1 - PEN) x 30%)
A57: Points and Power
A58: Points before the shrine | C58: =SUM(C6:C21) -> 184
A59: Power at the shrine | C59: =MAX(0,MIN(20,INT((C58-15)/15))) -> 11 | D59: Power = (points - 15) / 15, rounded down, 0 to 20
A60: Shrine of Order allowed? | C60: =IF(C59>=Constants!$B$3,"yes","no: needs Power 8 (135 points)") -> yes
A61: Shrine refund (points the shrine returns) | C61: =IF(C59>=Constants!$B$3,C58-SUM(D6:D21),0) -> 5 | D61: shrine leaves fewer points than went in; the rest come back
A62: Points added after the shrine | C62: =SUM(F6:F21) -> 141
A63: Attunement free points | C63: =MAX(0,COUNTIF(E15:E21,">0")-1) -> 1 | D63: every attunement after the first gets its first point free
A64: Points used | C64: =C58-C61+C62-C63 -> 319
A65: Points left (of 330) | C65: =Constants!$B$2-C64 -> 11
A66: Final Power | C66: =MAX(0,MIN(20,INT((C64-15)/15))) -> 20
A67: Points to next Power | C67: =IF(C66>=20,"max",15*(C66+2)-C64) -> max
A69: Talents and health
A70: Normal mantras in the build | C70: 8
A71: Talent cap | C71: =Constants!$B$28+(12-C70)*2 -> 60 | D71: 52 + (12 - normal mantras) x 2
A72: Health from equipment pips | C72: 150 | D72: Armor tab: health from pips and items
A73: Physical armor % from equipment | C73: 40 | D73: Armor tab: physical armor
A74: Health | C74: =Constants!$B$9+20*Constants!$B$10+MIN(E7,50)*Constants!$B$11+MAX(E7-50,0)*Constants!$B$12+Constants!$B$20*C26+C72 -> 502.5 | D74: 220 + 4 x Power 20 + Fortitude (0.5 each to 50, 0.25 past) + 10 x Vitality + gear
A75: Physical resistance | C75: =MIN(0.95,C73/100*(1-Constants!$B$7/100)) -> 0.26 | D75: armor % x (1 - 35% assumed penetration)
A76: Effective health vs physical | C76: =C74/(1-C75) -> 679.05405
A77: Ether from Erudition | C77: =Constants!$B$21*C29 -> 0
A78: Tempo from Erudition | C78: =Constants!$B$22*C29 -> 0

Sheet Formulas
A1: Area | B1: What | C1: How it is calculated | D1: Formula | E1: In the code
A2: Points | B2: Stat budget | C2: A Power 20 character has 330 points. Points used = points before the shrine - shrine refund + points added after - free attunement points - Shrine of Mastery refunds. | D2: used = preSum - refund + postSum - max(0, attunements-1) - mastery | E2: evaluate()
A3: Points | B3: Power | C3: Power from points invested. | D3: Power = clamp(floor((points - 15) / 15), 0, 20) | E3: powerAt()
A4: Points | B4: Next Power | C4: Points still needed for the next Power level. | D4: 15 x (Power + 2) - points used | E4: renderFinal()
A5: Points | B5: Free attunement points | C5: Every attunement after the first gets its first point free. | D5: discount = max(0, number of attunements above 0 - 1) | E5: evaluate()
A6: Shrine of Order | B6: When it can be used | C6: Only at Power 8 or higher (135 points invested before it). Below that the plan skips the shrine and the stats carry straight through. | D6: allowed = Power(preSum) >= 8 | E6: evaluate(), SHRINE_PWR
A7: Shrine of Order | B7: Averaging (deepwoken.co algorithm) | C7: Every stat above 0 is set to the average of the invested stats. No attribute may end more than 25 below its pre-shrine value: those are pinned at pre - 25 and the difference is taken evenly from the others (repeat until stable; attunements are exempt). Then values are rounded down, and leftover whole points are handed out one each to the unpinned stats while none would pass 100. Anything left is refunded. | D7: avg = sum/count; pinned k: pre_k - 25; others share the rest; floor; distribute remainder; refund = what is left | E7: shrine()
A8: Shrine of Order | B8: Pre-shrine is the peak | C8: An attribute (STR..CHA) raised above 1 before the shrine gets no points after it: either about 1 before and the rest after, or high before and the shrine brings it down. Weapon and attunement stats may be raised again (top builds do Ironsing 60 -> 80). Breaking it costs 20 points per point in the optimizer score. | D8: penalty = 20 x sum of points added after the shrine to attributes that were > 1 before | E8: evaluate() reup
A9: Shrine of Mastery | B9: Refunds | C9: Up to 3 points come off before (pre) or after (post) the Order shrine and are refunded; talents already taken stay. | D9: used -= mastery points | E9: evaluate(), masteryOf()
A10: Requirements | B10: Talent requirement options | C10: A talent can need stats (min values), "one of" groups (each option merged into the minimums, up to 16 options), combined sums (e.g. 75 combined weapon), prerequisite talents and mantras. Body = highest of STR/FTD/AGL, Mind = highest of INT/WLL/CHA, any weapon / any attunement expand into one option per stat. | D10: alternatives = expand(stats) x expand(one-of groups); each alternative = {min:{stat:value}, sum:[[stats],value]} | E10: reqAlts(), expandStats()
A11: Requirements | B11: Prerequisite chains | C11: A talent's requirement includes the stat needs of every prerequisite talent before it (merged as the highest of each stat). | D11: chain(t) = merge(req(t), chain(each prerequisite)) | E11: chainAlts(), chainStatic()
A12: Requirements | B12: Cost to meet | C12: Points needed to meet an alternative from given stats: the sum of what each minimum is short, plus what each combined sum is short. The cheapest alternative counts. | D12: cost = sum max(0, min_k - stat_k) + sum max(0, sumValue - sum of its stats); bestCost = min over alternatives | E12: altCost(), bestCost()
... A46: Import | B46: deepwoken.co | C46: deepwoken.co blocks other sites from reading its builds. The bookmark runs on the build page, reads the build there and opens Meta Builder with it in the address (#dwco=...), which imports on load. | D46: n/a | E46: DWCO_SNIP, dwbFromCoJson()

Sheet Talents
A1: Talent | B1: Category | C1: Rarity | D1: Pickable | E1: Requirement | F1: Cheapest way to meet it (with prerequisites) | G1: Points needed from 0 | H1: Can be taken before the shrine | I1: Popularity (% of top builds) | J1: Builds that can take it | K1: Builds that take it | L1: Take rate given stats | M1: Damage bonus | N1: PEN bonus | O1: Unique bonus | P1: Synergies (weight) | Q1: Exclusive with | R1: Description
A2: A World Without Song | B2: Silencer | C2: Advanced | D2: yes | E2: WND 75 · after Silencer's Blade · with prerequisites: WND 75 (Silencer's Blade) | F2: WND 75 | G2: 75 | H2: yes | I2: 0.11 | J2: 51 | K2: 43 | L2: =IF(J2>=5,K2/J2,"too few builds") -> 0.84313725 | M2: 0 | N2: 0 | R2: Every 3 hits with a Wind Mantra now procs Suffocating.
A3: Absolute Pitch | B3: Songmaster | C3: Advanced | D3: yes | E3: INT 100 | F3: INT 100 | G3: 100 | H3: yes | I3: 0.04 | J3: 32 | K3: 26 | L3: =IF(J3>=5,K3/J3,"too few builds") -> 0.8125 | M3: 0 | N3: 0 | R3: You can cast Ritual Mantras instantly.
A4: Absolute Radiance | B4: Dawnwalker | C4: Oath | D4: no | E4: after Oath: Dawnwalker | F4: none | G4: 0 | H4: no | I4: 0 | J4: 28 | K4: 12 | L4: =IF(J4>=5,K4/J4,"too few builds") -> 0.42857143 | M4: 0 | N4: 0 | R4: Dealing damage with Dawnwalker mantras briefly makes you immune to all elemental effects for a short period.
A5: Acceleration Points | B5: Jetstriker | C5: Oath | D5: no | E5: after Oath: Jetstriker | F5: none | G5: 0 | H5: no | I5: 0 | J5: 51 | K5: 20 | L5: =IF(J5>=5,K5/J5,"too few builds") -> 0.39215686 | M5: 0 | N5: 0 | R5: Striking an opponent in the back with mobility mantras or Basic Attacks now steals and grants additional momentum.
A6: Action Surge | B6: Vigil Swordsman | C6: Common | D6: yes | E6: AGL 70 | F6: AGL 70 | G6: 70 | H6: yes | I6: 0.07 | J6: 44 | K6: 23 | L6: =IF(J6>=5,K6/J6,"too few builds") -> 0.52272727 | M6: 0 | N6: 0 | R6: Adrenaline Surge now increases your swing speed by 0.04 for its duration.
A7: Adept Bloodrender | B7: Bloodrender | C7: Common | D7: no | E7: BLD 20 · after Bloodrender · with prerequisites: BLD 20 (Bloodrender) | F7: BLD 20 | G7: 20 | H7: yes | I7: 0.15 | J7: 88 | K7: 77 | L7: =IF(J7>=5,K7/J7,"too few builds") -> 0.875 | M7: 0 | N7: 0 | R7: You can now obtain 1-star Bloodrender mantras.
A8: Adept Flamecharmer | B8: Flamecharmer | C8: Common | D8: no | E8: FLM 20 · after Flamecharmer · with prerequisites: FLM 20 (Flamecharmer) | F8: FLM 20 | G8: 20 | H8: yes | I8: 0.17 | J8: 160 | K8: 81 | L8: =IF(J8>=5,K8/J8,"too few builds") -> 0.50625 | M8: 0 | N8: 0 | R8: You can now obtain 1-Star Leveled Flamecharmer Mantras.
A9: Adept Frostdrawer | B9: Frostdrawer | C9: Common | D9: no | E9: ICE 20 · after Frostdrawer · with prerequisites: ICE 20 (Frostdrawer) | F9: ICE 20 | G9: 20 | H9: yes | I9: 0.16 | J9: 112 | K9: 69 | L9: =IF(J9>=5,K9/J9,"too few builds") -> 0.61607143 | M9: 0 | N9: 0 | R9: You can now obtain 1-Star Leveled Frostdrawer Mantras.
A10: Adept Galebreather | B10: Galebreather | C10: Common | D10: no | E10: WND 20 · after Galebreather · with prerequisites: WND 20 (Galebreather) | F10: WND 20 | G10: 20 | H10: yes | I10: 0.13 | J10: 108 | K10: 49 | L10: =IF(J10>=5,K10/J10,"too few builds") -> 0.4537037 | M10: 0 | N10: 0 | R10: You can now obtain 1-Star Leveled Galebreathe mantras.
A11: Adept Ironsinger | B11: Ironsinger | C11: Common | D11: no | E11: IRN 20 · after Ironsinger · with prerequisites: IRN 20 (Ironsinger) | F11: IRN 20 | G11: 20 | H11: yes | I11: 0.14 | J11: 80 | K11: 69 | L11: =IF(J11>=5,K11/J11,"too few builds") -> 0.8625 | M11: 0 | N11: 0 | R11: You can now obtain 1-star Ironsinger mantras.
A12: Adept Shadowcaster | B12: Shadowcaster | C12: Common | D12: no | E12: SDW 20 · after Shadowcaster · with prerequisites: SDW 20 (Shadowcaster) | F12: SDW 20 | G12: 20 | H12: yes | I12: 0.1 | J12: 121 | K12: 50 | L12: =IF(J12>=5,K12/J12,"too few builds") -> 0.41322314 | M12: 0 | N12: 0 | R12: You can now obtain 1-star Leveled Shadowcaster Mantras.
A13: Adept Thundercaller | B13: Thundercaller | C13: Common | D13: no | E13: LTN 20 · after Thundercaller · with prerequisites: LTN 20 (Thundercaller) | F13: LTN 20 | G13: 20 | H13: yes | I13: 0.1 | J13: 106 | K13: 48 | L13: =IF(J13>=5,K13/J13,"too few builds") -> 0.45283019 | M13: 0 | N13: 0 | R13: You can now obtain 1-star Thundercaller mantras.
A14: Aerogliding | B14: Aeromancer | C14: Rare | D14: yes | E14: WND 35 · AGL 30 | F14: WND 35 · AGL 30 | G14: 65 | H14: yes | I14: 0.03 | J14: 54 | K14: 14 | L14: =IF(J14>=5,K14/J14,"too few builds") -> 0.25925926 | M14: 0 | N14: 0 | R14: When falling from a high place, hold space to generate wind currents until you land. More airtime with Gliders.
A15: After Cut | B15: Galeforce | C15: Common | D15: yes | E15: WND 40 | F15: WND 40 | G15: 40 | H15: yes | I15: 0.19 | J15: 100 | K15: 83 | L15: =IF(J15>=5,K15/J15,"too few builds") -> 0.83 | M15: 0.1 | N15: 0 | O15: yes | P15: Inhale (2) | R15: If an attack is physical and wind it will apply an after cut that does 5% of the damage you dealt. If an attack was a…
A16: Against All Odds | B16: Absolute Focus | C16: Common | D16: yes | E16: WLL 65 | F16: WLL 65 | G16: 65 | H16: yes | I16: 0.19 | J16: 125 | K16: 99 | L16: =IF(J16>=5,K16/J16,"too few builds") -> 0.792 | M16: 0 | N16: 0 | R16: For each combat tag you have on your character, increase your damage by 2% (max of 14%).
A17: Agility Unbounded | B17: Boundless Potential | C17: Common | D17: no | E17: AGL 75 | F17: AGL 75 | G17: 75 | H17: yes | I17: 0 | J17: 44 | K17: 12 | L17: =IF(J17>=5,K17/J17,"too few builds") -> 0.27272727 | M17: 0 | N17: 0 | R17: You have gained the ability to surpass your limits and train your agility to its fullest.
A18: Agitating Spark | B18: Immolator | C18: Common | D18: yes | E18: FLM 40 | F18: FLM 40 | G18: 40 | H18: yes | I18: 0.23 | J18: 130 | K18: 114 | L18: =IF(J18>=5,K18/J18,"too few builds") -> 0.87692308 | M18: 0 | N18: 0 | P18: Eruption Path: Lava Serpent (2) | R18: Applying Burning to enemies spreads it to anyone nearby. Including yourself.
A19: Air Pressure | B19: Legion Shock Trooper | C19: Common | D19: yes | E19: AGL 20 · WND 50 | F19: AGL 20 · WND 50 | G19: 70 | H19: yes | I19: 0.13 | J19: 71 | K19: 53 | L19: =IF(J19>=5,K19/J19,"too few builds") -> 0.74647887 | M19: 0 | N19: 0 | R19: Dodging an attack or hitting an enemy's block will transform your next dash into a Gale Dash. Gale Dashes carry you…
A20: All Above, Gods Below | B20: Heretic | C20: Advanced | D20: yes | E20: WLL 100 · INT 100 · after All the Dead Gods · with prerequisites: WLL 100 · INT 100 (All the Dead Gods) | F20: WLL 100 · INT 100 | G20: 200 | H20: yes | I20: 0 | J20: 9 | K20: 7 | L20: =IF(J20>=5,K20/J20,"too few builds") -> 0.77777778 | M20: 0 | N20: 0 | R20: Any healing your opponent were to receive while All The Dead Gods is active on them is stolen and given to you,…
A21: All Knowing | B21: Omniscient | C21: Rare | D21: yes | E21: INT 60 · mantra Prediction · with prerequisites: INT 60 (Prediction) | F21: INT 60 | G21: 60 | H21: yes | I21: 0.05 | J21: 77 | K21: 25 | L21: =IF(J21>=5,K21/J21,"too few builds") -> 0.32467532 | M21: 0 | N21: 0 | R21: Your prediction now ignores the range requirement to reflect attacks.
A22: All the Dead Gods | B22: Heretic | C22: Rare | D22: yes | E22: WLL 65 · INT 40 | F22: WLL 65 · INT 40 | G22: 105 | H22: yes | I22: 0.12 | J22: 73 | K22: 64 | L22: =IF(J22>=5,K22/J22,"too few builds") -> 0.87671233 | M22: 0 | N22: 0 | R22: Your Basic Attacks now apply anti-heal and 5% Heal Boost against PvE for 8s.
A23: All-Seeing Eye | B23: Blindseer | C23: Oath | D23: no | E23: after Oath: Blindseer | F23: none | G23: 0 | H23: no | I23: 0 | J23: 19 | K23: 3 | L23: =IF(J23>=5,K23/J23,"too few builds") -> 0.15789474 | M23: 0 | N23: 0 | R23: The mystic eye through which you now see the world can perceive the imperceptible. Invisible foes are highlighted.
A24: Alloyblood | B24: Ironsinger | C24: Advanced | D24: yes | E24: IRN 100 | F24: IRN 100 | G24: 100 | H24: yes | I24: 0.03 | J24: 17 | K24: 16 | L24: =IF(J24>=5,K24/J24,"too few builds") -> 0.94117647 | M24: 0 | N24: 0 | P24: Cauterized Wounds (2) | R24: You don't bleed like others do. Bleed damage reduced by 30%. Blood loss is reduced by 75%.
A25: Amplified Rage | B25: Jumpstarter | C25: Common | D25: yes | E25: LTN 35 · after Electrify · with prerequisites: LTN 35 (Electrify) | F25: LTN 35 | G25: 35 | H25: yes | I25: 0.09 | J25: 85 | K25: 40 | L25: =IF(J25>=5,K25/J25,"too few builds") -> 0.47058824 | M25: 0.1 | N25: 0 | Q25: Amplified Reflexes | R25: Amped now grants you an additional +10% weapon damage. Also self-damage and cooldown by 3x.
A26: Amplified Reflexes | B26: Jumpstarter | C26: Common | D26: yes | E26: LTN 35 · after Electrify · with prerequisites: LTN 35 (Electrify) | F26: LTN 35 | G26: 35 | H26: yes | I26: 0 | J26: 85 | K26: 9 | L26: =IF(J26>=5,K26/J26,"too few builds") -> 0.10588235 | M26: 0 | N26: 0 | Q26: Amplified Rage | R26: Amped now grants enhanced speed and parkour.
A27: An Ironsinger's Instinct | B27: Adaptive Arsenal | C27: Rare | D27: yes | E27: IRN 75 | F27: IRN 75 | G27: 75 | H27: yes | I27: 0.12 | J27: 66 | K27: 62 | L27: =IF(J27>=5,K27/J27,"too few builds") -> 0.93939394 | M27: 0 | N27: 0 | R27: Successfully dodging an attack coats you in metal and reduces the damage of the next attack taken.
A28: Anchor Shock | B28: Blightsurger | C28: Oath | D28: no | E28: after Oath: Blightsurger | F28: none | G28: 0 | H28: no | I28: 0 | J28: 11 | K28: 5 | L28: =IF(J28>=5,K28/J28,"too few builds") -> 0.45454545 | M28: 0 | N28: 0 | R28: Your Blightshock prevents targets from using mobility mantras.
A29: Ankle Cutter | B29: Silentheart | C29: Oath | D29: no | E29: after Oath: Silentheart | F29: none | G29: 0 | H29: no | I29: 0 | J29: 51 | K29: 20 | L29: =IF(J29>=5,K29/J29,"too few builds") -> 0.39215686 | M29: 0 | N29: 0
A30: Another Man's Trash | B30: Thief | C30: Advanced | D30: yes | E30: CHA 35 · AGL 10 · after Cap Artist, Pickpocket · with prerequisites: CHA 35 · AGL 25 (Cap Artist, Pickpocket) | F30: CHA 35 · AGL 25 | G30: 60 | H30: yes | I30: 0.04 | J30: 175 | K30: 20 | L30: =IF(J30>=5,K30/J30,"too few builds") -> 0.11428571 | M30: 0 | N30: 0
A31: Antithetic Salts | B31: Saltchemist | C31: Oath | D31: no | E31: after Oath: Saltchemist | F31: none | G31: 0 | H31: no | I31: 0 | J31: 18 | K31: 10 | L31: =IF(J31>=5,K31/J31,"too few builds") -> 0.55555556 | M31: 0 | N31: 0 | R31: Alter your brews to invert their effects. Does not count towards the ingredient limit.
A32: Apothecary | B32: Alchemist | C32: Common | D32: yes | E32: INT 10 | F32: INT 10 | G32: 10 | H32: yes | I32: 0.04 | J32: 329 | K32: 24 | L32: =IF(J32>=5,K32/J32,"too few builds") -> 0.072948328 | M32: 0 | N32: 0 | R32: Potions you prepare will have amplified positive effects when consumed, and amplified negative effects when thrown.
A33: Apparitions | B33: Specter | C33: Common | D33: yes | E33: WND 50 · after Haunted Path: Specter · with prerequisites: WND 50 (Haunted Path: Specter, Haunted Gale) | F33: WND 50 | G33: 50 | H33: yes | I33: 0.06 | J33: 90 | K33: 30 | L33: =IF(J33>=5,K33/J33,"too few builds") -> 0.33333333 | M33: 0 | N33: 0 | P33: Freezing Wight (2), Pressure Detonation (2), Haunted Gale (2), Phantom Step (2)
A34: Approaching Singularity | B34: All-Knowing | C34: Common | D34: yes | E34: INT 80 | F34: INT 80 | G34: 80 | H34: yes | I34: 0.11 | J34: 65 | K34: 59 | L34: =IF(J34>=5,K34/J34,"too few builds") -> 0.90769231 | M34: 0 | N34: 0 | R34: You now gain +1% Mantra PEN for every 10 point of Intelligence.
A35: Arc Module: Dash | B35: Arcwarder | C35: Oath | D35: no | E35: after Oath: Arcwarder | F35: none | G35: 0 | H35: no | I35: 0 | J35: 3 | K35: 1 | L35: =IF(J35>=5,K35/J35,"too few builds") -> too few builds | M35: 0 | N35: 0 | R35: [In Arc Suit] Your dashes become Jet Dashes, allowing you to attack while dashing.
A36: Arc Module: Eject | B36: Arcwarder | C36: Oath | D36: no | E36: after Oath: Arcwarder | F36: none | G36: 0 | H36: no | I36: 0 | J36: 3 | K36: 1 | L36: =IF(J36>=5,K36/J36,"too few builds") -> too few builds | M36: 0 | N36: 0 | R36: [In Arc Suit] When blockbroken, eject from your suit.
A37: Arc Module: Enhance | B37: Arcwarder | C37: Oath | D37: no | E37: after Oath: Arcwarder | F37: none | G37: 0 | H37: no | I37: 0 | J37: 3 | K37: 1 | L37: =IF(J37>=5,K37/J37,"too few builds") -> too few builds | M37: 0 | N37: 0 | R37: [In Arc Suit] Your Arcwarder Mantras deal increased damage.
A38: Arc Module: Guard | B38: Arcwarder | C38: Oath | D38: no | E38: after Oath: Arcwarder | F38: none | G38: 0 | H38: no | I38: 0 | J38: 3 | K38: 1 | L38: =IF(J38>=5,K38/J38,"too few builds") -> too few builds | M38: 0 | N38: 0 | R38: [In Arc Suit] You can block attacks from any direction and cannot be backstabbed.
A39: Arc Module: Leap | B39: Arcwarder | C39: Oath | D39: no | E39: after Oath: Arcwarder | F39: none | G39: 0 | H39: no | I39: 0 | J39: 3 | K39: 1 | L39: =IF(J39>=5,K39/J39,"too few builds") -> too few builds | M39: 0 | N39: 0 | R39: [In Arc Suit] Holding Spacebar after double jumping propels you up for a short duration.
A40: Arc Module: Null | B40: Arcwarder | C40: Oath | D40: no | E40: after Oath: Arcwarder | F40: none | G40: 0 | H40: no | I40: 0 | J40: 3 | K40: 1 | L40: =IF(J40>=5,K40/J40,"too few builds") -> too few builds | M40: 0 | N40: 0 | R40: [In Arc Suit] Outgoing and incoming enchant effects are nullified. Can be toggled with N.
A41: Ardour Scream | B41: Murmur | C41: Common | D41: yes | E41: (WLL 40 · STR 15 + Murmur: Ardour or Oath: Soulbreaker) | F41: none | G41: 0 | H41: yes | I41: 0.23 | J41: 500 | K41: 114 | L41: =IF(J41>=5,K41/J41,"too few builds") -> 0.228 | M41: 0.125 | N41: 0 | R41: Amplify your shout into a scream using Ardour, dominating weaker foes, Victims take 12.5% more damage and 50% more…
A42: Armor Conserver | B42: Natural Armor | C42: Common | D42: yes | E42: Power 8 | F42: none | G42: 0 | H42: no | I42: 0.41 | J42: 500 | K42: 196 | L42: =IF(J42>=5,K42/J42,"too few builds") -> 0.392 | M42: 0 | N42: 0 | P42: Exoskeleton (2) | R42: You lose 15% less armor when hit.
A43: Armor Piercing | B43: Gunslinger | C43: Rare | D43: yes | E43: any weapon 30 | F43: HVY 30 | G43: 30 | H43: yes | I43: 0.06 | J43: 431 | K43: 26 | L43: =IF(J43>=5,K43/J43,"too few builds") -> 0.060324826 | M43: 0 | N43: 0 | R43: [Guns] Your gun attacks now ignore 10% of an opponent's blunt armor. Applied multiplicatively before PEN is applied.
A44: Aromatic Salts | B44: Saltchemist | C44: Oath | D44: no | E44: after Oath: Saltchemist | F44: none | G44: 0 | H44: no | I44: 0 | J44: 18 | K44: 10 | L44: =IF(J44>=5,K44/J44,"too few builds") -> 0.55555556 | M44: 0 | N44: 0 | R44: Alter your brews to create lingering clouds of mist on shattering. Does not count towards the ingredient limit.
A45: Artisan Chef | B45: Tavernkeep | C45: Common | D45: yes | E45: INT 25 · CHA 15 | F45: INT 25 · CHA 15 | G45: 40 | H45: yes | I45: 0 | J45: 218 | K45: 10 | L45: =IF(J45>=5,K45/J45,"too few builds") -> 0.04587156 | M45: 0 | N45: 0 | R45: The food you cook now becomes Artisan food, increasing its hunger and thirst gained by +25%.
A46: Artisan's Blade | B46: Scrapsinger | C46: Common | D46: yes | E46: IRN 45 · after Gilded Path: Scrapsinger · with prerequisites: IRN 45 (Gilded Path: Scrapsinger) | F46: IRN 45 | G46: 45 | H46: yes | I46: 0.12 | J46: 71 | K46: 60 | L46: =IF(J46>=5,K46/J46,"too few builds") -> 0.84507042 | M46: 0 | N46: 0 | R46: Activating Scrapsinger forges a metal blade behind you for every 2 rods you consume. Metal blades will fire at a…
A47: Ash Ember | B47: Withered Flame | C47: Common | D47: yes | E47: any weapon 90 · FLM 90 | F47: HVY 90 · FLM 90 | G47: 180 | H47: yes | I47: 0 | J47: 8 | K47: 6 | L47: =IF(J47>=5,K47/J47,"too few builds") -> 0.75 | M47: 0 | N47: 0 | R47: The more wither your opponent has, the more damage your burn deals.
A48: Audacity | B48: Tyrant | C48: Advanced | D48: yes | E48: CHA 100 · STR 50 | F48: CHA 100 · STR 50 | G48: 150 | H48: yes | I48: 0 | J48: 7 | K48: 6 | L48: =IF(J48>=5,K48/J48,"too few builds") -> 0.85714286 | M48: 0 | N48: 0 | R48: Once you've brought down your prey, instill fear into all those who would separate you from claiming it. Charmed or…
A49: Authority Intimidation | B49: Authority Interrogator | C49: Common | D49: yes | E49: Power 10 · LTN 60 | F49: LTN 60 | G49: 60 | H49: yes | I49: 0.07 | J49: 46 | K49: 32 | L49: =IF(J49>=5,K49/J49,"too few builds") -> 0.69565217 | M49: 0 | N49: 0 | R49: Lightning moves slow your opponent more.
A50: Azure Flames | B50: Flamecharmer | C50: Common | D50: yes | E50: FLM 70 · WLL 40 | F50: FLM 70 · WLL 40 | G50: 110 | H50: yes | I50: 0.09 | J50: 53 | K50: 43 | L50: =IF(J50>=5,K50/J50,"too few builds") -> 0.81132075 | M50: 0 | N50: 0 | Q50: Wraith Path: Twisted Puppets | R50: Many of your flames turn blue, signifying their increased intensity.
A51: Barber's Skillset | B51: Fadetrimmer | C51: Oath | D51: no | E51: after Oath: Fadetrimmer | F51: none | G51: 0 | H51: no | I51: 0 | J51: 17 | K51: 3 | L51: =IF(J51>=5,K51/J51,"too few builds") -> 0.17647059 | M51: 0 | N51: 0 | R51: What type of look are we going for today?
A52: Battery Sapper | B52: Unstable Capacitor | C52: Common | D52: yes | E52: LTN 60 · SDW 25 · after Surge Path: Unstable Capacitor · with prerequisites: LTN 60 · SDW 25 (Surge Path: Unstable Capacitor) | F52: LTN 60 · SDW 25 | G52: 85 | H52: yes | I52: 0 | J52: 4 | K52: 2 | L52: =IF(J52>=5,K52/J52,"too few builds") -> too few builds | M52: 0 | N52: 0 | P52: Human Battery (2) | R52: If your Human Battery targets have Ether, it will drain their Ether to help pay for your Mantras.
A53: Battle Tendency | B53: Bastion | C53: Common | D53: yes | E53: FTD 15 · WLL 15 | F53: FTD 15 · WLL 15 | G53: 30 | H53: yes | I53: 0.65 | J53: 374 | K53: 321 | L53: =IF(J53>=5,K53/J53,"too few builds") -> 0.85828877 | M53: 0 | N53: 0 | R53: You can breathe more easily with +20% faster posture regen.
A54: Bear Trap | B54: Vigil Swordsman | C54: Common | D54: yes | E54: STR 20 · AGL 20 | F54: STR 20 · AGL 20 | G54: 40 | H54: yes | I54: 0.49 | J54: 324 | K54: 241 | L54: =IF(J54>=5,K54/J54,"too few builds") -> 0.74382716 | M54: 0 | N54: 0 | P54: Grounding Bolt (2) | R54: Landing a hit with your critical against an opponent makes your opponent unable to jump for a duration. Also slows…
A55: Behind You | B55: Ether Endeavours | C55: Common | D55: yes | E55: INT 70 · AGL 40 · after Keen Recovery · with prerequisites: INT 70 · AGL 40 (Keen Recovery) | F55: INT 70 · AGL 40 | G55: 110 | H55: yes | I55: 0 | J55: 23 | K55: 4 | L55: =IF(J55>=5,K55/J55,"too few builds") -> 0.17391304 | M55: 0 | N55: 0 | R55: Landing a basic attack behind your enemy after feinting a mantra will apply an ether slash, dealing extra damage based…
A56: Beiruul's Vengeance | B56: Quest | C56: Quest | D56: no | E56: no stat requirement | F56: none | G56: 0 | H56: no | I56: 0 | J56: 500 | K56: 23 | L56: =IF(J56>=5,K56/J56,"too few builds") -> 0.046 | M56: 0 | N56: 0
A57: Berserk | B57: Berserker | C57: Common | D57: yes | E57: STR 80 | F57: STR 80 | G57: 80 | H57: yes | I57: 0.11 | J57: 86 | K57: 53 | L57: =IF(J57>=5,K57/J57,"too few builds") -> 0.61627907 | M57: 0 | N57: 0 | P57: Million Ton Piercer (2) | R57: One with nothing to lose has everything to gain. Succumb to burning rage within and enter Berserk State.
A58: Biotic Salts | B58: Saltchemist | C58: Oath | D58: no | E58: after Oath: Saltchemist | F58: none | G58: 0 | H58: no | I58: 0 | J58: 18 | K58: 10 | L58: =IF(J58>=5,K58/J58,"too few builds") -> 0.55555556 | M58: 0 | N58: 0 | R58: Alter your brews to not provide their positive effects to your enemies. Does not count towards the ingredient limit.
A59: Blackhole | B59: Death Speaker | C59: Common | D59: yes | E59: Power 13 · SDW 60 · after Singularity · with prerequisites: SDW 60 (Singularity) | F59: SDW 60 | G59: 60 | H59: yes | I59: 0.04 | J59: 55 | K59: 21 | L59: =IF(J59>=5,K59/J59,"too few builds") -> 0.38181818 | M59: 0 | N59: 0 | R59: Your singularity pulls everyone nearby in.
A60: Blade Dancer | B60: Vigil Swordsman | C60: Common | D60: yes | E60: AGL 25 | F60: AGL 25 | G60: 25 | H60: yes | I60: 0.55 | J60: 409 | K60: 253 | L60: =IF(J60>=5,K60/J60,"too few builds") -> 0.61858191 | M60: 0 | N60: 0 | R60: Landing a Basic Attack removes your roll cooldown.
A61: Blade's Edge | B61: Lancer | C61: Common | D61: yes | E61: MED 30 | F61: MED 30 | G61: 30 | H61: yes | I61: 0.03 | J61: 177 | K61: 23 | L61: =IF(J61>=5,K61/J61,"too few builds") -> 0.1299435 | M61: 0 | N61: 0 | R61: [Spears] Damage dealt with the tip of the spear is increased by 10%.
A62: Blight Pierce | B62: Blightsurger | C62: Oath | D62: no | E62: after Oath: Blightsurger | F62: none | G62: 0 | H62: no | I62: 0 | J62: 11 | K62: 5 | L62: =IF(J62>=5,K62/J62,"too few builds") -> 0.45454545 | M62: 0 | N62: 0 | R62: Your Blightshock attacks pierce through your enemies hyperarmor and gain more penetration.
A63: Blighted Song | B63: Darksiphon | C63: Common | D63: yes | E63: FTD 10 · SDW 1 · mantra Shadow Chains · with prerequisites: FTD 10 · SDW 20 (Shadow Chains) | F63: FTD 10 · SDW 20 | G63: 30 | H63: yes | I63: 0 | J63: 90 | K63: 7 | L63: =IF(J63>=5,K63/J63,"too few builds") -> 0.077777778 | M63: 0 | N63: 0 | R63: Attaching your Shadow Chains to enemies disables yours and the enemy's ability to cast mantras. You take reduced…
A64: Blighted Touch | B64: Blightsurger | C64: Oath | D64: no | E64: after Oath: Blightsurger | F64: none | G64: 0 | H64: no | I64: 0 | J64: 11 | K64: 4 | L64: =IF(J64>=5,K64/J64,"too few builds") -> 0.36363636 | M64: 0 | N64: 0 | R64: Landing Basic Attacks during Sovereign State now applies Blightshock.
A65: Blightlash | B65: Blightsurger | C65: Oath | D65: no | E65: after Oath: Blightsurger | F65: none | G65: 0 | H65: no | I65: 0 | J65: 11 | K65: 4 | L65: =IF(J65>=5,K65/J65,"too few builds") -> 0.36363636 | M65: 0 | N65: 0 | R65: Your swing range is enhanced during Sovereign State.
A66: Blood Bag | B66: Quark Doctor | C66: Common | D66: yes | E66: BLD 20 | F66: BLD 20 | G66: 20 | H66: yes | I66: 0.07 | J66: 88 | K66: 31 | L66: =IF(J66>=5,K66/J66,"too few builds") -> 0.35227273 | M66: 0 | N66: 0 | R66: You receive extra blood from knocking an enemy.
A67: Blood Bank | B67: Scarlet Donor | C67: Common | D67: yes | E67: BLD 80 · CHA 40 · after Manipulator · with prerequisites: BLD 80 · CHA 60 (Manipulator, Charismatic Cast) | F67: BLD 80 · CHA 60 | G67: 140 | H67: yes | I67: 0.06 | J67: 38 | K67: 31 | L67: =IF(J67>=5,K67/J67,"too few builds") -> 0.81578947 | M67: 0 | N67: 0 | P67: Donation Drive (2) | R67: Consuming 'Charm' now gives slight temporary health.
A68: Blood Thirsty | B68: Cutthroat | C68: Common | D68: yes | E68: AGL 45 | F68: AGL 45 | G68: 45 | H68: yes | I68: 0.06 | J68: 143 | K68: 30 | L68: =IF(J68>=5,K68/J68,"too few builds") -> 0.20979021 | M68: 0 | N68: 0 | P68: Speed Emission (1.6680000000000001), Precise Swing (0.828), Matador (0.8039999999999999) | R68: Gain a speed boost after causing an opponent heavy blood loss.
A69: Blood Transfusion | B69: Quark Doctor | C69: Rare | D69: yes | E69: BLD 60 | F69: BLD 60 | G69: 60 | H69: yes | I69: 0.11 | J69: 76 | K69: 56 | L69: =IF(J69>=5,K69/J69,"too few builds") -> 0.73684211 | M69: 0 | N69: 0 | R69: Successfully landing a critical attack while under a negative status effect will transfer the effect plus recover a…
A70: Blood and Iron | B70: Bloodsong | C70: Common | D70: yes | E70: BLD 40 · IRN 40 | F70: BLD 40 · IRN 40 | G70: 80 | H70: yes | I70: 0 | J70: 10 | K70: 5 | L70: =IF(J70>=5,K70/J70,"too few builds") -> 0.5 | M70: 0 | N70: 0 | R70: Pulling rods out of your opponent now replenishes an equivalent amount of blood.
A71: Bloodiron Spirit | B71: Soul Converter | C71: Rare | D71: yes | E71: no stat requirement | F71: none | G71: 0 | H71: no | I71: 0.9 | J71: 500 | K71: 433 | L71: =IF(J71>=5,K71/J71,"too few builds") -> 0.866 | M71: 0 | N71: 0 | R71: You regain some Armor upon killing enemies.
A72: Bloodrend Unbounded | B72: Boundless Potential | C72: Common | D72: no | E72: BLD 75 · after Master Bloodrender · with prerequisites: BLD 75 (Master Bloodrender, Expert Bloodrender, Adept Bloodrender, Bloodrender) | F72: BLD 75 | G72: 75 | H72: yes | I72: 0.08 | J72: 73 | K72: 41 | L72: =IF(J72>=5,K72/J72,"too few builds") -> 0.56164384 | M72: 0 | N72: 0 | R72: You have gained the ability to surpass your limits and train your Bloodrend to its fullest.
A73: Bloodrender | B73: Bloodrender | C73: Common | D73: no | E73: BLD 1 | F73: BLD 1 | G73: 1 | H73: yes | I73: 0.15 | J73: 89 | K73: 79 | L73: =IF(J73>=5,K73/J73,"too few builds") -> 0.88764045 | M73: 0 | N73: 0 | R73: Grants you the ability to command Blood as a Bloodrender. Your Bloodrend mantras replenish your blood, steal blood and…
A74: Bloodwarden's Sense | B74: Bloodhound | C74: Common | D74: yes | E74: BLD 30 | F74: BLD 30 | G74: 30 | H74: yes | I74: 0.1 | J74: 87 | K74: 46 | L74: =IF(J74>=5,K74/J74,"too few builds") -> 0.52873563 | M74: 0 | N74: 0 | R74: Enemies you attack with a mantra above 60% Blood Poisoning are marked with Bloodwarden's Mark for 5s.
A75: Blossoming Darkness | B75: Shadowcaster | C75: Common | D75: yes | E75: SDW 40 · mantra Shadow Roar · with prerequisites: SDW 40 (Shadow Roar) | F75: SDW 40 | G75: 40 | H75: yes | I75: 0 | J75: 66 | K75: 11 | L75: =IF(J75>=5,K75/J75,"too few builds") -> 0.16666667 | M75: 0 | N75: 0 | R75: The more Ether you drain during Shadow Roar, the bigger it gets.
A76: Bodkin Arrow | B76: Greatarcher | C76: Rare | D76: yes | E76: STR 55 | F76: STR 55 | G76: 55 | H76: yes | I76: 0 | J76: 93 | K76: 2 | L76: =IF(J76>=5,K76/J76,"too few builds") -> 0.021505376 | M76: 0 | N76: 0 | R76: Your charged shots now do extra armor damage to armored enemies and extra damage to unarmored enemies.
A77: Boiling Point | B77: Vaporborne | C77: Common | D77: yes | E77: after Flashboil · no stats of its own, but its prerequisites need FLM 30 · ICE 30 (Flashboil) | F77: FLM 30 · ICE 30 | G77: 60 | H77: yes | I77: 0.03 | J77: 57 | K77: 15 | L77: =IF(J77>=5,K77/J77,"too few builds") -> 0.26315789 | M77: 0 | N77: 0 | R77: Using a fire mantra near your own steam cloud detonates it.
A78: Both Ends | B78: Vanguard Arts | C78: Common | D78: no | E78: MED 30 | F78: MED 30 | G78: 30 | H78: yes | I78: 0 | J78: 177 | K78: 0 | L78: =IF(J78>=5,K78/J78,"too few builds") -> 0 | M78: 0 | N78: 0 | P78: Counter Spin (2)
A79: Bottom Freeze | B79: Ice Age | C79: Common | D79: yes | E79: ICE 25 · mantra Ice Daggers · with prerequisites: ICE 25 (Ice Daggers) | F79: ICE 25 | G79: 25 | H79: yes | I79: 0.06 | J79: 106 | K79: 28 | L79: =IF(J79>=5,K79/J79,"too few builds") -> 0.26415094 | M79: 0 | N79: 0 | P79: Frozen Web (2), Frozen Anchor (2), Frozen Legs (0.948), Fragile Freeze (0.864) | R79: Hitting chilled enemies with Ice Projectiles while they are on ice freezes them to the ground.
A80: Braced Collapse | B80: Bastion | C80: Common | D80: yes | E80: FTD 25 | F80: FTD 25 | G80: 25 | H80: yes | I80: 0.57 | J80: 438 | K80: 276 | L80: =IF(J80>=5,K80/J80,"too few builds") -> 0.63013699 | M80: 0 | N80: 0 | R80: After being block broken, the next attack to hit you deals reduced damage.
A81: Brain Death | B81: Bloodsong | C81: Common | D81: yes | E81: BLD 40 · WND 40 | F81: BLD 40 · WND 40 | G81: 80 | H81: yes | I81: 0 | J81: 11 | K81: 3 | L81: =IF(J81>=5,K81/J81,"too few builds") -> 0.27272727 | M81: 0 | N81: 0 | R81: Enemies that are already suffocated will have their suffocation duration extended when hit by a bloodrend mantra.
A82: Brain Rattler | B82: Hammer Rage | C82: Common | D82: yes | E82: MED 50 | F82: MED 50 | G82: 50 | H82: yes | I82: 0 | J82: 137 | K82: 10 | L82: =IF(J82>=5,K82/J82,"too few builds") -> 0.072992701 | M82: 0 | N82: 0 | R82: [Clubs] Guardbreaking an opponent with your Critical rattles their brain in its container, causing increased blood…
A83: Brassneck | B83: Miscellaneous | C83: Common | D83: yes | E83: STR 30 · FTD 35 | F83: STR 30 · FTD 35 | G83: 65 | H83: yes | I83: 0.11 | J83: 264 | K83: 57 | L83: =IF(J83>=5,K83/J83,"too few builds") -> 0.21590909 | M83: 0 | N83: 0 | P83: Lose Your Mind (1.2359999999999998), Mythic Stability (1.344), Impervious Slumber (0.8999999999999999) | R83: Knocking an enemy grants you 20% damage resistance for 15 seconds.
A84: Brazen Blow | B84: Bruiser | C84: Common | D84: yes | E84: HVY 30 | F84: HVY 30 | G84: 30 | H84: yes | I84: 0.09 | J84: 147 | K84: 42 | L84: =IF(J84>=5,K84/J84,"too few builds") -> 0.28571429 | M84: 0 | N84: 0 | P84: Knight's Rally (1.008), Turtle Shell (1.02), Grasp on Reality (0.996) | R84: [Greataxes] Attacking an enemy slowed by your Greataxe grants you temporary hyperarmor.
A85: Breathing Exercise | B85: Mental Fortress | C85: Common | D85: yes | E85: WLL 5 | F85: WLL 5 | G85: 5 | H85: yes | I85: 0.78 | J85: 436 | K85: 381 | L85: =IF(J85>=5,K85/J85,"too few builds") -> 0.87385321 | M85: 0 | N85: 0 | R85: Your sanity recovers more quickly once out of terrifying situations.
A86: Breathing Impact | B86: Galeforce | C86: Common | D86: yes | E86: WND 30 | F86: WND 30 | G86: 30 | H86: yes | I86: 0.09 | J86: 106 | K86: 34 | L86: =IF(J86>=5,K86/J86,"too few builds") -> 0.32075472 | M86: 0 | N86: 0 | R86: Knocking enemies into objects with wind spells deals additional blunt damage based on how hard they're hit.
A87: Brick Wall | B87: Human Architecture | C87: Advanced | D87: yes | E87: WLL 100 · FTD 100 · after Perseverance · with prerequisites: WLL 100 · FTD 100 (Perseverance) | F87: WLL 100 · FTD 100 | G87: 200 | H87: yes | I87: 0.09 | J87: 39 | K87: 39 | L87: =IF(J87>=5,K87/J87,"too few builds") -> 1 | M87: 0 | N87: 0 | R87: You refuse. You cannot be knocked off your feet until you are knocked completely Unconscious. Also reduces the…
A88: Broken Ankles | B88: Raging Bull | C88: Common | D88: yes | E88: STR 70 | F88: STR 70 | G88: 70 | H88: yes | I88: 0.11 | J88: 88 | K88: 55 | L88: =IF(J88>=5,K88/J88,"too few builds") -> 0.625 | M88: 0 | N88: 0 | R88: Blockbreaking an opponent puts their Mobility slot Mantras on CD for 12s.
A89: Bruiser's Mixup | B89: Brawler | C89: Common | D89: yes | E89: no stat requirement | F89: none | G89: 0 | H89: no | I89: 0 | J89: 500 | K89: 12 | L89: =IF(J89>=5,K89/J89,"too few builds") -> 0.024 | M89: 0 | N89: 0 | R89: Switching your Fist Style mid-fight makes your basic Fist attacks inflict bleed temporarily.
A90: Brutal Momentum | B90: Weapon Master | C90: Common | D90: yes | E90: HVY 50 | F90: HVY 50 | G90: 50 | H90: yes | I90: 0.19 | J90: 127 | K90: 85 | L90: =IF(J90>=5,K90/J90,"too few builds") -> 0.66929134 | M90: 0 | N90: 0 | R90: [Heavy Weapons] Successfully dodging will give you hyperarmour on your next swing.
A91: Bulldozer | B91: Raging Bull | C91: Rare | D91: yes | E91: STR 25 | F91: STR 25 | G91: 25 | H91: yes | I91: 0.42 | J91: 349 | K91: 197 | L91: =IF(J91>=5,K91/J91,"too few builds") -> 0.56446991 | M91: 0 | N91: 0 | Q91: Dazing Finisher | R91: Enemies you flourish into a wall have a chance of breaking the wall and are guard broken on impact.
A92: Bulletproof | B92: Gunslinger | C92: Common | D92: yes | E92: (FTD 20 or any weapon 20) | F92: FTD 20 | G92: 20 | H92: yes | I92: 0 | J92: 498 | K92: 10 | L92: =IF(J92>=5,K92/J92,"too few builds") -> 0.020080321 | M92: 0 | N92: 0
A93: Burning Puppets | B93: Twisted Puppets | C93: Common | D93: yes | E93: FLM 40 · SDW 40 · after Wraith Path: Twisted Puppets · with prerequisites: FLM 40 · SDW 40 (Wraith Path: Twisted Puppets) | F93: FLM 40 · SDW 40 | G93: 80 | H93: yes | I93: 0.03 | J93: 23 | K93: 18 | L93: =IF(J93>=5,K93/J93,"too few builds") -> 0.7826087 | M93: 0 | N93: 0 | R93: Your puppets can now inflict burn and fire-based Talents when they explode.
A94: Burning Sacrifice | B94: Twisted Puppets | C94: Rare | D94: yes | E94: FLM 40 · SDW 40 · after Wraith Path: Twisted Puppets, Emperor Flame · with prerequisites: FLM 60 · SDW 40 (Wraith Path: Twisted Puppets, Emperor Flame, Agitating Spark) | F94: FLM 60 · SDW 40 | G94: 100 | H94: yes | I94: 0 | J94: 11 | K94: 3 | L94: =IF(J94>=5,K94/J94,"too few builds") -> 0.27272727 | M94: 0 | N94: 0 | R94: Sacrifice puppets who have been alive for half of their lifetime and burn purple for Emperor Flame Stacks, a damage…
A95: Callout | B95: Leader | C95: Common | D95: yes | E95: CHA 20 | F95: CHA 20 | G95: 20 | H95: yes | I95: 0 | J95: 348 | K95: 12 | L95: =IF(J95>=5,K95/J95,"too few builds") -> 0.034482759 | M95: 0 | N95: 0 | P95: Spotter (2) | R95: You can mark objects or enemies by pressing Z, which will mark them for all nearby allies.
A96: Cap Artist | B96: Thief | C96: Common | D96: yes | E96: AGL 25 · CHA 5 | F96: AGL 25 · CHA 5 | G96: 30 | H96: yes | I96: 0.04 | J96: 288 | K96: 22 | L96: =IF(J96>=5,K96/J96,"too few builds") -> 0.076388889 | M96: 0 | N96: 0 | P96: Kickstart (2) | R96: Pressing CapArtist while crouching allows you to fake being dead. You also take a bit less damage from PvE while ragdolled as well.
A97: Captain Etrea | B97: Navaen Nomad | C97: Common | D97: yes | E97: STR 30 · FTD 20 · after Moving Fortress · with prerequisites: STR 30 · FTD 20 (Moving Fortress) | F97: STR 30 · FTD 20 | G97: 50 | H97: yes | I97: 0 | J97: 271 | K97: 9 | L97: =IF(J97>=5,K97/J97,"too few builds") -> 0.033210332 | M97: 0 | N97: 0 | R97: [Fists] Moving while blocking with a shield no longer slows you down.
A98: Careful Handling | B98: Miscellaneous | C98: Quest | D98: no | E98: no stat requirement | F98: none | G98: 0 | H98: no | I98: 0 | J98: 500 | K98: 6 | L98: =IF(J98>=5,K98/J98,"too few builds") -> 0.012 | M98: 0 | N98: 0 | R98: Reduce your chances of dropping ingredients on death.
A99: Carnivore | B99: Apex Predator | C99: Rare | D99: yes | E99: STR 5 · WLL 5 | F99: STR 5 · WLL 5 | G99: 10 | H99: yes | I99: 0.4 | J99: 381 | K99: 187 | L99: =IF(J99>=5,K99/J99,"too few builds") -> 0.49081365 | M99: 0 | N99: 0 | Q99: Flaw: Vegetarian | R99: In return for losing the ability to eat vegetation, satiate your hunger by killing others.
A100: Catalytic Strike | B100: Unstable Capacitor | C100: Common | D100: yes | E100: LTN 50 · after Surge Path: Unstable Capacitor · with prerequisites: LTN 50 (Surge Path: Unstable Capacitor) | F100: LTN 50 | G100: 50 | H100: yes | I100: 0.07 | J100: 74 | K100: 28 | L100: =IF(J100>=5,K100/J100,"too few builds") -> 0.37837838 | M100: 0 | N100: 0 | R100: Posture breaking an enemy will Overload their Surge stack.
...

Sheet Mantras
A1: Mantra | B1: Attunement | C1: Category | D1: Type | E1: Requirement | F1: Scale stat 1 | G1: Coef 1 | H1: Scale stat 2 | I1: Coef 2 | J1: Lv1 | K1: Lv2 | L1: Lv3 | M1: Lv4 | N1: Lv5 | O1: Level with Calculator stats | P1: Hit with Calculator stats
A2: Abyssal Ridge | B2: Monster | C2: Combat | D2: M | E2: no stat requirement | G2: 0 | I2: 0
A3: Abyssal Tendrils | B3: Monster | C3: Combat | D3: M | E3: no stat requirement | G3: 0 | I3: 0
A4: Adrenaline Surge | B4: AGL | C4: Support | D4: N | E4: AGL 20 | G4: 0 | I4: 0
A5: Agile Dash | B5: AGL | C5: Mobility | D5: N | E5: AGL 40 | G5: 0 | I5: 0
A6: Air Force | B6: WND | C6: Combat | D6: N | E6: WND 1 | F6: WND | G6: 2.75 | I6: 0 | J6: 22 | K6: 24.4 | L6: 26.8 | M6: 29.2 | N6: 31.6 | O6: =MAX(1,MIN(5,1+INT(IFERROR(INDEX(Calculator!$E$6:$E$23,MATCH("WND",Calculator!$A$6:$A$23,0)),0)/20))) -> 1 | P6: =INDEX(J6:N6,O6)*(1+(IFERROR(G6/10*INDEX(Calculator!$E$6:$E$23,MATCH(F6,Calculator!$A$6:$A$23,0))/100,0)+IFERROR(I6/10*INDEX(Calculator!$E$6:$E$23,MATCH(H6,Calculator!$A$6:$A$23,0))/100,0))*(1+Constants!$B$25*Calculator!$C$28))*(1+Calculator!$C$45)*(1-(1-MIN(0.5,Constants!$B$26*Calculator!$C$28))*Constants!$B$6) -> 20.4765
A7: Arc Beam | B7: Oath: Arcwarder | C7: Combat | D7: O | E7: after Oath: Arcwarder | G7: 0 | I7: 0
A8: Arc Suit | B8: Oath: Arcwarder | C8: Support | D8: O | E8: after Oath: Arcwarder | G8: 0 | I8: 0
A9: Arc Wave | B9: Oath: Arcwarder | C9: Combat | D9: O | E9: after Oath: Arcwarder | G9: 0 | I9: 0
A10: Ardour Slicer | B10: Oath: Soulbreaker | C10: Combat | D10: O | E10: after Oath: Soulbreaker | G10: 0 | I10: 0
A11: Ascension | B11: Oath: Starkindred | C11: Combat | D11: O | E11: after Oath: Starkindred | G11: 0 | I11: 0
A12: Ash Slam | B12: FLM + STR | C12: Combat | D12: N | E12: FLM 50 · STR 20 | F12: FLM | G12: 2.75 | I12: 0 | J12: 16 | K12: 22.4 | L12: 28.8 | M12: 35.2 | N12: 41.6 | O12: =MAX(1,MIN(5,1+INT(IFERROR(INDEX(Calculator!$E$6:$E$23,MATCH("FLM",Calculator!$A$6:$A$23,0)),0)/20))) -> 1 | P12: =INDEX(J12:N12,O12)*(1+(IFERROR(G12/10*INDEX(Calculator!$E$6:$E$23,MATCH(F12,Calculator!$A$6:$A$23,0))/100,0)+IFERROR(I12/10*INDEX(Calculator!$E$6:$E$23,MATCH(H12,Calculator!$A$6:$A$23,0))/100,0))*(1+Constants!$B$25*Calculator!$C$28))*(1+Calculator!$C$45)*(1-(1-MIN(0.5,Constants!$B$26*Calculator!$C$28))*Constants!$B$6) -> 14.892
A13: Astral Wind | B13: WND | C13: Combat | D13: N | E13: WND 50 | F13: WND | G13: 2.75 | I13: 0 | J13: 21.25 | K13: 26.75 | L13: 32.25 | M13: 37.75 | N13: 43.25 | O13: =MAX(1,MIN(5,1+INT(IFERROR(INDEX(Calculator!$E$6:$E$23,MATCH("WND",Calculator!$A$6:$A$23,0)),0)/20))) -> 1 | P13: =INDEX(J13:N13,O13)*(1+(IFERROR(G13/10*INDEX(Calculator!$E$6:$E$23,MATCH(F13,Calculator!$A$6:$A$23,0))/100,0)+IFERROR(I13/10*INDEX(Calculator!$E$6:$E$23,MATCH(H13,Calculator!$A$6:$A$23,0))/100,0))*(1+Constants!$B$25*Calculator!$C$28))*(1+Calculator!$C$45)*(1-(1-MIN(0.5,Constants!$B$26*Calculator!$C$28))*Constants!$B$6) -> 19.778437
A14: Beast Burrow | B14: Monster | C14: Mobility | D14: M | E14: no stat requirement | G14: 0 | I14: 0
A15: Blade of Saints | B15: Oath: Saintsworn | C15: Combat | D15: O | E15: after Oath: Saintsworn | G15: 0 | I15: 0
A16: Blinding Dawn | B16: Oath: Dawnwalker | C16: Combat | D16: O | E16: after Oath: Dawnwalker | G16: 0 | I16: 0
A17: Blood Orb | B17: BLD | C17: Combat | D17: N | E17: BLD 1 | F17: BLD | G17: 2.75 | I17: 0 | J17: 14.5 | K17: 19 | L17: 23.5 | M17: 28 | N17: 32.5 | O17: =MAX(1,MIN(5,1+INT(IFERROR(INDEX(Calculator!$E$6:$E$23,MATCH("BLD",Calculator!$A$6:$A$23,0)),0)/20))) -> 1 | P17: =INDEX(J17:N17,O17)*(1+(IFERROR(G17/10*INDEX(Calculator!$E$6:$E$23,MATCH(F17,Calculator!$A$6:$A$23,0))/100,0)+IFERROR(I17/10*INDEX(Calculator!$E$6:$E$23,MATCH(H17,Calculator!$A$6:$A$23,0))/100,0))*(1+Constants!$B$25*Calculator!$C$28))*(1+Calculator!$C$45)*(1-(1-MIN(0.5,Constants!$B$26*Calculator!$C$28))*Constants!$B$6) -> 13.495875
A18: Blood Stakes | B18: BLD | C18: Combat | D18: N | E18: BLD 20 | F18: BLD | G18: 2.75 | I18: 0 | J18: 25 | K18: 36 | L18: 49 | M18: 64 | N18: 81 | O18: =MAX(1,MIN(5,1+INT(IFERROR(INDEX(Calculator!$E$6:$E$23,MATCH("BLD",Calculator!$A$6:$A$23,0)),0)/20))) -> 1 | P18: =INDEX(J18:N18,O18)*(1+(IFERROR(G18/10*INDEX(Calculator!$E$6:$E$23,MATCH(F18,Calculator!$A$6:$A$23,0))/100,0)+IFERROR(I18/10*INDEX(Calculator!$E$6:$E$23,MATCH(H18,Calculator!$A$6:$A$23,0))/100,0))*(1+Constants!$B$25*Calculator!$C$28))*(1+Calculator!$C$45)*(1-(1-MIN(0.5,Constants!$B$26*Calculator!$C$28))*Constants!$B$6) -> 23.26875
A19: Blood Wisp | B19: BLD | C19: Wildcard | D19: N | E19: BLD 30 | G19: 0 | I19: 0
A20: Bloodcurdle | B20: BLD | C20: Combat | D20: N | E20: BLD 50 | F20: BLD | G20: 2.75 | I20: 0 | J20: 17.4 | K20: 23.8 | L20: 31.2 | M20: 39.6 | N20: 49 | O20: =MAX(1,MIN(5,1+INT(IFERROR(INDEX(Calculator!$E$6:$E$23,MATCH("BLD",Calculator!$A$6:$A$23,0)),0)/20))) -> 1 | P20: =INDEX(J20:N20,O20)*(1+(IFERROR(G20/10*INDEX(Calculator!$E$6:$E$23,MATCH(F20,Calculator!$A$6:$A$23,0))/100,0)+IFERROR(I20/10*INDEX(Calculator!$E$6:$E$23,MATCH(H20,Calculator!$A$6:$A$23,0))/100,0))*(1+Constants!$B$25*Calculator!$C$28))*(1+Calculator!$C$45)*(1-(1-MIN(0.5,Constants!$B$26*Calculator!$C$28))*Constants!$B$6) -> 16.19505
A21: Bloodedge | B21: BLD | C21: Combat | D21: N | E21: BLD 20 | F21: BLD | G21: 2.75 | I21: 0 | J21: 16 | K21: 20 | L21: 24 | M21: 28 | N21: 32 | O21: =MAX(1,MIN(5,1+INT(IFERROR(INDEX(Calculator!$E$6:$E$23,MATCH("BLD",Calculator!$A$6:$A$23,0)),0)/20))) -> 1 | P21: =INDEX(J21:N21,O21)*(1+(IFERROR(G21/10*INDEX(Calculator!$E$6:$E$23,MATCH(F21,Calculator!$A$6:$A$23,0))/100,0)+IFERROR(I21/10*INDEX(Calculator!$E$6:$E$23,MATCH(H21,Calculator!$A$6:$A$23,0))/100,0))*(1+Constants!$B$25*Calculator!$C$28))*(1+Calculator!$C$45)*(1-(1-MIN(0.5,Constants!$B$26*Calculator!$C$28))*Constants!$B$6) -> 14.892
A22: Bloodtide Ritual | B22: BLD | C22: Combat | D22: N | E22: BLD 50 | F22: BLD | G22: 2.75 | I22: 0 | J22: 42 | K22: 47 | L22: 52 | M22: 57 | N22: 62 | O22: =MAX(1,MIN(5,1+INT(IFERROR(INDEX(Calculator!$E$6:$E$23,MATCH("BLD",Calculator!$A$6:$A$23,0)),0)/20))) -> 1 | P22: =INDEX(J22:N22,O22)*(1+(IFERROR(G22/10*INDEX(Calculator!$E$6:$E$23,MATCH(F22,Calculator!$A$6:$A$23,0))/100,0)+IFERROR(I22/10*INDEX(Calculator!$E$6:$E$23,MATCH(H22,Calculator!$A$6:$A$23,0))/100,0))*(1+Constants!$B$25*Calculator!$C$28))*(1+Calculator!$C$45)*(1-(1-MIN(0.5,Constants!$B$26*Calculator!$C$28))*Constants!$B$6) -> 39.0915
A23: Bolt Piercer | B23: LTN | C23: Combat | D23: N | E23: LTN 30 | F23: LTN | G23: 2.75 | I23: 0 | J23: 15 | K23: 16 | L23: 17 | M23: 18 | N23: 19 | O23: =MAX(1,MIN(5,1+INT(IFERROR(INDEX(Calculator!$E$6:$E$23,MATCH("LTN",Calculator!$A$6:$A$23,0)),0)/20))) -> 2 | P23: =INDEX(J23:N23,O23)*(1+(IFERROR(G23/10*INDEX(Calculator!$E$6:$E$23,MATCH(F23,Calculator!$A$6:$A$23,0))/100,0)+IFERROR(I23/10*INDEX(Calculator!$E$6:$E$23,MATCH(H23,Calculator!$A$6:$A$23,0))/100,0))*(1+Constants!$B$25*Calculator!$C$28))*(1+Calculator!$C$45)*(1-(1-MIN(0.5,Constants!$B$26*Calculator!$C$28))*Constants!$B$6) -> 16.027217
A24: Bone Wisp | B24: Monster | C24: Wildcard | D24: M | E24: no stat requirement | G24: 0 | I24: 0
A25: Brace | B25: FTD | C25: Support | D25: N | E25: FTD 75 | G25: 0 | I25: 0
A26: Brachial Spear | B26: Monster | C26: Combat | D26: M | E26: no stat requirement | G26: 0 | I26: 0
A27: Burning Servants | B27: FLM | C27: Combat | D27: N | E27: FLM 1 | F27: FLM | G27: 2.75 | I27: 0 | J27: 44 | K27: 48.4 | L27: 52.8 | M27: 57.2 | N27: 61.6 | O27: =MAX(1,MIN(5,1+INT(IFERROR(INDEX(Calculator!$E$6:$E$23,MATCH("FLM",Calculator!$A$6:$A$23,0)),0)/20))) -> 1 | P27: =INDEX(J27:N27,O27)*(1+(IFERROR(G27/10*INDEX(Calculator!$E$6:$E$23,MATCH(F27,Calculator!$A$6:$A$23,0))/100,0)+IFERROR(I27/10*INDEX(Calculator!$E$6:$E$23,MATCH(H27,Calculator!$A$6:$A$23,0))/100,0))*(1+Constants!$B$25*Calculator!$C$28))*(1+Calculator!$C$45)*(1-(1-MIN(0.5,Constants!$B$26*Calculator!$C$28))*Constants!$B$6) -> 40.953
A28: Caltrops | B28: IRN | C28: Combat | D28: N | E28: IRN 30 | F28: IRN | G28: 2.75 | I28: 0 | J28: 32 | K28: 29.9 | L28: 33.8 | M28: 37.7 | N28: 41.6 | O28: =MAX(1,MIN(5,1+INT(IFERROR(INDEX(Calculator!$E$6:$E$23,MATCH("IRN",Calculator!$A$6:$A$23,0)),0)/20))) -> 5 | P28: =INDEX(J28:N28,O28)*(1+(IFERROR(G28/10*INDEX(Calculator!$E$6:$E$23,MATCH(F28,Calculator!$A$6:$A$23,0))/100,0)+IFERROR(I28/10*INDEX(Calculator!$E$6:$E$23,MATCH(H28,Calculator!$A$6:$A$23,0))/100,0))*(1+Constants!$B$25*Calculator!$C$28))*(1+Calculator!$C$45)*(1-(1-MIN(0.5,Constants!$B$26*Calculator!$C$28))*Constants!$B$6) -> 50.793783
A29: Ceaseless Slashes | B29: LHT | C29: Combat | D29: N | E29: LHT 50 | G29: 0 | I29: 0
A30: Celestial Assault | B30: Oath: Starkindred | C30: Combat | D30: O | E30: after Oath: Starkindred | G30: 0 | I30: 0
A31: Chain Pull | B31: IRN | C31: Support | D31: N | E31: IRN 20 | F31: IRN | G31: 2.75 | I31: 0 | J31: 20 | K31: 22 | L31: 24 | M31: 26 | N31: 28 | O31: =MAX(1,MIN(5,1+INT(IFERROR(INDEX(Calculator!$E$6:$E$23,MATCH("IRN",Calculator!$A$6:$A$23,0)),0)/20))) -> 5 | P31: =INDEX(J31:N31,O31)*(1+(IFERROR(G31/10*INDEX(Calculator!$E$6:$E$23,MATCH(F31,Calculator!$A$6:$A$23,0))/100,0)+IFERROR(I31/10*INDEX(Calculator!$E$6:$E$23,MATCH(H31,Calculator!$A$6:$A$23,0))/100,0))*(1+Constants!$B$25*Calculator!$C$28))*(1+Calculator!$C$45)*(1-(1-MIN(0.5,Constants!$B$26*Calculator!$C$28))*Constants!$B$6) -> 34.188123
A32: Champion's Whirlthrow | B32: WND | C32: Combat | D32: N | E32: WND 30 | F32: WND | G32: 2.75 | I32: 0 | J32: 41 | K32: 46 | L32: 51 | M32: 56 | N32: 61 | O32: =MAX(1,MIN(5,1+INT(IFERROR(INDEX(Calculator!$E$6:$E$23,MATCH("WND",Calculator!$A$6:$A$23,0)),0)/20))) -> 1 | P32: =INDEX(J32:N32,O32)*(1+(IFERROR(G32/10*INDEX(Calculator!$E$6:$E$23,MATCH(F32,Calculator!$A$6:$A$23,0))/100,0)+IFERROR(I32/10*INDEX(Calculator!$E$6:$E$23,MATCH(H32,Calculator!$A$6:$A$23,0))/100,0))*(1+Constants!$B$25*Calculator!$C$28))*(1+Calculator!$C$45)*(1-(1-MIN(0.5,Constants!$B$26*Calculator!$C$28))*Constants!$B$6) -> 38.16075
A33: Close Shave | B33: Oath: Fadetrimmer | C33: Combat | D33: O | E33: after Oath: Fadetrimmer | G33: 0 | I33: 0
A34: Clutching Shadow | B34: SDW | C34: Combat | D34: N | E34: SDW 1 | F34: SDW | G34: 2.75 | I34: 0 | J34: 24 | K34: 28.2 | L34: 32.4 | M34: 36.6 | N34: 40.8 | O34: =MAX(1,MIN(5,1+INT(IFERROR(INDEX(Calculator!$E$6:$E$23,MATCH("SDW",Calculator!$A$6:$A$23,0)),0)/20))) -> 1 | P34: =INDEX(J34:N34,O34)*(1+(IFERROR(G34/10*INDEX(Calculator!$E$6:$E$23,MATCH(F34,Calculator!$A$6:$A$23,0))/100,0)+IFERROR(I34/10*INDEX(Calculator!$E$6:$E$23,MATCH(H34,Calculator!$A$6:$A$23,0))/100,0))*(1+Constants!$B$25*Calculator!$C$28))*(1+Calculator!$C$45)*(1-(1-MIN(0.5,Constants!$B$26*Calculator!$C$28))*Constants!$B$6) -> 22.338
A35: Coral Burst | B35: Monster | C35: Combat | D35: M | E35: no stat requirement | G35: 0 | I35: 0
A36: Crimson Rain | B36: BLD | C36: Combat | D36: N | E36: BLD 30 | F36: BLD | G36: 2.75 | I36: 0 | J36: 14.25 | K36: 16.5 | L36: 18.75 | M36: 21 | N36: 46.5 | O36: =MAX(1,MIN(5,1+INT(IFERROR(INDEX(Calculator!$E$6:$E$23,MATCH("BLD",Calculator!$A$6:$A$23,0)),0)/20))) -> 1 | P36: =INDEX(J36:N36,O36)*(1+(IFERROR(G36/10*INDEX(Calculator!$E$6:$E$23,MATCH(F36,Calculator!$A$6:$A$23,0))/100,0)+IFERROR(I36/10*INDEX(Calculator!$E$6:$E$23,MATCH(H36,Calculator!$A$6:$A$23,0))/100,0))*(1+Constants!$B$25*Calculator!$C$28))*(1+Calculator!$C$45)*(1-(1-MIN(0.5,Constants!$B$26*Calculator!$C$28))*Constants!$B$6) -> 13.263188
A37: Crimson Surge | B37: BLD | C37: Combat | D37: N | E37: BLD 30 | F37: BLD | G37: 2.75 | I37: 0 | J37: 24 | K37: 30 | L37: 36 | M37: 42 | N37: 48 | O37: =MAX(1,MIN(5,1+INT(IFERROR(INDEX(Calculator!$E$6:$E$23,MATCH("BLD",Calculator!$A$6:$A$23,0)),0)/20))) -> 1 | P37: =INDEX(J37:N37,O37)*(1+(IFERROR(G37/10*INDEX(Calculator!$E$6:$E$23,MATCH(F37,Calculator!$A$6:$A$23,0))/100,0)+IFERROR(I37/10*INDEX(Calculator!$E$6:$E$23,MATCH(H37,Calculator!$A$6:$A$23,0))/100,0))*(1+Constants!$B$25*Calculator!$C$28))*(1+Calculator!$C$45)*(1-(1-MIN(0.5,Constants!$B$26*Calculator!$C$28))*Constants!$B$6) -> 22.338
A38: Crucifixion | B38: BLD | C38: Combat | D38: N | E38: BLD 1 | F38: BLD | G38: 2.75 | I38: 0 | J38: 16 | K38: 22 | L38: 28 | M38: 34 | N38: 40 | O38: =MAX(1,MIN(5,1+INT(IFERROR(INDEX(Calculator!$E$6:$E$23,MATCH("BLD",Calculator!$A$6:$A$23,0)),0)/20))) -> 1 | P38: =INDEX(J38:N38,O38)*(1+(IFERROR(G38/10*INDEX(Calculator!$E$6:$E$23,MATCH(F38,Calculator!$A$6:$A$23,0))/100,0)+IFERROR(I38/10*INDEX(Calculator!$E$6:$E$23,MATCH(H38,Calculator!$A$6:$A$23,0))/100,0))*(1+Constants!$B$25*Calculator!$C$28))*(1+Calculator!$C$45)*(1-(1-MIN(0.5,Constants!$B$26*Calculator!$C$28))*Constants!$B$6) -> 14.892
A39: Crystal Impale | B39: ICE | C39: Combat | D39: N | E39: ICE 30 · after Glass Path: Crystallization | F39: ICE | G39: 2.75 | I39: 0 | J39: 23.3 | K39: 28.3 | L39: 33.3 | M39: 38.3 | N39: 43.3 | O39: =MAX(1,MIN(5,1+INT(IFERROR(INDEX(Calculator!$E$6:$E$23,MATCH("ICE",Calculator!$A$6:$A$23,0)),0)/20))) -> 1 | P39: =INDEX(J39:N39,O39)*(1+(IFERROR(G39/10*INDEX(Calculator!$E$6:$E$23,MATCH(F39,Calculator!$A$6:$A$23,0))/100,0)+IFERROR(I39/10*INDEX(Calculator!$E$6:$E$23,MATCH(H39,Calculator!$A$6:$A$23,0))/100,0))*(1+Constants!$B$25*Calculator!$C$28))*(1+Calculator!$C$45)*(1-(1-MIN(0.5,Constants!$B$26*Calculator!$C$28))*Constants!$B$6) -> 21.686475
A40: Crystal Knee | B40: ICE | C40: Combat | D40: N | E40: ICE 30 · after Glass Path: Crystallization | F40: ICE | G40: 2.75 | I40: 0 | J40: 35 | K40: 38 | L40: 41 | M40: 44 | N40: 47 | O40: =MAX(1,MIN(5,1+INT(IFERROR(INDEX(Calculator!$E$6:$E$23,MATCH("ICE",Calculator!$A$6:$A$23,0)),0)/20))) -> 1 | P40: =INDEX(J40:N40,O40)*(1+(IFERROR(G40/10*INDEX(Calculator!$E$6:$E$23,MATCH(F40,Calculator!$A$6:$A$23,0))/100,0)+IFERROR(I40/10*INDEX(Calculator!$E$6:$E$23,MATCH(H40,Calculator!$A$6:$A$23,0))/100,0))*(1+Constants!$B$25*Calculator!$C$28))*(1+Calculator!$C$45)*(1-(1-MIN(0.5,Constants!$B$26*Calculator!$C$28))*Constants!$B$6) -> 32.57625
A41: Dark Blade | B41: SDW | C41: Combat | D41: N | E41: SDW 1 | F41: SDW | G41: 2.75 | I41: 0 | J41: 30 | K41: 34.5 | L41: 39 | M41: 43.5 | N41: 48 | O41: =MAX(1,MIN(5,1+INT(IFERROR(INDEX(Calculator!$E$6:$E$23,MATCH("SDW",Calculator!$A$6:$A$23,0)),0)/20))) -> 1 | P41: =INDEX(J41:N41,O41)*(1+(IFERROR(G41/10*INDEX(Calculator!$E$6:$E$23,MATCH(F41,Calculator!$A$6:$A$23,0))/100,0)+IFERROR(I41/10*INDEX(Calculator!$E$6:$E$23,MATCH(H41,Calculator!$A$6:$A$23,0))/100,0))*(1+Constants!$B$25*Calculator!$C$28))*(1+Calculator!$C$45)*(1-(1-MIN(0.5,Constants!$B$26*Calculator!$C$28))*Constants!$B$6) -> 27.9225
A42: Decimate | B42: Oath: Bladeharper | C42: Combat | D42: O | E42: after Oath: Bladeharper | G42: 0 | I42: 0
A43: Devouring Eye | B43: SDW | C43: Support | D43: N | E43: SDW 30 | G43: 0 | I43: 0
A44: Disguise | B44: CHA | C44: Support | D44: M | E44: CHA 20 | G44: 0 | I44: 0
A45: Dread Breath | B45: Monster | C45: Combat | D45: M | E45: no stat requirement | G45: 0 | I45: 0
A46: Dread Whisper | B46: CHA | C46: Support | D46: N | E46: CHA 50 | F46: CHA | G46: 1.65 | I46: 0 | J46: 10 | K46: 12 | L46: 14 | M46: 16 | N46: 18 | O46: =MAX(1,MIN(5,1+INT(IFERROR(INDEX(Calculator!$E$6:$E$23,MATCH("CHA",Calculator!$A$6:$A$23,0)),0)/20))) -> 2 | P46: =INDEX(J46:N46,O46)*(1+(IFERROR(G46/10*INDEX(Calculator!$E$6:$E$23,MATCH(F46,Calculator!$A$6:$A$23,0))/100,0)+IFERROR(I46/10*INDEX(Calculator!$E$6:$E$23,MATCH(H46,Calculator!$A$6:$A$23,0))/100,0))*(1+Constants!$B$25*Calculator!$C$28))*(1+Calculator!$C$45)*(1-(1-MIN(0.5,Constants!$B$26*Calculator!$C$28))*Constants!$B$6) -> 11.749509
A47: Eclipse Kick | B47: SDW + STR | C47: Combat | D47: N | E47: SDW 50 · STR 15 | F47: SDW | G47: 2.75 | I47: 0 | J47: 65 | K47: 77.5 | L47: 90 | M47: 102.5 | N47: 115 | O47: =MAX(1,MIN(5,1+INT(IFERROR(INDEX(Calculator!$E$6:$E$23,MATCH("SDW",Calculator!$A$6:$A$23,0)),0)/20))) -> 1 | P47: =INDEX(J47:N47,O47)*(1+(IFERROR(G47/10*INDEX(Calculator!$E$6:$E$23,MATCH(F47,Calculator!$A$6:$A$23,0))/100,0)+IFERROR(I47/10*INDEX(Calculator!$E$6:$E$23,MATCH(H47,Calculator!$A$6:$A$23,0))/100,0))*(1+Constants!$B$25*Calculator!$C$28))*(1+Calculator!$C$45)*(1-(1-MIN(0.5,Constants!$B$26*Calculator!$C$28))*Constants!$B$6) -> 60.49875
A48: Electro Carve | B48: LTN | C48: Combat | D48: N | E48: LTN 20 | F48: LTN | G48: 2.75 | I48: 0 | J48: 56 | K48: 59.5 | L48: 63 | M48: 66.5 | N48: 70 | O48: =MAX(1,MIN(5,1+INT(IFERROR(INDEX(Calculator!$E$6:$E$23,MATCH("LTN",Calculator!$A$6:$A$23,0)),0)/20))) -> 2 | P48: =INDEX(J48:N48,O48)*(1+(IFERROR(G48/10*INDEX(Calculator!$E$6:$E$23,MATCH(F48,Calculator!$A$6:$A$23,0))/100,0)+IFERROR(I48/10*INDEX(Calculator!$E$6:$E$23,MATCH(H48,Calculator!$A$6:$A$23,0))/100,0))*(1+Constants!$B$25*Calculator!$C$28))*(1+Calculator!$C$45)*(1-(1-MIN(0.5,Constants!$B$26*Calculator!$C$28))*Constants!$B$6) -> 59.601214
A49: Emotion Wave | B49: LTN | C49: Combat | D49: N | E49: LTN 50 | F49: LTN | G49: 2.75 | I49: 0 | J49: 20.25 | K49: 22.95 | L49: 22.65 | M49: 28.35 | N49: 31.05 | O49: =MAX(1,MIN(5,1+INT(IFERROR(INDEX(Calculator!$E$6:$E$23,MATCH("LTN",Calculator!$A$6:$A$23,0)),0)/20))) -> 2 | P49: =INDEX(J49:N49,O49)*(1+(IFERROR(G49/10*INDEX(Calculator!$E$6:$E$23,MATCH(F49,Calculator!$A$6:$A$23,0))/100,0)+IFERROR(I49/10*INDEX(Calculator!$E$6:$E$23,MATCH(H49,Calculator!$A$6:$A$23,0))/100,0))*(1+Constants!$B$25*Calculator!$C$28))*(1+Calculator!$C$45)*(1-(1-MIN(0.5,Constants!$B$26*Calculator!$C$28))*Constants!$B$6) -> 22.98904
A50: Encircle | B50: SDW | C50: Mobility | D50: N | E50: SDW 20 | F50: SDW | G50: 2.75 | I50: 0 | J50: 10 | K50: 15 | L50: 20 | M50: 25 | N50: 30 | O50: =MAX(1,MIN(5,1+INT(IFERROR(INDEX(Calculator!$E$6:$E$23,MATCH("SDW",Calculator!$A$6:$A$23,0)),0)/20))) -> 1 | P50: =INDEX(J50:N50,O50)*(1+(IFERROR(G50/10*INDEX(Calculator!$E$6:$E$23,MATCH(F50,Calculator!$A$6:$A$23,0))/100,0)+IFERROR(I50/10*INDEX(Calculator!$E$6:$E$23,MATCH(H50,Calculator!$A$6:$A$23,0))/100,0))*(1+Constants!$B$25*Calculator!$C$28))*(1+Calculator!$C$45)*(1-(1-MIN(0.5,Constants!$B$26*Calculator!$C$28))*Constants!$B$6) -> 9.3075
A51: Enforcer Pull | B51: Monster | C51: Support | D51: M | E51: no stat requirement | G51: 0 | I51: 0
A52: Equalizer | B52: Oath: Contractor | C52: Combat | D52: O | E52: after Oath: Contractor | G52: 0 | I52: 0
A53: Ether Barrage | B53: INT | C53: Combat | D53: N | E53: INT 30 | F53: INT | G53: 1.65 | I53: 0 | J53: 36 | K53: 39 | L53: 42 | M53: 45 | N53: 48 | O53: =MAX(1,MIN(5,1+INT(IFERROR(INDEX(Calculator!$E$6:$E$23,MATCH("INT",Calculator!$A$6:$A$23,0)),0)/20))) -> 1 | P53: =INDEX(J53:N53,O53)*(1+(IFERROR(G53/10*INDEX(Calculator!$E$6:$E$23,MATCH(F53,Calculator!$A$6:$A$23,0))/100,0)+IFERROR(I53/10*INDEX(Calculator!$E$6:$E$23,MATCH(H53,Calculator!$A$6:$A$23,0))/100,0))*(1+Constants!$B$25*Calculator!$C$28))*(1+Calculator!$C$45)*(1-(1-MIN(0.5,Constants!$B$26*Calculator!$C$28))*Constants!$B$6) -> 33.507
A54: Exhaustion Strike | B54: WLL | C54: Combat | D54: N | E54: WLL 40 | F54: WLL | G54: 1.65 | I54: 0 | J54: 20 | K54: 22 | L54: 24 | M54: 26 | N54: 28 | O54: =MAX(1,MIN(5,1+INT(IFERROR(INDEX(Calculator!$E$6:$E$23,MATCH("WLL",Calculator!$A$6:$A$23,0)),0)/20))) -> 2 | P54: =INDEX(J54:N54,O54)*(1+(IFERROR(G54/10*INDEX(Calculator!$E$6:$E$23,MATCH(F54,Calculator!$A$6:$A$23,0))/100,0)+IFERROR(I54/10*INDEX(Calculator!$E$6:$E$23,MATCH(H54,Calculator!$A$6:$A$23,0))/100,0))*(1+Constants!$B$25*Calculator!$C$28))*(1+Calculator!$C$45)*(1-(1-MIN(0.5,Constants!$B$26*Calculator!$C$28))*Constants!$B$6) -> 21.413054
A55: Fake Strike | B55: Oath: Jetstriker | C55: Combat | D55: O | E55: after Oath: Jetstriker | G55: 0 | I55: 0
A56: Fire Blade | B56: FLM | C56: Combat | D56: N | E56: FLM 1 | F56: FLM | G56: 2.75 | I56: 0 | J56: 18 | K56: 21 | L56: 24 | M56: 27 | N56: 30 | O56: =MAX(1,MIN(5,1+INT(IFERROR(INDEX(Calculator!$E$6:$E$23,MATCH("FLM",Calculator!$A$6:$A$23,0)),0)/20))) -> 1 | P56: =INDEX(J56:N56,O56)*(1+(IFERROR(G56/10*INDEX(Calculator!$E$6:$E$23,MATCH(F56,Calculator!$A$6:$A$23,0))/100,0)+IFERROR(I56/10*INDEX(Calculator!$E$6:$E$23,MATCH(H56,Calculator!$A$6:$A$23,0))/100,0))*(1+Constants!$B$25*Calculator!$C$28))*(1+Calculator!$C$45)*(1-(1-MIN(0.5,Constants!$B$26*Calculator!$C$28))*Constants!$B$6) -> 16.7535
A57: Fire Eruption | B57: FLM | C57: Combat | D57: N | E57: FLM 20 | F57: FLM | G57: 2.75 | I57: 0 | J57: 48 | K57: 53 | L57: 58 | M57: 63 | N57: 68 | O57: =MAX(1,MIN(5,1+INT(IFERROR(INDEX(Calculator!$E$6:$E$23,MATCH("FLM",Calculator!$A$6:$A$23,0)),0)/20))) -> 1 | P57: =INDEX(J57:N57,O57)*(1+(IFERROR(G57/10*INDEX(Calculator!$E$6:$E$23,MATCH(F57,Calculator!$A$6:$A$23,0))/100,0)+IFERROR(I57/10*INDEX(Calculator!$E$6:$E$23,MATCH(H57,Calculator!$A$6:$A$23,0))/100,0))*(1+Constants!$B$25*Calculator!$C$28))*(1+Calculator!$C$45)*(1-(1-MIN(0.5,Constants!$B$26*Calculator!$C$28))*Constants!$B$6) -> 44.676
A58: Fire Forge | B58: FLM | C58: Combat | D58: N | E58: FLM 20 | F58: FLM | G58: 2.75 | I58: 0 | J58: 25 | K58: 28 | L58: 31 | M58: 34 | N58: 37 | O58: =MAX(1,MIN(5,1+INT(IFERROR(INDEX(Calculator!$E$6:$E$23,MATCH("FLM",Calculator!$A$6:$A$23,0)),0)/20))) -> 1 | P58: =INDEX(J58:N58,O58)*(1+(IFERROR(G58/10*INDEX(Calculator!$E$6:$E$23,MATCH(F58,Calculator!$A$6:$A$23,0))/100,0)+IFERROR(I58/10*INDEX(Calculator!$E$6:$E$23,MATCH(H58,Calculator!$A$6:$A$23,0))/100,0))*(1+Constants!$B$25*Calculator!$C$28))*(1+Calculator!$C$45)*(1-(1-MIN(0.5,Constants!$B$26*Calculator!$C$28))*Constants!$B$6) -> 23.26875
A59: Fire Gun | B59: FLM | C59: Combat | D59: N | E59: FLM 1 | F59: FLM | G59: 2.75 | I59: 0 | J59: 6.5 | K59: 8.5 | L59: 10.5 | M59: 12.5 | N59: 14.5 | O59: =MAX(1,MIN(5,1+INT(IFERROR(INDEX(Calculator!$E$6:$E$23,MATCH("FLM",Calculator!$A$6:$A$23,0)),0)/20))) -> 1 | P59: =INDEX(J59:N59,O59)*(1+(IFERROR(G59/10*INDEX(Calculator!$E$6:$E$23,MATCH(F59,Calculator!$A$6:$A$23,0))/100,0)+IFERROR(I59/10*INDEX(Calculator!$E$6:$E$23,MATCH(H59,Calculator!$A$6:$A$23,0))/100,0))*(1+Constants!$B$25*Calculator!$C$28))*(1+Calculator!$C$45)*(1-(1-MIN(0.5,Constants!$B$26*Calculator!$C$28))*Constants!$B$6) -> 6.049875
A60: Fire Palm | B60: FLM | C60: Combat | D60: N | E60: FLM 20 | F60: FLM | G60: 2.75 | I60: 0 | J60: 26 | K60: 27.5 | L60: 29 | M60: 30.5 | N60: 32 | O60: =MAX(1,MIN(5,1+INT(IFERROR(INDEX(Calculator!$E$6:$E$23,MATCH("FLM",Calculator!$A$6:$A$23,0)),0)/20))) -> 1 | P60: =INDEX(J60:N60,O60)*(1+(IFERROR(G60/10*INDEX(Calculator!$E$6:$E$23,MATCH(F60,Calculator!$A$6:$A$23,0))/100,0)+IFERROR(I60/10*INDEX(Calculator!$E$6:$E$23,MATCH(H60,Calculator!$A$6:$A$23,0))/100,0))*(1+Constants!$B$25*Calculator!$C$28))*(1+Calculator!$C$45)*(1-(1-MIN(0.5,Constants!$B$26*Calculator!$C$28))*Constants!$B$6) -> 24.1995
A61: Firing Line | B61: IRN | C61: Combat | D61: N | E61: IRN 30 | F61: IRN | G61: 2.75 | I61: 0 | J61: 5.2 | K61: 5.85 | L61: 6.5 | M61: 7.15 | N61: 7.8 | O61: =MAX(1,MIN(5,1+INT(IFERROR(INDEX(Calculator!$E$6:$E$23,MATCH("IRN",Calculator!$A$6:$A$23,0)),0)/20))) -> 5 | P61: =INDEX(J61:N61,O61)*(1+(IFERROR(G61/10*INDEX(Calculator!$E$6:$E$23,MATCH(F61,Calculator!$A$6:$A$23,0))/100,0)+IFERROR(I61/10*INDEX(Calculator!$E$6:$E$23,MATCH(H61,Calculator!$A$6:$A$23,0))/100,0))*(1+Constants!$B$25*Calculator!$C$28))*(1+Calculator!$C$45)*(1-(1-MIN(0.5,Constants!$B$26*Calculator!$C$28))*Constants!$B$6) -> 9.5238342
A62: Flame Assault | B62: FLM | C62: Mobility | D62: N | E62: FLM 30 | F62: FLM | G62: 2.75 | I62: 0 | J62: 8 | K62: 16 | L62: 24 | M62: 32 | N62: 40 | O62: =MAX(1,MIN(5,1+INT(IFERROR(INDEX(Calculator!$E$6:$E$23,MATCH("FLM",Calculator!$A$6:$A$23,0)),0)/20))) -> 1 | P62: =INDEX(J62:N62,O62)*(1+(IFERROR(G62/10*INDEX(Calculator!$E$6:$E$23,MATCH(F62,Calculator!$A$6:$A$23,0))/100,0)+IFERROR(I62/10*INDEX(Calculator!$E$6:$E$23,MATCH(H62,Calculator!$A$6:$A$23,0))/100,0))*(1+Constants!$B$25*Calculator!$C$28))*(1+Calculator!$C$45)*(1-(1-MIN(0.5,Constants!$B$26*Calculator!$C$28))*Constants!$B$6) -> 7.446
A63: Flame Ballista | B63: FLM | C63: Combat | D63: N | E63: FLM 50 | F63: FLM | G63: 2.75 | I63: 0 | J63: 82 | K63: 85.5 | L63: 89 | M63: 92.5 | N63: 96 | O63: =MAX(1,MIN(5,1+INT(IFERROR(INDEX(Calculator!$E$6:$E$23,MATCH("FLM",Calculator!$A$6:$A$23,0)),0)/20))) -> 1 | P63: =INDEX(J63:N63,O63)*(1+(IFERROR(G63/10*INDEX(Calculator!$E$6:$E$23,MATCH(F63,Calculator!$A$6:$A$23,0))/100,0)+IFERROR(I63/10*INDEX(Calculator!$E$6:$E$23,MATCH(H63,Calculator!$A$6:$A$23,0))/100,0))*(1+Constants!$B$25*Calculator!$C$28))*(1+Calculator!$C$45)*(1-(1-MIN(0.5,Constants!$B$26*Calculator!$C$28))*Constants!$B$6) -> 76.3215
A64: Flame Blind | B64: FLM | C64: Support | D64: N | E64: FLM 1 | G64: 0 | I64: 0
A65: Flame Grab | B65: FLM | C65: Combat | D65: N | E65: FLM 1 | F65: FLM | G65: 2.75 | I65: 0 | J65: 15 | K65: 20 | L65: 25 | M65: 30 | N65: 35 | O65: =MAX(1,MIN(5,1+INT(IFERROR(INDEX(Calculator!$E$6:$E$23,MATCH("FLM",Calculator!$A$6:$A$23,0)),0)/20))) -> 1 | P65: =INDEX(J65:N65,O65)*(1+(IFERROR(G65/10*INDEX(Calculator!$E$6:$E$23,MATCH(F65,Calculator!$A$6:$A$23,0))/100,0)+IFERROR(I65/10*INDEX(Calculator!$E$6:$E$23,MATCH(H65,Calculator!$A$6:$A$23,0))/100,0))*(1+Constants!$B$25*Calculator!$C$28))*(1+Calculator!$C$45)*(1-(1-MIN(0.5,Constants!$B$26*Calculator!$C$28))*Constants!$B$6) -> 13.96125
A66: Flame Leap | B66: FLM | C66: Mobility | D66: N | E66: FLM 30 | G66: 0 | I66: 0
A67: Flame Repulsion | B67: FLM | C67: Combat | D67: N | E67: FLM 1 | F67: FLM | G67: 2.75 | I67: 0 | J67: 16 | K67: 18.4 | L67: 20.8 | M67: 23.2 | N67: 25.6 | O67: =MAX(1,MIN(5,1+INT(IFERROR(INDEX(Calculator!$E$6:$E$23,MATCH("FLM",Calculator!$A$6:$A$23,0)),0)/20))) -> 1 | P67: =INDEX(J67:N67,O67)*(1+(IFERROR(G67/10*INDEX(Calculator!$E$6:$E$23,MATCH(F67,Calculator!$A$6:$A$23,0))/100,0)+IFERROR(I67/10*INDEX(Calculator!$E$6:$E$23,MATCH(H67,Calculator!$A$6:$A$23,0))/100,0))*(1+Constants!$B$25*Calculator!$C$28))*(1+Calculator!$C$45)*(1-(1-MIN(0.5,Constants!$B$26*Calculator!$C$28))*Constants!$B$6) -> 14.892
A68: Flame Sentinel | B68: FLM | C68: Combat | D68: N | E68: FLM 30 | F68: FLM | G68: 2.75 | I68: 0 | J68: 5 | K68: 6 | L68: 7 | M68: 8 | N68: 9 | O68: =MAX(1,MIN(5,1+INT(IFERROR(INDEX(Calculator!$E$6:$E$23,MATCH("FLM",Calculator!$A$6:$A$23,0)),0)/20))) -> 1 | P68: =INDEX(J68:N68,O68)*(1+(IFERROR(G68/10*INDEX(Calculator!$E$6:$E$23,MATCH(F68,Calculator!$A$6:$A$23,0))/100,0)+IFERROR(I68/10*INDEX(Calculator!$E$6:$E$23,MATCH(H68,Calculator!$A$6:$A$23,0))/100,0))*(1+Constants!$B$25*Calculator!$C$28))*(1+Calculator!$C$45)*(1-(1-MIN(0.5,Constants!$B$26*Calculator!$C$28))*Constants!$B$6) -> 4.65375
A69: Flame Wisp | B69: FLM | C69: Wildcard | D69: N | E69: FLM 30 | G69: 0 | I69: 0
A70: Flame of Denial | B70: FLM | C70: Support | D70: N | E70: FLM 1 | G70: 0 | I70: 0
A71: Flaming Scourge | B71: FLM | C71: Combat | D71: N | E71: FLM 50 | F71: FLM | G71: 2.75 | I71: 0 | J71: 30 | K71: 33 | L71: 36 | M71: 39 | N71: 42 | O71: =MAX(1,MIN(5,1+INT(IFERROR(INDEX(Calculator!$E$6:$E$23,MATCH("FLM",Calculator!$A$6:$A$23,0)),0)/20))) -> 1 | P71: =INDEX(J71:N71,O71)*(1+(IFERROR(G71/10*INDEX(Calculator!$E$6:$E$23,MATCH(F71,Calculator!$A$6:$A$23,0))/100,0)+IFERROR(I71/10*INDEX(Calculator!$E$6:$E$23,MATCH(H71,Calculator!$A$6:$A$23,0))/100,0))*(1+Constants!$B$25*Calculator!$C$28))*(1+Calculator!$C$45)*(1-(1-MIN(0.5,Constants!$B$26*Calculator!$C$28))*Constants!$B$6) -> 27.9225
A72: Flare Volley | B72: FLM | C72: Combat | D72: N | E72: FLM 30 | F72: FLM | G72: 2.75 | I72: 0 | J72: 18 | K72: 21 | L72: 24 | M72: 27 | N72: 30 | O72: =MAX(1,MIN(5,1+INT(IFERROR(INDEX(Calculator!$E$6:$E$23,MATCH("FLM",Calculator!$A$6:$A$23,0)),0)/20))) -> 1 | P72: =INDEX(J72:N72,O72)*(1+(IFERROR(G72/10*INDEX(Calculator!$E$6:$E$23,MATCH(F72,Calculator!$A$6:$A$23,0))/100,0)+IFERROR(I72/10*INDEX(Calculator!$E$6:$E$23,MATCH(H72,Calculator!$A$6:$A$23,0))/100,0))*(1+Constants!$B$25*Calculator!$C$28))*(1+Calculator!$C$45)*(1-(1-MIN(0.5,Constants!$B$26*Calculator!$C$28))*Constants!$B$6) -> 16.7535
A73: Flashdraw Strike | B73: MED + AGL | C73: Combat | D73: N | E73: MED 60 · AGL 25 | F73: MED | G73: 1.65 | I73: 0 | J73: 20 | K73: 22 | L73: 24 | M73: 26 | N73: 28 | O73: =MAX(1,MIN(5,1+INT(IFERROR(INDEX(Calculator!$E$6:$E$23,MATCH("MED",Calculator!$A$6:$A$23,0)),0)/20))) -> 5 | P73: =INDEX(J73:N73,O73)*(1+(IFERROR(G73/10*INDEX(Calculator!$E$6:$E$23,MATCH(F73,Calculator!$A$6:$A$23,0))/100,0)+IFERROR(I73/10*INDEX(Calculator!$E$6:$E$23,MATCH(H73,Calculator!$A$6:$A$23,0))/100,0))*(1+Constants!$B$25*Calculator!$C$28))*(1+Calculator!$C$45)*(1-(1-MIN(0.5,Constants!$B$26*Calculator!$C$28))*Constants!$B$6) -> 31.045635
A74: Flashfire Sweep | B74: FLM + LTN | C74: Combat | D74: N | E74: FLM 30 · LTN 30 | F74: FLM | G74: 2.75 | H74: LTN | I74: 2.75 | J74: 15 | K74: 17.5 | L74: 20 | M74: 22.5 | N74: 25 | O74: =MAX(1,MIN(5,1+INT(IFERROR(INDEX(Calculator!$E$6:$E$23,MATCH("FLM",Calculator!$A$6:$A$23,0)),0)/20))) -> 1 | P74: =INDEX(J74:N74,O74)*(1+(IFERROR(G74/10*INDEX(Calculator!$E$6:$E$23,MATCH(F74,Calculator!$A$6:$A$23,0))/100,0)+IFERROR(I74/10*INDEX(Calculator!$E$6:$E$23,MATCH(H74,Calculator!$A$6:$A$23,0))/100,0))*(1+Constants!$B$25*Calculator!$C$28))*(1+Calculator!$C$45)*(1-(1-MIN(0.5,Constants!$B$26*Calculator!$C$28))*Constants!$B$6) -> 15.025516
A75: Fleeting Sparks | B75: LTN | C75: Combat | D75: N | E75: LTN 20 | F75: LTN | G75: 2.75 | I75: 0 | J75: 15 | K75: 19.5 | L75: 24 | M75: 28.5 | N75: 33 | O75: =MAX(1,MIN(5,1+INT(IFERROR(INDEX(Calculator!$E$6:$E$23,MATCH("LTN",Calculator!$A$6:$A$23,0)),0)/20))) -> 2 | P75: =INDEX(J75:N75,O75)*(1+(IFERROR(G75/10*INDEX(Calculator!$E$6:$E$23,MATCH(F75,Calculator!$A$6:$A$23,0))/100,0)+IFERROR(I75/10*INDEX(Calculator!$E$6:$E$23,MATCH(H75,Calculator!$A$6:$A$23,0))/100,0))*(1+Constants!$B$25*Calculator!$C$28))*(1+Calculator!$C$45)*(1-(1-MIN(0.5,Constants!$B$26*Calculator!$C$28))*Constants!$B$6) -> 19.533171
A76: Frost Grab | B76: ICE | C76: Combat | D76: N | E76: ICE 30 | F76: ICE | G76: 2.75 | I76: 0 | J76: 12 | K76: 14.4 | L76: 16.8 | M76: 19.2 | N76: 21.6 | O76: =MAX(1,MIN(5,1+INT(IFERROR(INDEX(Calculator!$E$6:$E$23,MATCH("ICE",Calculator!$A$6:$A$23,0)),0)/20))) -> 1 | P76: =INDEX(J76:N76,O76)*(1+(IFERROR(G76/10*INDEX(Calculator!$E$6:$E$23,MATCH(F76,Calculator!$A$6:$A$23,0))/100,0)+IFERROR(I76/10*INDEX(Calculator!$E$6:$E$23,MATCH(H76,Calculator!$A$6:$A$23,0))/100,0))*(1+Constants!$B$25*Calculator!$C$28))*(1+Calculator!$C$45)*(1-(1-MIN(0.5,Constants!$B$26*Calculator!$C$28))*Constants!$B$6) -> 11.169
A77: Frost Wisp | B77: ICE | C77: Wildcard | D77: N | E77: ICE 30 | G77: 0 | I77: 0
A78: Frozen Servants | B78: ICE | C78: Combat | D78: N | E78: ICE 1 | F78: ICE | G78: 2.75 | I78: 0 | J78: 12 | K78: 16 | L78: 20 | M78: 24 | N78: 28 | O78: =MAX(1,MIN(5,1+INT(IFERROR(INDEX(Calculator!$E$6:$E$23,MATCH("ICE",Calculator!$A$6:$A$23,0)),0)/20))) -> 1 | P78: =INDEX(J78:N78,O78)*(1+(IFERROR(G78/10*INDEX(Calculator!$E$6:$E$23,MATCH(F78,Calculator!$A$6:$A$23,0))/100,0)+IFERROR(I78/10*INDEX(Calculator!$E$6:$E$23,MATCH(H78,Calculator!$A$6:$A$23,0))/100,0))*(1+Constants!$B$25*Calculator!$C$28))*(1+Calculator!$C$45)*(1-(1-MIN(0.5,Constants!$B$26*Calculator!$C$28))*Constants!$B$6) -> 11.169
A79: Gale Lunge | B79: WND | C79: Combat | D79: N | E79: WND 20 | F79: WND | G79: 2.75 | I79: 0 | J79: 12.5 | K79: 13.75 | L79: 15 | M79: 16.25 | N79: 17.5 | O79: =MAX(1,MIN(5,1+INT(IFERROR(INDEX(Calculator!$E$6:$E$23,MATCH("WND",Calculator!$A$6:$A$23,0)),0)/20))) -> 1 | P79: =INDEX(J79:N79,O79)*(1+(IFERROR(G79/10*INDEX(Calculator!$E$6:$E$23,MATCH(F79,Calculator!$A$6:$A$23,0))/100,0)+IFERROR(I79/10*INDEX(Calculator!$E$6:$E$23,MATCH(H79,Calculator!$A$6:$A$23,0))/100,0))*(1+Constants!$B$25*Calculator!$C$28))*(1+Calculator!$C$45)*(1-(1-MIN(0.5,Constants!$B$26*Calculator!$C$28))*Constants!$B$6) -> 11.634375
A80: Gale Punch | B80: WND | C80: Combat | D80: N | E80: WND 20 | F80: WND | G80: 2.75 | I80: 0 | J80: 37.5 | K80: 41.25 | L80: 45 | M80: 48.75 | N80: 52.5 | O80: =MAX(1,MIN(5,1+INT(IFERROR(INDEX(Calculator!$E$6:$E$23,MATCH("WND",Calculator!$A$6:$A$23,0)),0)/20))) -> 1 | P80: =INDEX(J80:N80,O80)*(1+(IFERROR(G80/10*INDEX(Calculator!$E$6:$E$23,MATCH(F80,Calculator!$A$6:$A$23,0))/100,0)+IFERROR(I80/10*INDEX(Calculator!$E$6:$E$23,MATCH(H80,Calculator!$A$6:$A$23,0))/100,0))*(1+Constants!$B$25*Calculator!$C$28))*(1+Calculator!$C$45)*(1-(1-MIN(0.5,Constants!$B$26*Calculator!$C$28))*Constants!$B$6) -> 34.903125
A81: Gale Wisp | B81: WND | C81: Wildcard | D81: N | E81: WND 30 | G81: 0 | I81: 0
A82: Galetrap | B82: WND | C82: Combat | D82: N | E82: WND 20 | F82: WND | G82: 2.75 | I82: 0 | J82: 31.5 | K82: 32.38 | L82: 33.25 | M82: 34.13 | N82: 35 | O82: =MAX(1,MIN(5,1+INT(IFERROR(INDEX(Calculator!$E$6:$E$23,MATCH("WND",Calculator!$A$6:$A$23,0)),0)/20))) -> 1 | P82: =INDEX(J82:N82,O82)*(1+(IFERROR(G82/10*INDEX(Calculator!$E$6:$E$23,MATCH(F82,Calculator!$A$6:$A$23,0))/100,0)+IFERROR(I82/10*INDEX(Calculator!$E$6:$E$23,MATCH(H82,Calculator!$A$6:$A$23,0))/100,0))*(1+Constants!$B$25*Calculator!$C$28))*(1+Calculator!$C$45)*(1-(1-MIN(0.5,Constants!$B$26*Calculator!$C$28))*Constants!$B$6) -> 29.318625
A83: Gaze | B83: WLL | C83: Support | D83: N | E83: WLL 30 | G83: 0 | I83: 0
A84: Glacial Arc | B84: ICE | C84: Mobility | D84: N | E84: ICE 20 | F84: ICE | G84: 2.75 | I84: 0 | J84: 37 | K84: 42.2 | L84: 47.4 | M84: 52.6 | N84: 57.8 | O84: =MAX(1,MIN(5,1+INT(IFERROR(INDEX(Calculator!$E$6:$E$23,MATCH("ICE",Calculator!$A$6:$A$23,0)),0)/20))) -> 1 | P84: =INDEX(J84:N84,O84)*(1+(IFERROR(G84/10*INDEX(Calculator!$E$6:$E$23,MATCH(F84,Calculator!$A$6:$A$23,0))/100,0)+IFERROR(I84/10*INDEX(Calculator!$E$6:$E$23,MATCH(H84,Calculator!$A$6:$A$23,0))/100,0))*(1+Constants!$B$25*Calculator!$C$28))*(1+Calculator!$C$45)*(1-(1-MIN(0.5,Constants!$B$26*Calculator!$C$28))*Constants!$B$6) -> 34.43775
A85: Glare | B85: CHA + WLL | C85: Support | D85: N | E85: CHA 25 · (WLL 5 or WLL 20 · any attunement 1) | G85: 0 | I85: 0
A86: Graceful Flame | B86: FLM | C86: Support | D86: N | E86: FLM 20 | G86: 0 | I86: 0
A87: Grand Javelin | B87: LTN | C87: Combat | D87: N | E87: LTN 30 | F87: LTN | G87: 2.75 | I87: 0 | J87: 10.2 | K87: 18.7 | L87: 27.2 | M87: 35.7 | N87: 44.2 | O87: =MAX(1,MIN(5,1+INT(IFERROR(INDEX(Calculator!$E$6:$E$23,MATCH("LTN",Calculator!$A$6:$A$23,0)),0)/20))) -> 2 | P87: =INDEX(J87:N87,O87)*(1+(IFERROR(G87/10*INDEX(Calculator!$E$6:$E$23,MATCH(F87,Calculator!$A$6:$A$23,0))/100,0)+IFERROR(I87/10*INDEX(Calculator!$E$6:$E$23,MATCH(H87,Calculator!$A$6:$A$23,0))/100,0))*(1+Constants!$B$25*Calculator!$C$28))*(1+Calculator!$C$45)*(1-(1-MIN(0.5,Constants!$B$26*Calculator!$C$28))*Constants!$B$6) -> 18.73181
A88: Heavenly Wind | B88: WND | C88: Combat | D88: N | E88: WND 20 | F88: WND | G88: 2.75 | I88: 0 | J88: 15 | K88: 22 | L88: 29 | M88: 36 | N88: 43 | O88: =MAX(1,MIN(5,1+INT(IFERROR(INDEX(Calculator!$E$6:$E$23,MATCH("WND",Calculator!$A$6:$A$23,0)),0)/20))) -> 1 | P88: =INDEX(J88:N88,O88)*(1+(IFERROR(G88/10*INDEX(Calculator!$E$6:$E$23,MATCH(F88,Calculator!$A$6:$A$23,0))/100,0)+IFERROR(I88/10*INDEX(Calculator!$E$6:$E$23,MATCH(H88,Calculator!$A$6:$A$23,0))/100,0))*(1+Constants!$B$25*Calculator!$C$28))*(1+Calculator!$C$45)*(1-(1-MIN(0.5,Constants!$B$26*Calculator!$C$28))*Constants!$B$6) -> 13.96125
A89: Ice Beam | B89: ICE | C89: Combat | D89: N | E89: ICE 1 | F89: ICE | G89: 2.75 | I89: 0 | J89: 28 | K89: 29.2 | L89: 30.4 | M89: 31.6 | N89: 32.8 | O89: =MAX(1,MIN(5,1+INT(IFERROR(INDEX(Calculator!$E$6:$E$23,MATCH("ICE",Calculator!$A$6:$A$23,0)),0)/20))) -> 1 | P89: =INDEX(J89:N89,O89)*(1+(IFERROR(G89/10*INDEX(Calculator!$E$6:$E$23,MATCH(F89,Calculator!$A$6:$A$23,0))/100,0)+IFERROR(I89/10*INDEX(Calculator!$E$6:$E$23,MATCH(H89,Calculator!$A$6:$A$23,0))/100,0))*(1+Constants!$B$25*Calculator!$C$28))*(1+Calculator!$C$45)*(1-(1-MIN(0.5,Constants!$B$26*Calculator!$C$28))*Constants!$B$6) -> 26.061
A90: Ice Blade | B90: ICE | C90: Combat | D90: N | E90: ICE 20 | F90: ICE | G90: 2.75 | I90: 0 | J90: 28.7 | K90: 37.4 | L90: 46.1 | M90: 54.8 | N90: 63.5 | O90: =MAX(1,MIN(5,1+INT(IFERROR(INDEX(Calculator!$E$6:$E$23,MATCH("ICE",Calculator!$A$6:$A$23,0)),0)/20))) -> 1 | P90: =INDEX(J90:N90,O90)*(1+(IFERROR(G90/10*INDEX(Calculator!$E$6:$E$23,MATCH(F90,Calculator!$A$6:$A$23,0))/100,0)+IFERROR(I90/10*INDEX(Calculator!$E$6:$E$23,MATCH(H90,Calculator!$A$6:$A$23,0))/100,0))*(1+Constants!$B$25*Calculator!$C$28))*(1+Calculator!$C$45)*(1-(1-MIN(0.5,Constants!$B$26*Calculator!$C$28))*Constants!$B$6) -> 26.712525
A91: Ice Carve | B91: ICE | C91: Combat | D91: N | E91: ICE 30 | F91: ICE | G91: 2.75 | I91: 0 | J91: 45 | K91: 49.5 | L91: 54 | M91: 58.5 | N91: 63 | O91: =MAX(1,MIN(5,1+INT(IFERROR(INDEX(Calculator!$E$6:$E$23,MATCH("ICE",Calculator!$A$6:$A$23,0)),0)/20))) -> 1 | P91: =INDEX(J91:N91,O91)*(1+(IFERROR(G91/10*INDEX(Calculator!$E$6:$E$23,MATCH(F91,Calculator!$A$6:$A$23,0))/100,0)+IFERROR(I91/10*INDEX(Calculator!$E$6:$E$23,MATCH(H91,Calculator!$A$6:$A$23,0))/100,0))*(1+Constants!$B$25*Calculator!$C$28))*(1+Calculator!$C$45)*(1-(1-MIN(0.5,Constants!$B$26*Calculator!$C$28))*Constants!$B$6) -> 41.88375
A92: Ice Chains | B92: ICE | C92: Combat | D92: N | E92: ICE 20 | F92: ICE | G92: 2.75 | I92: 0 | J92: 20 | K92: 22.5 | L92: 25 | M92: 27.5 | N92: 30 | O92: =MAX(1,MIN(5,1+INT(IFERROR(INDEX(Calculator!$E$6:$E$23,MATCH("ICE",Calculator!$A$6:$A$23,0)),0)/20))) -> 1 | P92: =INDEX(J92:N92,O92)*(1+(IFERROR(G92/10*INDEX(Calculator!$E$6:$E$23,MATCH(F92,Calculator!$A$6:$A$23,0))/100,0)+IFERROR(I92/10*INDEX(Calculator!$E$6:$E$23,MATCH(H92,Calculator!$A$6:$A$23,0))/100,0))*(1+Constants!$B$25*Calculator!$C$28))*(1+Calculator!$C$45)*(1-(1-MIN(0.5,Constants!$B$26*Calculator!$C$28))*Constants!$B$6) -> 18.615
A93: Ice Cubes | B93: ICE | C93: Combat | D93: N | E93: ICE 50 | F93: ICE | G93: 2.75 | I93: 0 | J93: 24 | K93: 30 | L93: 36 | M93: 42 | N93: 48 | O93: =MAX(1,MIN(5,1+INT(IFERROR(INDEX(Calculator!$E$6:$E$23,MATCH("ICE",Calculator!$A$6:$A$23,0)),0)/20))) -> 1 | P93: =INDEX(J93:N93,O93)*(1+(IFERROR(G93/10*INDEX(Calculator!$E$6:$E$23,MATCH(F93,Calculator!$A$6:$A$23,0))/100,0)+IFERROR(I93/10*INDEX(Calculator!$E$6:$E$23,MATCH(H93,Calculator!$A$6:$A$23,0))/100,0))*(1+Constants!$B$25*Calculator!$C$28))*(1+Calculator!$C$45)*(1-(1-MIN(0.5,Constants!$B$26*Calculator!$C$28))*Constants!$B$6) -> 22.338
A94: Ice Daggers | B94: ICE | C94: Combat | D94: N | E94: ICE 20 | F94: ICE | G94: 2.75 | I94: 0 | J94: 15 | K94: 18 | L94: 21 | M94: 24 | N94: 27 | O94: =MAX(1,MIN(5,1+INT(IFERROR(INDEX(Calculator!$E$6:$E$23,MATCH("ICE",Calculator!$A$6:$A$23,0)),0)/20))) -> 1 | P94: =INDEX(J94:N94,O94)*(1+(IFERROR(G94/10*INDEX(Calculator!$E$6:$E$23,MATCH(F94,Calculator!$A$6:$A$23,0))/100,0)+IFERROR(I94/10*INDEX(Calculator!$E$6:$E$23,MATCH(H94,Calculator!$A$6:$A$23,0))/100,0))*(1+Constants!$B$25*Calculator!$C$28))*(1+Calculator!$C$45)*(1-(1-MIN(0.5,Constants!$B$26*Calculator!$C$28))*Constants!$B$6) -> 13.96125
A95: Ice Eruption | B95: ICE | C95: Combat | D95: N | E95: ICE 20 | F95: ICE | G95: 2.75 | I95: 0 | J95: 25 | K95: 25 | L95: 25 | M95: 25 | N95: 25 | O95: =MAX(1,MIN(5,1+INT(IFERROR(INDEX(Calculator!$E$6:$E$23,MATCH("ICE",Calculator!$A$6:$A$23,0)),0)/20))) -> 1 | P95: =INDEX(J95:N95,O95)*(1+(IFERROR(G95/10*INDEX(Calculator!$E$6:$E$23,MATCH(F95,Calculator!$A$6:$A$23,0))/100,0)+IFERROR(I95/10*INDEX(Calculator!$E$6:$E$23,MATCH(H95,Calculator!$A$6:$A$23,0))/100,0))*(1+Constants!$B$25*Calculator!$C$28))*(1+Calculator!$C$45)*(1-(1-MIN(0.5,Constants!$B$26*Calculator!$C$28))*Constants!$B$6) -> 23.26875
A96: Ice Fissure | B96: ICE | C96: Combat | D96: N | E96: ICE 50 | F96: ICE | G96: 2.75 | I96: 0 | J96: 11.48 | K96: 13.01 | L96: 14.54 | M96: 16.07 | N96: 17.6 | O96: =MAX(1,MIN(5,1+INT(IFERROR(INDEX(Calculator!$E$6:$E$23,MATCH("ICE",Calculator!$A$6:$A$23,0)),0)/20))) -> 1 | P96: =INDEX(J96:N96,O96)*(1+(IFERROR(G96/10*INDEX(Calculator!$E$6:$E$23,MATCH(F96,Calculator!$A$6:$A$23,0))/100,0)+IFERROR(I96/10*INDEX(Calculator!$E$6:$E$23,MATCH(H96,Calculator!$A$6:$A$23,0))/100,0))*(1+Constants!$B$25*Calculator!$C$28))*(1+Calculator!$C$45)*(1-(1-MIN(0.5,Constants!$B$26*Calculator!$C$28))*Constants!$B$6) -> 10.68501
A97: Ice Flock | B97: ICE | C97: Combat | D97: N | E97: ICE 30 | F97: ICE | G97: 2.75 | I97: 0 | J97: 48 | K97: 62.4 | L97: 76.8 | M97: 91.2 | N97: 105.6 | O97: =MAX(1,MIN(5,1+INT(IFERROR(INDEX(Calculator!$E$6:$E$23,MATCH("ICE",Calculator!$A$6:$A$23,0)),0)/20))) -> 1 | P97: =INDEX(J97:N97,O97)*(1+(IFERROR(G97/10*INDEX(Calculator!$E$6:$E$23,MATCH(F97,Calculator!$A$6:$A$23,0))/100,0)+IFERROR(I97/10*INDEX(Calculator!$E$6:$E$23,MATCH(H97,Calculator!$A$6:$A$23,0))/100,0))*(1+Constants!$B$25*Calculator!$C$28))*(1+Calculator!$C$45)*(1-(1-MIN(0.5,Constants!$B$26*Calculator!$C$28))*Constants!$B$6) -> 44.676
A98: Ice Forge | B98: ICE | C98: Combat | D98: N | E98: ICE 20 | F98: ICE | G98: 2.75 | I98: 0 | J98: 18 | K98: 23.8 | L98: 30.4 | M98: 37.8 | N98: 46 | O98: =MAX(1,MIN(5,1+INT(IFERROR(INDEX(Calculator!$E$6:$E$23,MATCH("ICE",Calculator!$A$6:$A$23,0)),0)/20))) -> 1 | P98: =INDEX(J98:N98,O98)*(1+(IFERROR(G98/10*INDEX(Calculator!$E$6:$E$23,MATCH(F98,Calculator!$A$6:$A$23,0))/100,0)+IFERROR(I98/10*INDEX(Calculator!$E$6:$E$23,MATCH(H98,Calculator!$A$6:$A$23,0))/100,0))*(1+Constants!$B$25*Calculator!$C$28))*(1+Calculator!$C$45)*(1-(1-MIN(0.5,Constants!$B$26*Calculator!$C$28))*Constants!$B$6) -> 16.7535
A99: Ice Lance | B99: ICE | C99: Combat | D99: N | E99: ICE 30 | F99: ICE | G99: 2.75 | I99: 0 | J99: 25 | K99: 30 | L99: 35 | M99: 40 | N99: 45 | O99: =MAX(1,MIN(5,1+INT(IFERROR(INDEX(Calculator!$E$6:$E$23,MATCH("ICE",Calculator!$A$6:$A$23,0)),0)/20))) -> 1 | P99: =INDEX(J99:N99,O99)*(1+(IFERROR(G99/10*INDEX(Calculator!$E$6:$E$23,MATCH(F99,Calculator!$A$6:$A$23,0))/100,0)+IFERROR(I99/10*INDEX(Calculator!$E$6:$E$23,MATCH(H99,Calculator!$A$6:$A$23,0))/100,0))*(1+Constants!$B$25*Calculator!$C$28))*(1+Calculator!$C$45)*(1-(1-MIN(0.5,Constants!$B$26*Calculator!$C$28))*Constants!$B$6) -> 23.26875
A100: Ice Lasers | B100: ICE | C100: Combat | D100: N | E100: ICE 30 · after Glass Path: Crystallization | F100: ICE | G100: 2.75 | I100: 0 | J100: 8 | K100: 11 | L100: 14 | M100: 17 | N100: 20 | O100: =MAX(1,MIN(5,1+INT(IFERROR(INDEX(Calculator!$E$6:$E$23,MATCH("ICE",Calculator!$A$6:$A$23,0)),0)/20))) -> 1 | P100: =INDEX(J100:N100,O100)*(1+(IFERROR(G100/10*INDEX(Calculator!$E$6:$E$23,MATCH(F100,Calculator!$A$6:$A$23,0))/100,0)+IFERROR(I100/10*INDEX(Calculator!$E$6:$E$23,MATCH(H100,Calculator!$A$6:$A$23,0))/100,0))*(1+Constants!$B$25*Calculator!$C$28))*(1+Calculator!$C$45)*(1-(1-MIN(0.5,Constants!$B$26*Calculator!$C$28))*Constants!$B$6) -> 7.446
...

Sheet Weapons
A1: Weapon | B1: Type | C1: Requirement | D1: Base damage | E1: PEN | F1: Scale stat 1 | G1: Coef 1 | H1: Scale stat 2 | I1: Coef 2 | J1: Scale stat 3 | K1: Coef 3 | L1: Hit with Calculator stats
A2: Acheron's Warspear | B2: Spear | C2: MED 40 | D2: 18 | E2: 0.15 | F2: MED | G2: 6 | I2: 0 | K2: 0 | L2: =D2*(1+0.75*(IFERROR(G2*INDEX(Calculator!$E$6:$E$23,MATCH(F2,Calculator!$A$6:$A$23,0)),0)+IFERROR(I2*INDEX(Calculator!$E$6:$E$23,MATCH(H2,Calculator!$A$6:$A$23,0)),0)+IFERROR(K2*INDEX(Calculator!$E$6:$E$23,MATCH(J2,Calculator!$A$6:$A$23,0)),0))*(1+Constants!$B$23*Calculator!$C$27)/1000)*(1+Calculator!$C$45+Calculator!$C$37)*Calculator!$C$39*(1-(1-MIN(Calculator!$C$44,MIN(1,E2+Calculator!$E$6/10*Constants!$B$16+Calculator!$C$36+Calculator!$C$40+Constants!$B$24*Calculator!$C$27)))*Constants!$B$6) -> 27.294752
A3: Adretian Axe | B3: Greataxe | C3: HVY 35 | D3: 24 | E3: 0 | F3: HVY | G3: 7 | I3: 0 | K3: 0 | L3: =D3*(1+0.75*(IFERROR(G3*INDEX(Calculator!$E$6:$E$23,MATCH(F3,Calculator!$A$6:$A$23,0)),0)+IFERROR(I3*INDEX(Calculator!$E$6:$E$23,MATCH(H3,Calculator!$A$6:$A$23,0)),0)+IFERROR(K3*INDEX(Calculator!$E$6:$E$23,MATCH(J3,Calculator!$A$6:$A$23,0)),0))*(1+Constants!$B$23*Calculator!$C$27)/1000)*(1+Calculator!$C$45+Calculator!$C$37)*Calculator!$C$39*(1-(1-MIN(Calculator!$C$44,MIN(1,E3+Calculator!$E$6/10*Constants!$B$16+Calculator!$C$36+Calculator!$C$40+Constants!$B$24*Calculator!$C$27)))*Constants!$B$6) -> 22.53996
A4: Alloyed Adretian Axe | B4: Greataxe | C4: HVY 75 | D4: 24 | E4: 0.1 | F4: HVY | G4: 8 | I4: 0 | K4: 0 | L4: =D4*(1+0.75*(IFERROR(G4*INDEX(Calculator!$E$6:$E$23,MATCH(F4,Calculator!$A$6:$A$23,0)),0)+IFERROR(I4*INDEX(Calculator!$E$6:$E$23,MATCH(H4,Calculator!$A$6:$A$23,0)),0)+IFERROR(K4*INDEX(Calculator!$E$6:$E$23,MATCH(J4,Calculator!$A$6:$A$23,0)),0))*(1+Constants!$B$23*Calculator!$C$27)/1000)*(1+Calculator!$C$45+Calculator!$C$37)*Calculator!$C$39*(1-(1-MIN(Calculator!$C$44,MIN(1,E4+Calculator!$E$6/10*Constants!$B$16+Calculator!$C$36+Calculator!$C$40+Constants!$B$24*Calculator!$C$27)))*Constants!$B$6) -> 23.45796
A5: Alloyed Canorian Axe | B5: Greataxe | C5: HVY 75 | D5: 24 | E5: 0.2 | F5: HVY | G5: 9 | I5: 0 | K5: 0 | L5: =D5*(1+0.75*(IFERROR(G5*INDEX(Calculator!$E$6:$E$23,MATCH(F5,Calculator!$A$6:$A$23,0)),0)+IFERROR(I5*INDEX(Calculator!$E$6:$E$23,MATCH(H5,Calculator!$A$6:$A$23,0)),0)+IFERROR(K5*INDEX(Calculator!$E$6:$E$23,MATCH(J5,Calculator!$A$6:$A$23,0)),0))*(1+Constants!$B$23*Calculator!$C$27)/1000)*(1+Calculator!$C$45+Calculator!$C$37)*Calculator!$C$39*(1-(1-MIN(Calculator!$C$44,MIN(1,E5+Calculator!$E$6/10*Constants!$B$16+Calculator!$C$36+Calculator!$C$40+Constants!$B$24*Calculator!$C$27)))*Constants!$B$6) -> 24.37596
A6: Alloyed Cavalry Saber | B6: Sword | C6: MED 75 | D6: 22.5 | E6: 0.1 | F6: MED | G6: 5.5 | I6: 0 | K6: 0 | L6: =D6*(1+0.75*(IFERROR(G6*INDEX(Calculator!$E$6:$E$23,MATCH(F6,Calculator!$A$6:$A$23,0)),0)+IFERROR(I6*INDEX(Calculator!$E$6:$E$23,MATCH(H6,Calculator!$A$6:$A$23,0)),0)+IFERROR(K6*INDEX(Calculator!$E$6:$E$23,MATCH(J6,Calculator!$A$6:$A$23,0)),0))*(1+Constants!$B$23*Calculator!$C$27)/1000)*(1+Calculator!$C$45+Calculator!$C$37)*Calculator!$C$39*(1-(1-MIN(Calculator!$C$44,MIN(1,E6+Calculator!$E$6/10*Constants!$B$16+Calculator!$C$36+Calculator!$C$40+Constants!$B$24*Calculator!$C$27)))*Constants!$B$6) -> 32.507674
A7: Alloyed Crescent Cleaver | B7: Greatsword | C7: HVY 75 · STR 10 | D7: 22 | E7: 0 | F7: HVY | G7: 10 | I7: 0 | K7: 0 | L7: =D7*(1+0.75*(IFERROR(G7*INDEX(Calculator!$E$6:$E$23,MATCH(F7,Calculator!$A$6:$A$23,0)),0)+IFERROR(I7*INDEX(Calculator!$E$6:$E$23,MATCH(H7,Calculator!$A$6:$A$23,0)),0)+IFERROR(K7*INDEX(Calculator!$E$6:$E$23,MATCH(J7,Calculator!$A$6:$A$23,0)),0))*(1+Constants!$B$23*Calculator!$C$27)/1000)*(1+Calculator!$C$45+Calculator!$C$37)*Calculator!$C$39*(1-(1-MIN(Calculator!$C$44,MIN(1,E7+Calculator!$E$6/10*Constants!$B$16+Calculator!$C$36+Calculator!$C$40+Constants!$B$24*Calculator!$C$27)))*Constants!$B$6) -> 20.66163
A8: Alloyed Dawnshot | B8: Pistol | C8: LHT 75 | D8: 16 | E8: 0.05 | F8: LHT | G8: 12 | I8: 0 | K8: 0 | L8: =D8*(1+0.75*(IFERROR(G8*INDEX(Calculator!$E$6:$E$23,MATCH(F8,Calculator!$A$6:$A$23,0)),0)+IFERROR(I8*INDEX(Calculator!$E$6:$E$23,MATCH(H8,Calculator!$A$6:$A$23,0)),0)+IFERROR(K8*INDEX(Calculator!$E$6:$E$23,MATCH(J8,Calculator!$A$6:$A$23,0)),0))*(1+Constants!$B$23*Calculator!$C$27)/1000)*(1+Calculator!$C$45+Calculator!$C$37)*Calculator!$C$39*(1-(1-MIN(Calculator!$C$44,MIN(1,E8+Calculator!$E$6/10*Constants!$B$16+Calculator!$C$36+Calculator!$C$40+Constants!$B$24*Calculator!$C$27)))*Constants!$B$6) -> 15.33264
A9: Alloyed Falchion | B9: Sword | C9: MED 75 | D9: 18 | E9: 0.2 | F9: MED | G9: 7 | I9: 0 | K9: 0 | L9: =D9*(1+0.75*(IFERROR(G9*INDEX(Calculator!$E$6:$E$23,MATCH(F9,Calculator!$A$6:$A$23,0)),0)+IFERROR(I9*INDEX(Calculator!$E$6:$E$23,MATCH(H9,Calculator!$A$6:$A$23,0)),0)+IFERROR(K9*INDEX(Calculator!$E$6:$E$23,MATCH(J9,Calculator!$A$6:$A$23,0)),0))*(1+Constants!$B$23*Calculator!$C$27)/1000)*(1+Calculator!$C$45+Calculator!$C$37)*Calculator!$C$39*(1-(1-MIN(Calculator!$C$44,MIN(1,E9+Calculator!$E$6/10*Constants!$B$16+Calculator!$C$36+Calculator!$C$40+Constants!$B$24*Calculator!$C$27)))*Constants!$B$6) -> 29.408011
A10: Alloyed Forge Greathammer | B10: Greathammer | C10: HVY 75 · STR 10 | D10: 25.5 | E10: 0 | F10: HVY | G10: 8 | I10: 0 | K10: 0 | L10: =D10*(1+0.75*(IFERROR(G10*INDEX(Calculator!$E$6:$E$23,MATCH(F10,Calculator!$A$6:$A$23,0)),0)+IFERROR(I10*INDEX(Calculator!$E$6:$E$23,MATCH(H10,Calculator!$A$6:$A$23,0)),0)+IFERROR(K10*INDEX(Calculator!$E$6:$E$23,MATCH(J10,Calculator!$A$6:$A$23,0)),0))*(1+Constants!$B$23*Calculator!$C$27)/1000)*(1+Calculator!$C$45+Calculator!$C$37)*Calculator!$C$39*(1-(1-MIN(Calculator!$C$44,MIN(1,E10+Calculator!$E$6/10*Constants!$B$16+Calculator!$C$36+Calculator!$C$40+Constants!$B$24*Calculator!$C$27)))*Constants!$B$6) -> 23.948708
A11: Alloyed Halberd | B11: Greataxe | C11: HVY 75 | D11: 24 | E11: 0.15 | F11: HVY | G11: 8 | I11: 0 | K11: 0 | L11: =D11*(1+0.75*(IFERROR(G11*INDEX(Calculator!$E$6:$E$23,MATCH(F11,Calculator!$A$6:$A$23,0)),0)+IFERROR(I11*INDEX(Calculator!$E$6:$E$23,MATCH(H11,Calculator!$A$6:$A$23,0)),0)+IFERROR(K11*INDEX(Calculator!$E$6:$E$23,MATCH(J11,Calculator!$A$6:$A$23,0)),0))*(1+Constants!$B$23*Calculator!$C$27)/1000)*(1+Calculator!$C$45+Calculator!$C$37)*Calculator!$C$39*(1-(1-MIN(Calculator!$C$44,MIN(1,E11+Calculator!$E$6/10*Constants!$B$16+Calculator!$C$36+Calculator!$C$40+Constants!$B$24*Calculator!$C$27)))*Constants!$B$6) -> 23.91696
A12: Alloyed Inheritor | B12: Greatsword | C12: HVY 75 · STR 10 | D12: 24 | E12: 0.15 | F12: HVY | G12: 8 | I12: 0 | K12: 0 | L12: =D12*(1+0.75*(IFERROR(G12*INDEX(Calculator!$E$6:$E$23,MATCH(F12,Calculator!$A$6:$A$23,0)),0)+IFERROR(I12*INDEX(Calculator!$E$6:$E$23,MATCH(H12,Calculator!$A$6:$A$23,0)),0)+IFERROR(K12*INDEX(Calculator!$E$6:$E$23,MATCH(J12,Calculator!$A$6:$A$23,0)),0))*(1+Constants!$B$23*Calculator!$C$27)/1000)*(1+Calculator!$C$45+Calculator!$C$37)*Calculator!$C$39*(1-(1-MIN(Calculator!$C$44,MIN(1,E12+Calculator!$E$6/10*Constants!$B$16+Calculator!$C$36+Calculator!$C$40+Constants!$B$24*Calculator!$C$27)))*Constants!$B$6) -> 23.91696
A13: Alloyed Katana | B13: Sword | C13: MED 75 | D13: 20 | E13: 0.1 | F13: MED | G13: 7 | I13: 0 | K13: 0 | L13: =D13*(1+0.75*(IFERROR(G13*INDEX(Calculator!$E$6:$E$23,MATCH(F13,Calculator!$A$6:$A$23,0)),0)+IFERROR(I13*INDEX(Calculator!$E$6:$E$23,MATCH(H13,Calculator!$A$6:$A$23,0)),0)+IFERROR(K13*INDEX(Calculator!$E$6:$E$23,MATCH(J13,Calculator!$A$6:$A$23,0)),0))*(1+Constants!$B$23*Calculator!$C$27)/1000)*(1+Calculator!$C$45+Calculator!$C$37)*Calculator!$C$39*(1-(1-MIN(Calculator!$C$44,MIN(1,E13+Calculator!$E$6/10*Constants!$B$16+Calculator!$C$36+Calculator!$C$40+Constants!$B$24*Calculator!$C$27)))*Constants!$B$6) -> 31.445004
... A30: Big Brother | B30: Dagger | C30: LHT 80 | D30: 15 | E30: 0.15 | F30: LHT | G30: 8 | I30: 0 | K30: 0 | L30: =D30*(1+0.75*(IFERROR(G30*INDEX(Calculator!$E$6:$E$23,MATCH(F30,Calculator!$A$6:$A$23,0)),0)+IFERROR(I30*INDEX(Calculator!$E$6:$E$23,MATCH(H30,Calculator!$A$6:$A$23,0)),0)+IFERROR(K30*INDEX(Calculator!$E$6:$E$23,MATCH(J30,Calculator!$A$6:$A$23,0)),0))*(1+Constants!$B$23*Calculator!$C$27)/1000)*(1+Calculator!$C$45+Calculator!$C$37)*Calculator!$C$39*(1-(1-MIN(Calculator!$C$44,MIN(1,E30+Calculator!$E$6/10*Constants!$B$16+Calculator!$C$36+Calculator!$C$40+Constants!$B$24*Calculator!$C$27)))*Constants!$B$6) -> 14.9481
A31: Black Death | B31: Spear | C31: MED 30 · Mind 50 · SDW 70 · Power 10 | D31: 16.5 | E31: 0.15 | F31: MED | G31: 2.5 | H31: MND | I31: 2 | J31: SDW | K31: 3 | L31: =D31*(1+0.75*(IFERROR(G31*INDEX(Calculator!$E$6:$E$23,MATCH(F31,Calculator!$A$6:$A$23,0)),0)+IFERROR(I31*INDEX(Calculator!$E$6:$E$23,MATCH(H31,Calculator!$A$6:$A$23,0)),0)+IFERROR(K31*INDEX(Calculator!$E$6:$E$23,MATCH(J31,Calculator!$A$6:$A$23,0)),0))*(1+Constants!$B$23*Calculator!$C$27)/1000)*(1+Calculator!$C$45+Calculator!$C$37)*Calculator!$C$39*(1-(1-MIN(Calculator!$C$44,MIN(1,E31+Calculator!$E$6/10*Constants!$B$16+Calculator!$C$36+Calculator!$C$40+Constants!$B$24*Calculator!$C$27)))*Constants!$B$6) -> 20.793704
A32: Bloodbane | B32: Greatsword | C32: HVY 60 · STR 30 | D32: 23 | E32: 0 | F32: HVY | G32: 7 | I32: 0 | K32: 0 | L32: =D32*(1+0.75*(IFERROR(G32*INDEX(Calculator!$E$6:$E$23,MATCH(F32,Calculator!$A$6:$A$23,0)),0)+IFERROR(I32*INDEX(Calculator!$E$6:$E$23,MATCH(H32,Calculator!$A$6:$A$23,0)),0)+IFERROR(K32*INDEX(Calculator!$E$6:$E$23,MATCH(J32,Calculator!$A$6:$A$23,0)),0))*(1+Constants!$B$23*Calculator!$C$27)/1000)*(1+Calculator!$C$45+Calculator!$C$37)*Calculator!$C$39*(1-(1-MIN(Calculator!$C$44,MIN(1,E32+Calculator!$E$6/10*Constants!$B$16+Calculator!$C$36+Calculator!$C$40+Constants!$B$24*Calculator!$C$27)))*Constants!$B$6) -> 21.600795
A33: Bloodfouler | B33: Greatsword | C33: HVY 50 · BLD 75 · Power 10 | D33: 19 | E33: 0.2 | F33: HVY | G33: 5 | H33: BLD | I33: 4 | K33: 0 | L33: =D33*(1+0.75*(IFERROR(G33*INDEX(Calculator!$E$6:$E$23,MATCH(F33,Calculator!$A$6:$A$23,0)),0)+IFERROR(I33*INDEX(Calculator!$E$6:$E$23,MATCH(H33,Calculator!$A$6:$A$23,0)),0)+IFERROR(K33*INDEX(Calculator!$E$6:$E$23,MATCH(J33,Calculator!$A$6:$A$23,0)),0))*(1+Constants!$B$23*Calculator!$C$27)/1000)*(1+Calculator!$C$45+Calculator!$C$37)*Calculator!$C$39*(1-(1-MIN(Calculator!$C$44,MIN(1,E33+Calculator!$E$6/10*Constants!$B$16+Calculator!$C$36+Calculator!$C$40+Constants!$B$24*Calculator!$C$27)))*Constants!$B$6) -> 19.297635
A34: Bloodtide Trident | B34: Spear | C34: MED 75 | D34: 18 | E34: 0.25 | F34: MED | G34: 6 | I34: 0 | K34: 0 | L34: =D34*(1+0.75*(IFERROR(G34*INDEX(Calculator!$E$6:$E$23,MATCH(F34,Calculator!$A$6:$A$23,0)),0)+IFERROR(I34*INDEX(Calculator!$E$6:$E$23,MATCH(H34,Calculator!$A$6:$A$23,0)),0)+IFERROR(K34*INDEX(Calculator!$E$6:$E$23,MATCH(J34,Calculator!$A$6:$A$23,0)),0))*(1+Constants!$B$23*Calculator!$C$27)/1000)*(1+Calculator!$C$45+Calculator!$C$37)*Calculator!$C$39*(1-(1-MIN(Calculator!$C$44,MIN(1,E34+Calculator!$E$6/10*Constants!$B$16+Calculator!$C$36+Calculator!$C$40+Constants!$B$24*Calculator!$C$27)))*Constants!$B$6) -> 28.342401
A35: Boltcrusher | B35: Greathammer | C35: HVY 55 · STR 20 · LTN 80 | D35: 23 | E35: 0.2 | F35: HVY | G35: 4.2 | H35: LTN | I35: 7 | K35: 0 | L35: =D35*(1+0.75*(IFERROR(G35*INDEX(Calculator!$E$6:$E$23,MATCH(F35,Calculator!$A$6:$A$23,0)),0)+IFERROR(I35*INDEX(Calculator!$E$6:$E$23,MATCH(H35,Calculator!$A$6:$A$23,0)),0)+IFERROR(K35*INDEX(Calculator!$E$6:$E$23,MATCH(J35,Calculator!$A$6:$A$23,0)),0))*(1+Constants!$B$23*Calculator!$C$27)/1000)*(1+Calculator!$C$45+Calculator!$C$37)*Calculator!$C$39*(1-(1-MIN(Calculator!$C$44,MIN(1,E35+Calculator!$E$6/10*Constants!$B$16+Calculator!$C$36+Calculator!$C$40+Constants!$B$24*Calculator!$C$27)))*Constants!$B$6) -> 26.759919
A36: Broodalloy Cestus | B36: Fist | C36: LHT 85 | D36: 15.5 | E36: 0.2 | F36: LHT | G36: 9 | I36: 0 | K36: 0 | L36: =D36*(1+0.75*(IFERROR(G36*INDEX(Calculator!$E$6:$E$23,MATCH(F36,Calculator!$A$6:$A$23,0)),0)+IFERROR(I36*INDEX(Calculator!$E$6:$E$23,MATCH(H36,Calculator!$A$6:$A$23,0)),0)+IFERROR(K36*INDEX(Calculator!$E$6:$E$23,MATCH(J36,Calculator!$A$6:$A$23,0)),0))*(1+Constants!$B$23*Calculator!$C$27)/1000)*(1+Calculator!$C$45+Calculator!$C$37)*Calculator!$C$39*(1-(1-MIN(Calculator!$C$44,MIN(1,E36+Calculator!$E$6/10*Constants!$B$16+Calculator!$C$36+Calculator!$C$40+Constants!$B$24*Calculator!$C$27)))*Constants!$B$6) -> 15.742807
A37: Calamity Cinnabar | B37: Greatsword | C37: HVY 40 · SDW 75 · Power 10 | D37: 22 | E37: 0 | F37: HVY | G37: 4 | H37: SDW | I37: 9 | K37: 0 | L37: =D37*(1+0.75*(IFERROR(G37*INDEX(Calculator!$E$6:$E$23,MATCH(F37,Calculator!$A$6:$A$23,0)),0)+IFERROR(I37*INDEX(Calculator!$E$6:$E$23,MATCH(H37,Calculator!$A$6:$A$23,0)),0)+IFERROR(K37*INDEX(Calculator!$E$6:$E$23,MATCH(J37,Calculator!$A$6:$A$23,0)),0))*(1+Constants!$B$23*Calculator!$C$27)/1000)*(1+Calculator!$C$45+Calculator!$C$37)*Calculator!$C$39*(1-(1-MIN(Calculator!$C$44,MIN(1,E37+Calculator!$E$6/10*Constants!$B$16+Calculator!$C$36+Calculator!$C$40+Constants!$B$24*Calculator!$C$27)))*Constants!$B$6) -> 20.66163
A38: Canor Fang | B38: Dagger | C38: LHT 40 | D38: 11 | E38: 0.05 | F38: LHT | G38: 10 | I38: 0 | K38: 0 | L38: =D38*(1+0.75*(IFERROR(G38*INDEX(Calculator!$E$6:$E$23,MATCH(F38,Calculator!$A$6:$A$23,0)),0)+IFERROR(I38*INDEX(Calculator!$E$6:$E$23,MATCH(H38,Calculator!$A$6:$A$23,0)),0)+IFERROR(K38*INDEX(Calculator!$E$6:$E$23,MATCH(J38,Calculator!$A$6:$A$23,0)),0))*(1+Constants!$B$23*Calculator!$C$27)/1000)*(1+Calculator!$C$45+Calculator!$C$37)*Calculator!$C$39*(1-(1-MIN(Calculator!$C$44,MIN(1,E38+Calculator!$E$6/10*Constants!$B$16+Calculator!$C$36+Calculator!$C$40+Constants!$B$24*Calculator!$C$27)))*Constants!$B$6) -> 10.54119
A39: Canorian Axe | B39: Greataxe | C39: HVY 35 | D39: 24 | E39: 0 | F39: HVY | G39: 7 | I39: 0 | K39: 0 | L39: =D39*(1+0.75*(IFERROR(G39*INDEX(Calculator!$E$6:$E$23,MATCH(F39,Calculator!$A$6:$A$23,0)),0)+IFERROR(I39*INDEX(Calculator!$E$6:$E$23,MATCH(H39,Calculator!$A$6:$A$23,0)),0)+IFERROR(K39*INDEX(Calculator!$E$6:$E$23,MATCH(J39,Calculator!$A$6:$A$23,0)),0))*(1+Constants!$B$23*Calculator!$C$27)/1000)*(1+Calculator!$C$45+Calculator!$C$37)*Calculator!$C$39*(1-(1-MIN(Calculator!$C$44,MIN(1,E39+Calculator!$E$6/10*Constants!$B$16+Calculator!$C$36+Calculator!$C$40+Constants!$B$24*Calculator!$C$27)))*Constants!$B$6) -> 22.53996
A40: Cavalry Saber | B40: Sword | C40: MED 40 | D40: 21 | E40: 0 | F40: MED | G40: 5 | I40: 0 | K40: 0 | L40: =D40*(1+0.75*(IFERROR(G40*INDEX(Calculator!$E$6:$E$23,MATCH(F40,Calculator!$A$6:$A$23,0)),0)+IFERROR(I40*INDEX(Calculator!$E$6:$E$23,MATCH(H40,Calculator!$A$6:$A$23,0)),0)+IFERROR(K40*INDEX(Calculator!$E$6:$E$23,MATCH(J40,Calculator!$A$6:$A$23,0)),0))*(1+Constants!$B$23*Calculator!$C$27)/1000)*(1+Calculator!$C$45+Calculator!$C$37)*Calculator!$C$39*(1-(1-MIN(Calculator!$C$44,MIN(1,E40+Calculator!$E$6/10*Constants!$B$16+Calculator!$C$36+Calculator!$C$40+Constants!$B$24*Calculator!$C$27)))*Constants!$B$6) -> 28.295821
A41: Central Dirk | B41: Dagger | C41: LHT 50 | D41: 16 | E41: 0.05 | F41: LHT | G41: 7 | I41: 0 | K41: 0 | L41: =D41*(1+0.75*(IFERROR(G41*INDEX(Calculator!$E$6:$E$23,MATCH(F41,Calculator!$A$6:$A$23,0)),0)+IFERROR(I41*INDEX(Calculator!$E$6:$E$23,MATCH(H41,Calculator!$A$6:$A$23,0)),0)+IFERROR(K41*INDEX(Calculator!$E$6:$E$23,MATCH(J41,Calculator!$A$6:$A$23,0)),0))*(1+Constants!$B$23*Calculator!$C$27)/1000)*(1+Calculator!$C$45+Calculator!$C$37)*Calculator!$C$39*(1-(1-MIN(Calculator!$C$44,MIN(1,E41+Calculator!$E$6/10*Constants!$B$16+Calculator!$C$36+Calculator!$C$40+Constants!$B$24*Calculator!$C$27)))*Constants!$B$6) -> 15.33264
A42: Cerulean Thread | B42: Dagger | C42: LHT 85 · Power 10 | D42: 14.5 | E42: 0.25 | F42: LHT | G42: 7.5 | I42: 0 | K42: 0 | L42: =D42*(1+0.75*(IFERROR(G42*INDEX(Calculator!$E$6:$E$23,MATCH(F42,Calculator!$A$6:$A$23,0)),0)+IFERROR(I42*INDEX(Calculator!$E$6:$E$23,MATCH(H42,Calculator!$A$6:$A$23,0)),0)+IFERROR(K42*INDEX(Calculator!$E$6:$E$23,MATCH(J42,Calculator!$A$6:$A$23,0)),0))*(1+Constants!$B$23*Calculator!$C$27)/1000)*(1+Calculator!$C$45+Calculator!$C$37)*Calculator!$C$39*(1-(1-MIN(Calculator!$C$44,MIN(1,E42+Calculator!$E$6/10*Constants!$B$16+Calculator!$C$36+Calculator!$C$40+Constants!$B$24*Calculator!$C$27)))*Constants!$B$6) -> 15.004455
A43: Champion's Dagger | B43: Dagger | C43: LHT 50 | D43: 16 | E43: 0 | F43: LHT | G43: 8 | I43: 0 | K43: 0 | L43: =D43*(1+0.75*(IFERROR(G43*INDEX(Calculator!$E$6:$E$23,MATCH(F43,Calculator!$A$6:$A$23,0)),0)+IFERROR(I43*INDEX(Calculator!$E$6:$E$23,MATCH(H43,Calculator!$A$6:$A$23,0)),0)+IFERROR(K43*INDEX(Calculator!$E$6:$E$23,MATCH(J43,Calculator!$A$6:$A$23,0)),0))*(1+Constants!$B$23*Calculator!$C$27)/1000)*(1+Calculator!$C$45+Calculator!$C$37)*Calculator!$C$39*(1-(1-MIN(Calculator!$C$44,MIN(1,E43+Calculator!$E$6/10*Constants!$B$16+Calculator!$C$36+Calculator!$C$40+Constants!$B$24*Calculator!$C$27)))*Constants!$B$6) -> 15.02664
A44: Champion's Sword | B44: Sword | C44: MED 40 | D44: 19 | E44: 0 | F44: MED | G44: 6.5 | I44: 0 | K44: 0 | L44: =D44*(1+0.75*(IFERROR(G44*INDEX(Calculator!$E$6:$E$23,MATCH(F44,Calculator!$A$6:$A$23,0)),0)+IFERROR(I44*INDEX(Calculator!$E$6:$E$23,MATCH(H44,Calculator!$A$6:$A$23,0)),0)+IFERROR(K44*INDEX(Calculator!$E$6:$E$23,MATCH(J44,Calculator!$A$6:$A$23,0)),0))*(1+Constants!$B$23*Calculator!$C$27)/1000)*(1+Calculator!$C$45+Calculator!$C$37)*Calculator!$C$39*(1-(1-MIN(Calculator!$C$44,MIN(1,E44+Calculator!$E$6/10*Constants!$B$16+Calculator!$C$36+Calculator!$C$40+Constants!$B$24*Calculator!$C$27)))*Constants!$B$6) -> 27.928034
A45: Chorus of Agonies | B45: Greataxe | C45: HVY 100 · STR 20 · Power 10 | D45: 26 | E45: 0 | F45: HVY | G45: 11 | I45: 0 | K45: 0 | L45: =D45*(1+0.75*(IFERROR(G45*INDEX(Calculator!$E$6:$E$23,MATCH(F45,Calculator!$A$6:$A$23,0)),0)+IFERROR(I45*INDEX(Calculator!$E$6:$E$23,MATCH(H45,Calculator!$A$6:$A$23,0)),0)+IFERROR(K45*INDEX(Calculator!$E$6:$E$23,MATCH(J45,Calculator!$A$6:$A$23,0)),0))*(1+Constants!$B$23*Calculator!$C$27)/1000)*(1+Calculator!$C$45+Calculator!$C$37)*Calculator!$C$39*(1-(1-MIN(Calculator!$C$44,MIN(1,E45+Calculator!$E$6/10*Constants!$B$16+Calculator!$C$36+Calculator!$C$40+Constants!$B$24*Calculator!$C$27)))*Constants!$B$6) -> 24.41829
A46: Coldpoint | B46: Rapier | C46: LHT 70 · ICE 25 | D46: 15 | E46: 0.1 | F46: LHT | G46: 7 | H46: ICE | I46: 4 | K46: 0 | L46: =D46*(1+0.75*(IFERROR(G46*INDEX(Calculator!$E$6:$E$23,MATCH(F46,Calculator!$A$6:$A$23,0)),0)+IFERROR(I46*INDEX(Calculator!$E$6:$E$23,MATCH(H46,Calculator!$A$6:$A$23,0)),0)+IFERROR(K46*INDEX(Calculator!$E$6:$E$23,MATCH(J46,Calculator!$A$6:$A$23,0)),0))*(1+Constants!$B$23*Calculator!$C$27)/1000)*(1+Calculator!$C$45+Calculator!$C$37)*Calculator!$C$39*(1-(1-MIN(Calculator!$C$44,MIN(1,E46+Calculator!$E$6/10*Constants!$B$16+Calculator!$C$36+Calculator!$C$40+Constants!$B$24*Calculator!$C$27)))*Constants!$B$6) -> 14.661225
A47: Coral Cestus | B47: Fist | C47: LHT 50 | D47: 14 | E47: 0.1 | F47: LHT | G47: 9.5 | I47: 0 | K47: 0 | L47: =D47*(1+0.75*(IFERROR(G47*INDEX(Calculator!$E$6:$E$23,MATCH(F47,Calculator!$A$6:$A$23,0)),0)+IFERROR(I47*INDEX(Calculator!$E$6:$E$23,MATCH(H47,Calculator!$A$6:$A$23,0)),0)+IFERROR(K47*INDEX(Calculator!$E$6:$E$23,MATCH(J47,Calculator!$A$6:$A$23,0)),0))*(1+Constants!$B$23*Calculator!$C$27)/1000)*(1+Calculator!$C$45+Calculator!$C$37)*Calculator!$C$39*(1-(1-MIN(Calculator!$C$44,MIN(1,E47+Calculator!$E$6/10*Constants!$B$16+Calculator!$C$36+Calculator!$C$40+Constants!$B$24*Calculator!$C$27)))*Constants!$B$6) -> 13.68381
A48: Crescendo | B48: Twinblade | C48: MED 75 | D48: 22 | E48: 0.05 | F48: MED | G48: 6 | I48: 0 | K48: 0 | L48: =D48*(1+0.75*(IFERROR(G48*INDEX(Calculator!$E$6:$E$23,MATCH(F48,Calculator!$A$6:$A$23,0)),0)+IFERROR(I48*INDEX(Calculator!$E$6:$E$23,MATCH(H48,Calculator!$A$6:$A$23,0)),0)+IFERROR(K48*INDEX(Calculator!$E$6:$E$23,MATCH(J48,Calculator!$A$6:$A$23,0)),0))*(1+Constants!$B$23*Calculator!$C$27)/1000)*(1+Calculator!$C$45+Calculator!$C$37)*Calculator!$C$39*(1-(1-MIN(Calculator!$C$44,MIN(1,E48+Calculator!$E$6/10*Constants!$B$16+Calculator!$C$36+Calculator!$C$40+Constants!$B$24*Calculator!$C$27)))*Constants!$B$6) -> 32.079793
A49: Crescent Cleaver | B49: Greatsword | C49: HVY 45 · STR 10 | D49: 22 | E49: 0 | F49: HVY | G49: 8 | I49: 0 | K49: 0 | L49: =D49*(1+0.75*(IFERROR(G49*INDEX(Calculator!$E$6:$E$23,MATCH(F49,Calculator!$A$6:$A$23,0)),0)+IFERROR(I49*INDEX(Calculator!$E$6:$E$23,MATCH(H49,Calculator!$A$6:$A$23,0)),0)+IFERROR(K49*INDEX(Calculator!$E$6:$E$23,MATCH(J49,Calculator!$A$6:$A$23,0)),0))*(1+Constants!$B$23*Calculator!$C$27)/1000)*(1+Calculator!$C$45+Calculator!$C$37)*Calculator!$C$39*(1-(1-MIN(Calculator!$C$44,MIN(1,E49+Calculator!$E$6/10*Constants!$B$16+Calculator!$C$36+Calculator!$C$40+Constants!$B$24*Calculator!$C$27)))*Constants!$B$6) -> 20.66163
A50: Crucible Rapier | B50: Rapier | C50: LHT 75 | D50: 15 | E50: 0.2 | F50: LHT | G50: 8 | I50: 0 | K50: 0 | L50: =D50*(1+0.75*(IFERROR(G50*INDEX(Calculator!$E$6:$E$23,MATCH(F50,Calculator!$A$6:$A$23,0)),0)+IFERROR(I50*INDEX(Calculator!$E$6:$E$23,MATCH(H50,Calculator!$A$6:$A$23,0)),0)+IFERROR(K50*INDEX(Calculator!$E$6:$E$23,MATCH(J50,Calculator!$A$6:$A$23,0)),0))*(1+Constants!$B$23*Calculator!$C$27)/1000)*(1+Calculator!$C$45+Calculator!$C$37)*Calculator!$C$39*(1-(1-MIN(Calculator!$C$44,MIN(1,E50+Calculator!$E$6/10*Constants!$B$16+Calculator!$C$36+Calculator!$C$40+Constants!$B$24*Calculator!$C$27)))*Constants!$B$6) -> 15.234975
A51: Crypt Blade | B51: Greatsword | C51: HVY 40 · SDW 75 · Power 10 | D51: 22 | E51: 0 | F51: HVY | G51: 4 | H51: SDW | I51: 9 | K51: 0 | L51: =D51*(1+0.75*(IFERROR(G51*INDEX(Calculator!$E$6:$E$23,MATCH(F51,Calculator!$A$6:$A$23,0)),0)+IFERROR(I51*INDEX(Calculator!$E$6:$E$23,MATCH(H51,Calculator!$A$6:$A$23,0)),0)+IFERROR(K51*INDEX(Calculator!$E$6:$E$23,MATCH(J51,Calculator!$A$6:$A$23,0)),0))*(1+Constants!$B$23*Calculator!$C$27)/1000)*(1+Calculator!$C$45+Calculator!$C$37)*Calculator!$C$39*(1-(1-MIN(Calculator!$C$44,MIN(1,E51+Calculator!$E$6/10*Constants!$B$16+Calculator!$C$36+Calculator!$C$40+Constants!$B$24*Calculator!$C$27)))*Constants!$B$6) -> 20.66163
A52: Curved Blade of Winds | B52: Sword | C52: MED 40 · WND 75 · Power 10 | D52: 17.5 | E52: 0.15 | F52: MED | G52: 5 | H52: WND | I52: 5 | K52: 0 | L52: =D52*(1+0.75*(IFERROR(G52*INDEX(Calculator!$E$6:$E$23,MATCH(F52,Calculator!$A$6:$A$23,0)),0)+IFERROR(I52*INDEX(Calculator!$E$6:$E$23,MATCH(H52,Calculator!$A$6:$A$23,0)),0)+IFERROR(K52*INDEX(Calculator!$E$6:$E$23,MATCH(J52,Calculator!$A$6:$A$23,0)),0))*(1+Constants!$B$23*Calculator!$C$27)/1000)*(1+Calculator!$C$45+Calculator!$C$37)*Calculator!$C$39*(1-(1-MIN(Calculator!$C$44,MIN(1,E52+Calculator!$E$6/10*Constants!$B$16+Calculator!$C$36+Calculator!$C$40+Constants!$B$24*Calculator!$C$27)))*Constants!$B$6) -> 25.020379
A53: Darkalloy Greatsword | B53: Greatsword | C53: HVY 75 · STR 10 | D53: 26 | E53: 0.1 | F53: HVY | G53: 8 | I53: 0 | K53: 0 | L53: =D53*(1+0.75*(IFERROR(G53*INDEX(Calculator!$E$6:$E$23,MATCH(F53,Calculator!$A$6:$A$23,0)),0)+IFERROR(I53*INDEX(Calculator!$E$6:$E$23,MATCH(H53,Calculator!$A$6:$A$23,0)),0)+IFERROR(K53*INDEX(Calculator!$E$6:$E$23,MATCH(J53,Calculator!$A$6:$A$23,0)),0))*(1+Constants!$B$23*Calculator!$C$27)/1000)*(1+Calculator!$C$45+Calculator!$C$37)*Calculator!$C$39*(1-(1-MIN(Calculator!$C$44,MIN(1,E53+Calculator!$E$6/10*Constants!$B$16+Calculator!$C$36+Calculator!$C$40+Constants!$B$24*Calculator!$C$27)))*Constants!$B$6) -> 25.41279
A54: Darksteel Cleaver | B54: Greatsword | C54: HVY 100 · STR 10 | D54: 28.5 | E54: 0 | F54: HVY | G54: 8 | I54: 0 | K54: 0 | L54: =D54*(1+0.75*(IFERROR(G54*INDEX(Calculator!$E$6:$E$23,MATCH(F54,Calculator!$A$6:$A$23,0)),0)+IFERROR(I54*INDEX(Calculator!$E$6:$E$23,MATCH(H54,Calculator!$A$6:$A$23,0)),0)+IFERROR(K54*INDEX(Calculator!$E$6:$E$23,MATCH(J54,Calculator!$A$6:$A$23,0)),0))*(1+Constants!$B$23*Calculator!$C$27)/1000)*(1+Calculator!$C$45+Calculator!$C$37)*Calculator!$C$39*(1-(1-MIN(Calculator!$C$44,MIN(1,E54+Calculator!$E$6/10*Constants!$B$16+Calculator!$C$36+Calculator!$C$40+Constants!$B$24*Calculator!$C$27)))*Constants!$B$6) -> 26.766202
A55: Darksteel Greatsword | B55: Greatsword | C55: HVY 40 · STR 10 | D55: 26 | E55: 0 | F55: HVY | G55: 7 | I55: 0 | K55: 0 | L55: =D55*(1+0.75*(IFERROR(G55*INDEX(Calculator!$E$6:$E$23,MATCH(F55,Calculator!$A$6:$A$23,0)),0)+IFERROR(I55*INDEX(Calculator!$E$6:$E$23,MATCH(H55,Calculator!$A$6:$A$23,0)),0)+IFERROR(K55*INDEX(Calculator!$E$6:$E$23,MATCH(J55,Calculator!$A$6:$A$23,0)),0))*(1+Constants!$B$23*Calculator!$C$27)/1000)*(1+Calculator!$C$45+Calculator!$C$37)*Calculator!$C$39*(1-(1-MIN(Calculator!$C$44,MIN(1,E55+Calculator!$E$6/10*Constants!$B$16+Calculator!$C$36+Calculator!$C$40+Constants!$B$24*Calculator!$C$27)))*Constants!$B$6) -> 24.41829
A56: Dawnshot | B56: Pistol | C56: LHT 40 | D56: 14 | E56: 0 | F56: LHT | G56: 12 | I56: 0 | K56: 0 | L56: =D56*(1+0.75*(IFERROR(G56*INDEX(Calculator!$E$6:$E$23,MATCH(F56,Calculator!$A$6:$A$23,0)),0)+IFERROR(I56*INDEX(Calculator!$E$6:$E$23,MATCH(H56,Calculator!$A$6:$A$23,0)),0)+IFERROR(K56*INDEX(Calculator!$E$6:$E$23,MATCH(J56,Calculator!$A$6:$A$23,0)),0))*(1+Constants!$B$23*Calculator!$C$27)/1000)*(1+Calculator!$C$45+Calculator!$C$37)*Calculator!$C$39*(1-(1-MIN(Calculator!$C$44,MIN(1,E56+Calculator!$E$6/10*Constants!$B$16+Calculator!$C$36+Calculator!$C$40+Constants!$B$24*Calculator!$C$27)))*Constants!$B$6) -> 13.14831
A57: Death's Reverie | B57: Twinblade | C57: MED 75 | D57: 18 | E57: 0.15 | F57: MED | G57: 5 | I57: 0 | K57: 0 | L57: =D57*(1+0.75*(IFERROR(G57*INDEX(Calculator!$E$6:$E$23,MATCH(F57,Calculator!$A$6:$A$23,0)),0)+IFERROR(I57*INDEX(Calculator!$E$6:$E$23,MATCH(H57,Calculator!$A$6:$A$23,0)),0)+IFERROR(K57*INDEX(Calculator!$E$6:$E$23,MATCH(J57,Calculator!$A$6:$A$23,0)),0))*(1+Constants!$B$23*Calculator!$C$27)/1000)*(1+Calculator!$C$45+Calculator!$C$37)*Calculator!$C$39*(1-(1-MIN(Calculator!$C$44,MIN(1,E57+Calculator!$E$6/10*Constants!$B$16+Calculator!$C$36+Calculator!$C$40+Constants!$B$24*Calculator!$C$27)))*Constants!$B$6) -> 25.735247
A58: Deepspindle | B58: Rapier | C58: LHT 50 · SDW 75 | D58: 14 | E58: 0.2 | F58: LHT | G58: 4 | H58: SDW | I58: 9 | K58: 0 | L58: =D58*(1+0.75*(IFERROR(G58*INDEX(Calculator!$E$6:$E$23,MATCH(F58,Calculator!$A$6:$A$23,0)),0)+IFERROR(I58*INDEX(Calculator!$E$6:$E$23,MATCH(H58,Calculator!$A$6:$A$23,0)),0)+IFERROR(K58*INDEX(Calculator!$E$6:$E$23,MATCH(J58,Calculator!$A$6:$A$23,0)),0))*(1+Constants!$B$23*Calculator!$C$27)/1000)*(1+Calculator!$C$45+Calculator!$C$37)*Calculator!$C$39*(1-(1-MIN(Calculator!$C$44,MIN(1,E58+Calculator!$E$6/10*Constants!$B$16+Calculator!$C$36+Calculator!$C$40+Constants!$B$24*Calculator!$C$27)))*Constants!$B$6) -> 14.21931
A59: Depthsplitter | B59: Twinblade | C59: MED 40 | D59: 17 | E59: 0.05 | F59: MED | G59: 4.5 | I59: 0 | K59: 0 | L59: =D59*(1+0.75*(IFERROR(G59*INDEX(Calculator!$E$6:$E$23,MATCH(F59,Calculator!$A$6:$A$23,0)),0)+IFERROR(I59*INDEX(Calculator!$E$6:$E$23,MATCH(H59,Calculator!$A$6:$A$23,0)),0)+IFERROR(K59*INDEX(Calculator!$E$6:$E$23,MATCH(J59,Calculator!$A$6:$A$23,0)),0))*(1+Constants!$B$23*Calculator!$C$27)/1000)*(1+Calculator!$C$45+Calculator!$C$37)*Calculator!$C$39*(1-(1-MIN(Calculator!$C$44,MIN(1,E59+Calculator!$E$6/10*Constants!$B$16+Calculator!$C$36+Calculator!$C$40+Constants!$B$24*Calculator!$C$27)))*Constants!$B$6) -> 22.664431
A60: Dissonant Chimecaller | B60: Greathammer | C60: HVY 80 | D60: 26 | E60: 0.1 | F60: HVY | G60: 8.4 | I60: 0 | K60: 0 | L60: =D60*(1+0.75*(IFERROR(G60*INDEX(Calculator!$E$6:$E$23,MATCH(F60,Calculator!$A$6:$A$23,0)),0)+IFERROR(I60*INDEX(Calculator!$E$6:$E$23,MATCH(H60,Calculator!$A$6:$A$23,0)),0)+IFERROR(K60*INDEX(Calculator!$E$6:$E$23,MATCH(J60,Calculator!$A$6:$A$23,0)),0))*(1+Constants!$B$23*Calculator!$C$27)/1000)*(1+Calculator!$C$45+Calculator!$C$37)*Calculator!$C$39*(1-(1-MIN(Calculator!$C$44,MIN(1,E60+Calculator!$E$6/10*Constants!$B$16+Calculator!$C$36+Calculator!$C$40+Constants!$B$24*Calculator!$C$27)))*Constants!$B$6) -> 25.41279
A61: Dormant Splinter | B61: Sword | C61: MED 5 | D61: 5 | E61: 0.1 | F61: MED | G61: 7 | I61: 0 | K61: 0 | L61: =D61*(1+0.75*(IFERROR(G61*INDEX(Calculator!$E$6:$E$23,MATCH(F61,Calculator!$A$6:$A$23,0)),0)+IFERROR(I61*INDEX(Calculator!$E$6:$E$23,MATCH(H61,Calculator!$A$6:$A$23,0)),0)+IFERROR(K61*INDEX(Calculator!$E$6:$E$23,MATCH(J61,Calculator!$A$6:$A$23,0)),0))*(1+Constants!$B$23*Calculator!$C$27)/1000)*(1+Calculator!$C$45+Calculator!$C$37)*Calculator!$C$39*(1-(1-MIN(Calculator!$C$44,MIN(1,E61+Calculator!$E$6/10*Constants!$B$16+Calculator!$C$36+Calculator!$C$40+Constants!$B$24*Calculator!$C$27)))*Constants!$B$6) -> 7.8612511
A62: Dragoon | B62: Pistol | C62: LHT 65 | D62: 16 | E62: 0 | F62: LHT | G62: 12 | I62: 0 | K62: 0 | L62: =D62*(1+0.75*(IFERROR(G62*INDEX(Calculator!$E$6:$E$23,MATCH(F62,Calculator!$A$6:$A$23,0)),0)+IFERROR(I62*INDEX(Calculator!$E$6:$E$23,MATCH(H62,Calculator!$A$6:$A$23,0)),0)+IFERROR(K62*INDEX(Calculator!$E$6:$E$23,MATCH(J62,Calculator!$A$6:$A$23,0)),0))*(1+Constants!$B$23*Calculator!$C$27)/1000)*(1+Calculator!$C$45+Calculator!$C$37)*Calculator!$C$39*(1-(1-MIN(Calculator!$C$44,MIN(1,E62+Calculator!$E$6/10*Constants!$B$16+Calculator!$C$36+Calculator!$C$40+Constants!$B$24*Calculator!$C$27)))*Constants!$B$6) -> 15.02664
A63: Drakemaw Gauntlets | B63: Fist | C63: LHT 75 | D63: 15 | E63: 0.1 | F63: LHT | G63: 8 | I63: 0 | K63: 0 | L63: =D63*(1+0.75*(IFERROR(G63*INDEX(Calculator!$E$6:$E$23,MATCH(F63,Calculator!$A$6:$A$23,0)),0)+IFERROR(I63*INDEX(Calculator!$E$6:$E$23,MATCH(H63,Calculator!$A$6:$A$23,0)),0)+IFERROR(K63*INDEX(Calculator!$E$6:$E$23,MATCH(J63,Calculator!$A$6:$A$23,0)),0))*(1+Constants!$B$23*Calculator!$C$27)/1000)*(1+Calculator!$C$45+Calculator!$C$37)*Calculator!$C$39*(1-(1-MIN(Calculator!$C$44,MIN(1,E63+Calculator!$E$6/10*Constants!$B$16+Calculator!$C$36+Calculator!$C$40+Constants!$B$24*Calculator!$C$27)))*Constants!$B$6) -> 14.661225
A64: Duskguard Axe | B64: Greataxe | C64: HVY 75 · STR 10 · Power 10 | D64: 26 | E64: 0.15 | F64: HVY | G64: 8 | I64: 0 | K64: 0 | L64: =D64*(1+0.75*(IFERROR(G64*INDEX(Calculator!$E$6:$E$23,MATCH(F64,Calculator!$A$6:$A$23,0)),0)+IFERROR(I64*INDEX(Calculator!$E$6:$E$23,MATCH(H64,Calculator!$A$6:$A$23,0)),0)+IFERROR(K64*INDEX(Calculator!$E$6:$E$23,MATCH(J64,Calculator!$A$6:$A$23,0)),0))*(1+Constants!$B$23*Calculator!$C$27)/1000)*(1+Calculator!$C$45+Calculator!$C$37)*Calculator!$C$39*(1-(1-MIN(Calculator!$C$44,MIN(1,E64+Calculator!$E$6/10*Constants!$B$16+Calculator!$C$36+Calculator!$C$40+Constants!$B$24*Calculator!$C$27)))*Constants!$B$6) -> 25.91004
A65: Duskpole | B65: Staff | C65: MED 40 | D65: 17 | E65: 0.05 | F65: MED | G65: 7 | H65: WLL | I65: 1 | K65: 0 | L65: =D65*(1+0.75*(IFERROR(G65*INDEX(Calculator!$E$6:$E$23,MATCH(F65,Calculator!$A$6:$A$23,0)),0)+IFERROR(I65*INDEX(Calculator!$E$6:$E$23,MATCH(H65,Calculator!$A$6:$A$23,0)),0)+IFERROR(K65*INDEX(Calculator!$E$6:$E$23,MATCH(J65,Calculator!$A$6:$A$23,0)),0))*(1+Constants!$B$23*Calculator!$C$27)/1000)*(1+Calculator!$C$45+Calculator!$C$37)*Calculator!$C$39*(1-(1-MIN(Calculator!$C$44,MIN(1,E65+Calculator!$E$6/10*Constants!$B$16+Calculator!$C$36+Calculator!$C$40+Constants!$B$24*Calculator!$C$27)))*Constants!$B$6) -> 26.543953
A66: Duskshot | B66: Pistol | C66: LHT 40 | D66: 13 | E66: 0.05 | F66: LHT | G66: 11 | I66: 0 | K66: 0 | L66: =D66*(1+0.75*(IFERROR(G66*INDEX(Calculator!$E$6:$E$23,MATCH(F66,Calculator!$A$6:$A$23,0)),0)+IFERROR(I66*INDEX(Calculator!$E$6:$E$23,MATCH(H66,Calculator!$A$6:$A$23,0)),0)+IFERROR(K66*INDEX(Calculator!$E$6:$E$23,MATCH(J66,Calculator!$A$6:$A$23,0)),0))*(1+Constants!$B$23*Calculator!$C$27)/1000)*(1+Calculator!$C$45+Calculator!$C$37)*Calculator!$C$39*(1-(1-MIN(Calculator!$C$44,MIN(1,E66+Calculator!$E$6/10*Constants!$B$16+Calculator!$C$36+Calculator!$C$40+Constants!$B$24*Calculator!$C$27)))*Constants!$B$6) -> 12.45777
A67: Edenbrand Hellcoil | B67: Greatcannon | C67: HVY 75 · STR 30 | D67: 27 | E67: 0 | F67: HVY | G67: 8.3 | I67: 0 | K67: 0 | L67: =D67*(1+0.75*(IFERROR(G67*INDEX(Calculator!$E$6:$E$23,MATCH(F67,Calculator!$A$6:$A$23,0)),0)+IFERROR(I67*INDEX(Calculator!$E$6:$E$23,MATCH(H67,Calculator!$A$6:$A$23,0)),0)+IFERROR(K67*INDEX(Calculator!$E$6:$E$23,MATCH(J67,Calculator!$A$6:$A$23,0)),0))*(1+Constants!$B$23*Calculator!$C$27)/1000)*(1+Calculator!$C$45+Calculator!$C$37)*Calculator!$C$39*(1-(1-MIN(Calculator!$C$44,MIN(1,E67+Calculator!$E$6/10*Constants!$B$16+Calculator!$C$36+Calculator!$C$40+Constants!$B$24*Calculator!$C$27)))*Constants!$B$6) -> 25.357455
A68: Enforcer's Axe | B68: Greataxe | C68: HVY 75 | D68: 26 | E68: 0.1 | F68: HVY | G68: 9 | I68: 0 | K68: 0 | L68: =D68*(1+0.75*(IFERROR(G68*INDEX(Calculator!$E$6:$E$23,MATCH(F68,Calculator!$A$6:$A$23,0)),0)+IFERROR(I68*INDEX(Calculator!$E$6:$E$23,MATCH(H68,Calculator!$A$6:$A$23,0)),0)+IFERROR(K68*INDEX(Calculator!$E$6:$E$23,MATCH(J68,Calculator!$A$6:$A$23,0)),0))*(1+Constants!$B$23*Calculator!$C$27)/1000)*(1+Calculator!$C$45+Calculator!$C$37)*Calculator!$C$39*(1-(1-MIN(Calculator!$C$44,MIN(1,E68+Calculator!$E$6/10*Constants!$B$16+Calculator!$C$36+Calculator!$C$40+Constants!$B$24*Calculator!$C$27)))*Constants!$B$6) -> 25.41279
A69: Enforcer's Blade | B69: Greatsword | C69: HVY 80 · STR 25 | D69: 25.5 | E69: 0.05 | F69: HVY | G69: 10 | I69: 0 | K69: 0 | L69: =D69*(1+0.75*(IFERROR(G69*INDEX(Calculator!$E$6:$E$23,MATCH(F69,Calculator!$A$6:$A$23,0)),0)+IFERROR(I69*INDEX(Calculator!$E$6:$E$23,MATCH(H69,Calculator!$A$6:$A$23,0)),0)+IFERROR(K69*INDEX(Calculator!$E$6:$E$23,MATCH(J69,Calculator!$A$6:$A$23,0)),0))*(1+Constants!$B$23*Calculator!$C$27)/1000)*(1+Calculator!$C$45+Calculator!$C$37)*Calculator!$C$39*(1-(1-MIN(Calculator!$C$44,MIN(1,E69+Calculator!$E$6/10*Constants!$B$16+Calculator!$C$36+Calculator!$C$40+Constants!$B$24*Calculator!$C$27)))*Constants!$B$6) -> 24.436395
A70: Enforcer's Hammer | B70: Greathammer | C70: HVY 80 · STR 25 | D70: 25 | E70: 0.1 | F70: HVY | G70: 9 | I70: 0 | K70: 0 | L70: =D70*(1+0.75*(IFERROR(G70*INDEX(Calculator!$E$6:$E$23,MATCH(F70,Calculator!$A$6:$A$23,0)),0)+IFERROR(I70*INDEX(Calculator!$E$6:$E$23,MATCH(H70,Calculator!$A$6:$A$23,0)),0)+IFERROR(K70*INDEX(Calculator!$E$6:$E$23,MATCH(J70,Calculator!$A$6:$A$23,0)),0))*(1+Constants!$B$23*Calculator!$C$27)/1000)*(1+Calculator!$C$45+Calculator!$C$37)*Calculator!$C$39*(1-(1-MIN(Calculator!$C$44,MIN(1,E70+Calculator!$E$6/10*Constants!$B$16+Calculator!$C$36+Calculator!$C$40+Constants!$B$24*Calculator!$C$27)))*Constants!$B$6) -> 24.435375
A71: Evanspear Greataxe | B71: Greataxe | C71: HVY 70 | D71: 24 | E71: 0 | F71: HVY | G71: 9.5 | I71: 0 | K71: 0 | L71: =D71*(1+0.75*(IFERROR(G71*INDEX(Calculator!$E$6:$E$23,MATCH(F71,Calculator!$A$6:$A$23,0)),0)+IFERROR(I71*INDEX(Calculator!$E$6:$E$23,MATCH(H71,Calculator!$A$6:$A$23,0)),0)+IFERROR(K71*INDEX(Calculator!$E$6:$E$23,MATCH(J71,Calculator!$A$6:$A$23,0)),0))*(1+Constants!$B$23*Calculator!$C$27)/1000)*(1+Calculator!$C$45+Calculator!$C$37)*Calculator!$C$39*(1-(1-MIN(Calculator!$C$44,MIN(1,E71+Calculator!$E$6/10*Constants!$B$16+Calculator!$C$36+Calculator!$C$40+Constants!$B$24*Calculator!$C$27)))*Constants!$B$6) -> 22.53996
A72: Eye of Malice | B72: Sword | C72: MED 75 | D72: 20 | E72: 0.25 | F72: MED | G72: 7.7 | I72: 0 | K72: 0 | L72: =D72*(1+0.75*(IFERROR(G72*INDEX(Calculator!$E$6:$E$23,MATCH(F72,Calculator!$A$6:$A$23,0)),0)+IFERROR(I72*INDEX(Calculator!$E$6:$E$23,MATCH(H72,Calculator!$A$6:$A$23,0)),0)+IFERROR(K72*INDEX(Calculator!$E$6:$E$23,MATCH(J72,Calculator!$A$6:$A$23,0)),0))*(1+Constants!$B$23*Calculator!$C$27)/1000)*(1+Calculator!$C$45+Calculator!$C$37)*Calculator!$C$39*(1-(1-MIN(Calculator!$C$44,MIN(1,E72+Calculator!$E$6/10*Constants!$B$16+Calculator!$C$36+Calculator!$C$40+Constants!$B$24*Calculator!$C$27)))*Constants!$B$6) -> 34.550355
A73: Eyes of Ethiron | B73: Sword | C73: MED 40 · WND 40 · SDW 40 · Power 10 | D73: 16.5 | E73: 0.15 | F73: MED | G73: 4 | H73: SDW | I73: 4.5 | J73: WND | K73: 4.5 | L73: =D73*(1+0.75*(IFERROR(G73*INDEX(Calculator!$E$6:$E$23,MATCH(F73,Calculator!$A$6:$A$23,0)),0)+IFERROR(I73*INDEX(Calculator!$E$6:$E$23,MATCH(H73,Calculator!$A$6:$A$23,0)),0)+IFERROR(K73*INDEX(Calculator!$E$6:$E$23,MATCH(J73,Calculator!$A$6:$A$23,0)),0))*(1+Constants!$B$23*Calculator!$C$27)/1000)*(1+Calculator!$C$45+Calculator!$C$37)*Calculator!$C$39*(1-(1-MIN(Calculator!$C$44,MIN(1,E73+Calculator!$E$6/10*Constants!$B$16+Calculator!$C$36+Calculator!$C$40+Constants!$B$24*Calculator!$C$27)))*Constants!$B$6) -> 22.161096
A74: Falchion | B74: Sword | C74: MED 20 | D74: 16 | E74: 0 | F74: MED | G74: 6 | I74: 0 | K74: 0 | L74: =D74*(1+0.75*(IFERROR(G74*INDEX(Calculator!$E$6:$E$23,MATCH(F74,Calculator!$A$6:$A$23,0)),0)+IFERROR(I74*INDEX(Calculator!$E$6:$E$23,MATCH(H74,Calculator!$A$6:$A$23,0)),0)+IFERROR(K74*INDEX(Calculator!$E$6:$E$23,MATCH(J74,Calculator!$A$6:$A$23,0)),0))*(1+Constants!$B$23*Calculator!$C$27)/1000)*(1+Calculator!$C$45+Calculator!$C$37)*Calculator!$C$39*(1-(1-MIN(Calculator!$C$44,MIN(1,E74+Calculator!$E$6/10*Constants!$B$16+Calculator!$C$36+Calculator!$C$40+Constants!$B$24*Calculator!$C$27)))*Constants!$B$6) -> 22.865136
A75: First Light | B75: Greatsword | C75: HVY 75 | D75: 23 | E75: 0.15 | F75: HVY | G75: 8 | I75: 0 | K75: 0 | L75: =D75*(1+0.75*(IFERROR(G75*INDEX(Calculator!$E$6:$E$23,MATCH(F75,Calculator!$A$6:$A$23,0)),0)+IFERROR(I75*INDEX(Calculator!$E$6:$E$23,MATCH(H75,Calculator!$A$6:$A$23,0)),0)+IFERROR(K75*INDEX(Calculator!$E$6:$E$23,MATCH(J75,Calculator!$A$6:$A$23,0)),0))*(1+Constants!$B$23*Calculator!$C$27)/1000)*(1+Calculator!$C$45+Calculator!$C$37)*Calculator!$C$39*(1-(1-MIN(Calculator!$C$44,MIN(1,E75+Calculator!$E$6/10*Constants!$B$16+Calculator!$C$36+Calculator!$C$40+Constants!$B$24*Calculator!$C$27)))*Constants!$B$6) -> 22.92042
A76: Flamekeeper Cestus | B76: Fist | C76: LHT 65 | D76: 15.5 | E76: 0.05 | F76: LHT | G76: 9.5 | I76: 0 | K76: 0 | L76: =D76*(1+0.75*(IFERROR(G76*INDEX(Calculator!$E$6:$E$23,MATCH(F76,Calculator!$A$6:$A$23,0)),0)+IFERROR(I76*INDEX(Calculator!$E$6:$E$23,MATCH(H76,Calculator!$A$6:$A$23,0)),0)+IFERROR(K76*INDEX(Calculator!$E$6:$E$23,MATCH(J76,Calculator!$A$6:$A$23,0)),0))*(1+Constants!$B$23*Calculator!$C$27)/1000)*(1+Calculator!$C$45+Calculator!$C$37)*Calculator!$C$39*(1-(1-MIN(Calculator!$C$44,MIN(1,E76+Calculator!$E$6/10*Constants!$B$16+Calculator!$C$36+Calculator!$C$40+Constants!$B$24*Calculator!$C$27)))*Constants!$B$6) -> 14.853495
A77: Flareblood Kamas | B77: Dagger | C77: LHT 60 · INT 30 | D77: 14 | E77: 0.3 | F77: LHT | G77: 8 | H77: INT | I77: 1.5 | J77: BLD | K77: 3 | L77: =D77*(1+0.75*(IFERROR(G77*INDEX(Calculator!$E$6:$E$23,MATCH(F77,Calculator!$A$6:$A$23,0)),0)+IFERROR(I77*INDEX(Calculator!$E$6:$E$23,MATCH(H77,Calculator!$A$6:$A$23,0)),0)+IFERROR(K77*INDEX(Calculator!$E$6:$E$23,MATCH(J77,Calculator!$A$6:$A$23,0)),0))*(1+Constants!$B$23*Calculator!$C$27)/1000)*(1+Calculator!$C$45+Calculator!$C$37)*Calculator!$C$39*(1-(1-MIN(Calculator!$C$44,MIN(1,E77+Calculator!$E$6/10*Constants!$B$16+Calculator!$C$36+Calculator!$C$40+Constants!$B$24*Calculator!$C$27)))*Constants!$B$6) -> 14.75481
A78: Flintlock | B78: Pistol | C78: LHT 20 | D78: 11 | E78: 0 | F78: LHT | G78: 12 | I78: 0 | K78: 0 | L78: =D78*(1+0.75*(IFERROR(G78*INDEX(Calculator!$E$6:$E$23,MATCH(F78,Calculator!$A$6:$A$23,0)),0)+IFERROR(I78*INDEX(Calculator!$E$6:$E$23,MATCH(H78,Calculator!$A$6:$A$23,0)),0)+IFERROR(K78*INDEX(Calculator!$E$6:$E$23,MATCH(J78,Calculator!$A$6:$A$23,0)),0))*(1+Constants!$B$23*Calculator!$C$27)/1000)*(1+Calculator!$C$45+Calculator!$C$37)*Calculator!$C$39*(1-(1-MIN(Calculator!$C$44,MIN(1,E78+Calculator!$E$6/10*Constants!$B$16+Calculator!$C$36+Calculator!$C$40+Constants!$B$24*Calculator!$C$27)))*Constants!$B$6) -> 10.330815
A79: Fondant Splitter | B79: Sword | C79: MED 65 · Power 10 | D79: 15 | E79: 0.05 | F79: MED | G79: 8 | I79: 0 | K79: 0 | L79: =D79*(1+0.75*(IFERROR(G79*INDEX(Calculator!$E$6:$E$23,MATCH(F79,Calculator!$A$6:$A$23,0)),0)+IFERROR(I79*INDEX(Calculator!$E$6:$E$23,MATCH(H79,Calculator!$A$6:$A$23,0)),0)+IFERROR(K79*INDEX(Calculator!$E$6:$E$23,MATCH(J79,Calculator!$A$6:$A$23,0)),0))*(1+Constants!$B$23*Calculator!$C$27)/1000)*(1+Calculator!$C$45+Calculator!$C$37)*Calculator!$C$39*(1-(1-MIN(Calculator!$C$44,MIN(1,E79+Calculator!$E$6/10*Constants!$B$16+Calculator!$C$36+Calculator!$C$40+Constants!$B$24*Calculator!$C$27)))*Constants!$B$6) -> 24.371998
A80: Fool's Tankard | B80: Dagger | C80: LHT 40 | D80: 12.5 | E80: 0 | F80: LHT | G80: 12 | I80: 0 | K80: 0 | L80: =D80*(1+0.75*(IFERROR(G80*INDEX(Calculator!$E$6:$E$23,MATCH(F80,Calculator!$A$6:$A$23,0)),0)+IFERROR(I80*INDEX(Calculator!$E$6:$E$23,MATCH(H80,Calculator!$A$6:$A$23,0)),0)+IFERROR(K80*INDEX(Calculator!$E$6:$E$23,MATCH(J80,Calculator!$A$6:$A$23,0)),0))*(1+Constants!$B$23*Calculator!$C$27)/1000)*(1+Calculator!$C$45+Calculator!$C$37)*Calculator!$C$39*(1-(1-MIN(Calculator!$C$44,MIN(1,E80+Calculator!$E$6/10*Constants!$B$16+Calculator!$C$36+Calculator!$C$40+Constants!$B$24*Calculator!$C$27)))*Constants!$B$6) -> 11.739562
A81: Forge Greathammer | B81: Greathammer | C81: HVY 55 · STR 10 | D81: 24 | E81: 0 | F81: HVY | G81: 8 | I81: 0 | K81: 0 | L81: =D81*(1+0.75*(IFERROR(G81*INDEX(Calculator!$E$6:$E$23,MATCH(F81,Calculator!$A$6:$A$23,0)),0)+IFERROR(I81*INDEX(Calculator!$E$6:$E$23,MATCH(H81,Calculator!$A$6:$A$23,0)),0)+IFERROR(K81*INDEX(Calculator!$E$6:$E$23,MATCH(J81,Calculator!$A$6:$A$23,0)),0))*(1+Constants!$B$23*Calculator!$C$27)/1000)*(1+Calculator!$C$45+Calculator!$C$37)*Calculator!$C$39*(1-(1-MIN(Calculator!$C$44,MIN(1,E81+Calculator!$E$6/10*Constants!$B$16+Calculator!$C$36+Calculator!$C$40+Constants!$B$24*Calculator!$C$27)))*Constants!$B$6) -> 22.53996
A82: Forgotten Gladius | B82: Sword | C82: MED 65 | D82: 18 | E82: 0.13 | F82: MED | G82: 7.5 | I82: 0 | K82: 0 | L82: =D82*(1+0.75*(IFERROR(G82*INDEX(Calculator!$E$6:$E$23,MATCH(F82,Calculator!$A$6:$A$23,0)),0)+IFERROR(I82*INDEX(Calculator!$E$6:$E$23,MATCH(H82,Calculator!$A$6:$A$23,0)),0)+IFERROR(K82*INDEX(Calculator!$E$6:$E$23,MATCH(J82,Calculator!$A$6:$A$23,0)),0))*(1+Constants!$B$23*Calculator!$C$27)/1000)*(1+Calculator!$C$45+Calculator!$C$37)*Calculator!$C$39*(1-(1-MIN(Calculator!$C$44,MIN(1,E82+Calculator!$E$6/10*Constants!$B$16+Calculator!$C$36+Calculator!$C$40+Constants!$B$24*Calculator!$C$27)))*Constants!$B$6) -> 29.406523
A83: Formless Shard | B83: Dagger | C83: no stat requirement | D83: 24 | E83: 0.05 | F83: HVY | G83: 8 | I83: 0 | K83: 0 | L83: =D83*(1+0.75*(IFERROR(G83*INDEX(Calculator!$E$6:$E$23,MATCH(F83,Calculator!$A$6:$A$23,0)),0)+IFERROR(I83*INDEX(Calculator!$E$6:$E$23,MATCH(H83,Calculator!$A$6:$A$23,0)),0)+IFERROR(K83*INDEX(Calculator!$E$6:$E$23,MATCH(J83,Calculator!$A$6:$A$23,0)),0))*(1+Constants!$B$23*Calculator!$C$27)/1000)*(1+Calculator!$C$45+Calculator!$C$37)*Calculator!$C$39*(1-(1-MIN(Calculator!$C$44,MIN(1,E83+Calculator!$E$6/10*Constants!$B$16+Calculator!$C$36+Calculator!$C$40+Constants!$B$24*Calculator!$C$27)))*Constants!$B$6) -> 22.99896
A84: Fractine | B84: Greatsword | C84: HVY 80 · INT 40 · Power 10 | D84: 22 | E84: 0.25 | F84: HVY | G84: 7 | H84: INT | I84: 4 | K84: 0 | L84: =D84*(1+0.75*(IFERROR(G84*INDEX(Calculator!$E$6:$E$23,MATCH(F84,Calculator!$A$6:$A$23,0)),0)+IFERROR(I84*INDEX(Calculator!$E$6:$E$23,MATCH(H84,Calculator!$A$6:$A$23,0)),0)+IFERROR(K84*INDEX(Calculator!$E$6:$E$23,MATCH(J84,Calculator!$A$6:$A$23,0)),0))*(1+Constants!$B$23*Calculator!$C$27)/1000)*(1+Calculator!$C$45+Calculator!$C$37)*Calculator!$C$39*(1-(1-MIN(Calculator!$C$44,MIN(1,E84+Calculator!$E$6/10*Constants!$B$16+Calculator!$C$36+Calculator!$C$40+Constants!$B$24*Calculator!$C$27)))*Constants!$B$6) -> 22.76538
A85: Frost Gauntlets | B85: Fist | C85: LHT 30 | D85: 14 | E85: 0.05 | F85: LHT | G85: 9 | I85: 0 | K85: 0 | L85: =D85*(1+0.75*(IFERROR(G85*INDEX(Calculator!$E$6:$E$23,MATCH(F85,Calculator!$A$6:$A$23,0)),0)+IFERROR(I85*INDEX(Calculator!$E$6:$E$23,MATCH(H85,Calculator!$A$6:$A$23,0)),0)+IFERROR(K85*INDEX(Calculator!$E$6:$E$23,MATCH(J85,Calculator!$A$6:$A$23,0)),0))*(1+Constants!$B$23*Calculator!$C$27)/1000)*(1+Calculator!$C$45+Calculator!$C$37)*Calculator!$C$39*(1-(1-MIN(Calculator!$C$44,MIN(1,E85+Calculator!$E$6/10*Constants!$B$16+Calculator!$C$36+Calculator!$C$40+Constants!$B$24*Calculator!$C$27)))*Constants!$B$6) -> 13.41606
A86: Frostthorn | B86: Dagger | C86: LHT 90 | D86: 14.5 | E86: 0.15 | F86: LHT | G86: 8 | H86: ICE | I86: 1 | K86: 0 | L86: =D86*(1+0.75*(IFERROR(G86*INDEX(Calculator!$E$6:$E$23,MATCH(F86,Calculator!$A$6:$A$23,0)),0)+IFERROR(I86*INDEX(Calculator!$E$6:$E$23,MATCH(H86,Calculator!$A$6:$A$23,0)),0)+IFERROR(K86*INDEX(Calculator!$E$6:$E$23,MATCH(J86,Calculator!$A$6:$A$23,0)),0))*(1+Constants!$B$23*Calculator!$C$27)/1000)*(1+Calculator!$C$45+Calculator!$C$37)*Calculator!$C$39*(1-(1-MIN(Calculator!$C$44,MIN(1,E86+Calculator!$E$6/10*Constants!$B$16+Calculator!$C$36+Calculator!$C$40+Constants!$B$24*Calculator!$C$27)))*Constants!$B$6) -> 14.44983
A87: Gale Pale | B87: Greathammer | C87: HVY 75 | D87: 23 | E87: 0.15 | F87: HVY | G87: 9 | I87: 0 | K87: 0 | L87: =D87*(1+0.75*(IFERROR(G87*INDEX(Calculator!$E$6:$E$23,MATCH(F87,Calculator!$A$6:$A$23,0)),0)+IFERROR(I87*INDEX(Calculator!$E$6:$E$23,MATCH(H87,Calculator!$A$6:$A$23,0)),0)+IFERROR(K87*INDEX(Calculator!$E$6:$E$23,MATCH(J87,Calculator!$A$6:$A$23,0)),0))*(1+Constants!$B$23*Calculator!$C$27)/1000)*(1+Calculator!$C$45+Calculator!$C$37)*Calculator!$C$39*(1-(1-MIN(Calculator!$C$44,MIN(1,E87+Calculator!$E$6/10*Constants!$B$16+Calculator!$C$36+Calculator!$C$40+Constants!$B$24*Calculator!$C$27)))*Constants!$B$6) -> 22.92042
A88: Gaunts of Enmity | B88: Fist | C88: LHT 75 · FTD 10 | D88: 15 | E88: 0 | F88: LHT | G88: 9.5 | I88: 0 | K88: 0 | L88: =D88*(1+0.75*(IFERROR(G88*INDEX(Calculator!$E$6:$E$23,MATCH(F88,Calculator!$A$6:$A$23,0)),0)+IFERROR(I88*INDEX(Calculator!$E$6:$E$23,MATCH(H88,Calculator!$A$6:$A$23,0)),0)+IFERROR(K88*INDEX(Calculator!$E$6:$E$23,MATCH(J88,Calculator!$A$6:$A$23,0)),0))*(1+Constants!$B$23*Calculator!$C$27)/1000)*(1+Calculator!$C$45+Calculator!$C$37)*Calculator!$C$39*(1-(1-MIN(Calculator!$C$44,MIN(1,E88+Calculator!$E$6/10*Constants!$B$16+Calculator!$C$36+Calculator!$C$40+Constants!$B$24*Calculator!$C$27)))*Constants!$B$6) -> 14.087475
A89: Gilded Knife | B89: Dagger | C89: LHT 25 | D89: 14.5 | E89: 0 | F89: LHT | G89: 8 | I89: 0 | K89: 0 | L89: =D89*(1+0.75*(IFERROR(G89*INDEX(Calculator!$E$6:$E$23,MATCH(F89,Calculator!$A$6:$A$23,0)),0)+IFERROR(I89*INDEX(Calculator!$E$6:$E$23,MATCH(H89,Calculator!$A$6:$A$23,0)),0)+IFERROR(K89*INDEX(Calculator!$E$6:$E$23,MATCH(J89,Calculator!$A$6:$A$23,0)),0))*(1+Constants!$B$23*Calculator!$C$27)/1000)*(1+Calculator!$C$45+Calculator!$C$37)*Calculator!$C$39*(1-(1-MIN(Calculator!$C$44,MIN(1,E89+Calculator!$E$6/10*Constants!$B$16+Calculator!$C$36+Calculator!$C$40+Constants!$B$24*Calculator!$C$27)))*Constants!$B$6) -> 13.617892
A90: Golden Swordfish | B90: Rapier | C90: LHT 75 | D90: 15 | E90: 0.2 | F90: LHT | G90: 8 | I90: 0 | K90: 0 | L90: =D90*(1+0.75*(IFERROR(G90*INDEX(Calculator!$E$6:$E$23,MATCH(F90,Calculator!$A$6:$A$23,0)),0)+IFERROR(I90*INDEX(Calculator!$E$6:$E$23,MATCH(H90,Calculator!$A$6:$A$23,0)),0)+IFERROR(K90*INDEX(Calculator!$E$6:$E$23,MATCH(J90,Calculator!$A$6:$A$23,0)),0))*(1+Constants!$B$23*Calculator!$C$27)/1000)*(1+Calculator!$C$45+Calculator!$C$37)*Calculator!$C$39*(1-(1-MIN(Calculator!$C$44,MIN(1,E90+Calculator!$E$6/10*Constants!$B$16+Calculator!$C$36+Calculator!$C$40+Constants!$B$24*Calculator!$C$27)))*Constants!$B$6) -> 15.234975
A91: Gran Sudaruska | B91: Greataxe | C91: HVY 40 · ICE 75 · Power 10 | D91: 24 | E91: 0 | F91: HVY | G91: 4 | H91: ICE | I91: 6 | K91: 0 | L91: =D91*(1+0.75*(IFERROR(G91*INDEX(Calculator!$E$6:$E$23,MATCH(F91,Calculator!$A$6:$A$23,0)),0)+IFERROR(I91*INDEX(Calculator!$E$6:$E$23,MATCH(H91,Calculator!$A$6:$A$23,0)),0)+IFERROR(K91*INDEX(Calculator!$E$6:$E$23,MATCH(J91,Calculator!$A$6:$A$23,0)),0))*(1+Constants!$B$23*Calculator!$C$27)/1000)*(1+Calculator!$C$45+Calculator!$C$37)*Calculator!$C$39*(1-(1-MIN(Calculator!$C$44,MIN(1,E91+Calculator!$E$6/10*Constants!$B$16+Calculator!$C$36+Calculator!$C$40+Constants!$B$24*Calculator!$C$27)))*Constants!$B$6) -> 22.53996
A92: Great Maul | B92: Greathammer | C92: HVY 75 · STR 30 | D92: 25 | E92: 0.05 | F92: HVY | G92: 8.3 | I92: 0 | K92: 0 | L92: =D92*(1+0.75*(IFERROR(G92*INDEX(Calculator!$E$6:$E$23,MATCH(F92,Calculator!$A$6:$A$23,0)),0)+IFERROR(I92*INDEX(Calculator!$E$6:$E$23,MATCH(H92,Calculator!$A$6:$A$23,0)),0)+IFERROR(K92*INDEX(Calculator!$E$6:$E$23,MATCH(J92,Calculator!$A$6:$A$23,0)),0))*(1+Constants!$B$23*Calculator!$C$27)/1000)*(1+Calculator!$C$45+Calculator!$C$37)*Calculator!$C$39*(1-(1-MIN(Calculator!$C$44,MIN(1,E92+Calculator!$E$6/10*Constants!$B$16+Calculator!$C$36+Calculator!$C$40+Constants!$B$24*Calculator!$C$27)))*Constants!$B$6) -> 23.95725
A93: Gremorian Longspear | B93: Spear | C93: MED 20 | D93: 18 | E93: 0 | F93: MED | G93: 4 | I93: 0 | K93: 0 | L93: =D93*(1+0.75*(IFERROR(G93*INDEX(Calculator!$E$6:$E$23,MATCH(F93,Calculator!$A$6:$A$23,0)),0)+IFERROR(I93*INDEX(Calculator!$E$6:$E$23,MATCH(H93,Calculator!$A$6:$A$23,0)),0)+IFERROR(K93*INDEX(Calculator!$E$6:$E$23,MATCH(J93,Calculator!$A$6:$A$23,0)),0))*(1+Constants!$B$23*Calculator!$C$27)/1000)*(1+Calculator!$C$45+Calculator!$C$37)*Calculator!$C$39*(1-(1-MIN(Calculator!$C$44,MIN(1,E93+Calculator!$E$6/10*Constants!$B$16+Calculator!$C$36+Calculator!$C$40+Constants!$B$24*Calculator!$C$27)))*Constants!$B$6) -> 22.783842
A94: Guiding Star | B94: Bow | C94: MED 75 · Mind 25 | D94: 14 | E94: 0.1 | F94: MED | G94: 10 | H94: MND | I94: 3 | K94: 0 | L94: =D94*(1+0.75*(IFERROR(G94*INDEX(Calculator!$E$6:$E$23,MATCH(F94,Calculator!$A$6:$A$23,0)),0)+IFERROR(I94*INDEX(Calculator!$E$6:$E$23,MATCH(H94,Calculator!$A$6:$A$23,0)),0)+IFERROR(K94*INDEX(Calculator!$E$6:$E$23,MATCH(J94,Calculator!$A$6:$A$23,0)),0))*(1+Constants!$B$23*Calculator!$C$27)/1000)*(1+Calculator!$C$45+Calculator!$C$37)*Calculator!$C$39*(1-(1-MIN(Calculator!$C$44,MIN(1,E94+Calculator!$E$6/10*Constants!$B$16+Calculator!$C$36+Calculator!$C$40+Constants!$B$24*Calculator!$C$27)))*Constants!$B$6) -> 26.550354
A95: Hailbreaker | B95: Greatsword | C95: HVY 65 · ICE 55 · Power 10 | D95: 22 | E95: 0.15 | F95: HVY | G95: 7.5 | H95: ICE | I95: 4 | K95: 0 | L95: =D95*(1+0.75*(IFERROR(G95*INDEX(Calculator!$E$6:$E$23,MATCH(F95,Calculator!$A$6:$A$23,0)),0)+IFERROR(I95*INDEX(Calculator!$E$6:$E$23,MATCH(H95,Calculator!$A$6:$A$23,0)),0)+IFERROR(K95*INDEX(Calculator!$E$6:$E$23,MATCH(J95,Calculator!$A$6:$A$23,0)),0))*(1+Constants!$B$23*Calculator!$C$27)/1000)*(1+Calculator!$C$45+Calculator!$C$37)*Calculator!$C$39*(1-(1-MIN(Calculator!$C$44,MIN(1,E95+Calculator!$E$6/10*Constants!$B$16+Calculator!$C$36+Calculator!$C$40+Constants!$B$24*Calculator!$C$27)))*Constants!$B$6) -> 21.92388
A96: Halberd | B96: Greataxe | C96: HVY 25 | D96: 22 | E96: 0 | F96: HVY | G96: 7 | I96: 0 | K96: 0 | L96: =D96*(1+0.75*(IFERROR(G96*INDEX(Calculator!$E$6:$E$23,MATCH(F96,Calculator!$A$6:$A$23,0)),0)+IFERROR(I96*INDEX(Calculator!$E$6:$E$23,MATCH(H96,Calculator!$A$6:$A$23,0)),0)+IFERROR(K96*INDEX(Calculator!$E$6:$E$23,MATCH(J96,Calculator!$A$6:$A$23,0)),0))*(1+Constants!$B$23*Calculator!$C$27)/1000)*(1+Calculator!$C$45+Calculator!$C$37)*Calculator!$C$39*(1-(1-MIN(Calculator!$C$44,MIN(1,E96+Calculator!$E$6/10*Constants!$B$16+Calculator!$C$36+Calculator!$C$40+Constants!$B$24*Calculator!$C$27)))*Constants!$B$6) -> 20.66163
A97: Hallowscleave | B97: Sword | C97: MED 75 | D97: 19 | E97: 0.25 | F97: MED | G97: 7 | I97: 0 | K97: 0 | L97: =D97*(1+0.75*(IFERROR(G97*INDEX(Calculator!$E$6:$E$23,MATCH(F97,Calculator!$A$6:$A$23,0)),0)+IFERROR(I97*INDEX(Calculator!$E$6:$E$23,MATCH(H97,Calculator!$A$6:$A$23,0)),0)+IFERROR(K97*INDEX(Calculator!$E$6:$E$23,MATCH(J97,Calculator!$A$6:$A$23,0)),0))*(1+Constants!$B$23*Calculator!$C$27)/1000)*(1+Calculator!$C$45+Calculator!$C$37)*Calculator!$C$39*(1-(1-MIN(Calculator!$C$44,MIN(1,E97+Calculator!$E$6/10*Constants!$B$16+Calculator!$C$36+Calculator!$C$40+Constants!$B$24*Calculator!$C$27)))*Constants!$B$6) -> 31.626307
A98: Hero's Blade of Flame | B98: Sword | C98: FLM 100 · Power 10 | D98: 19 | E98: 0 | F98: FLM | G98: 5.5 | I98: 0 | K98: 0 | L98: =D98*(1+0.75*(IFERROR(G98*INDEX(Calculator!$E$6:$E$23,MATCH(F98,Calculator!$A$6:$A$23,0)),0)+IFERROR(I98*INDEX(Calculator!$E$6:$E$23,MATCH(H98,Calculator!$A$6:$A$23,0)),0)+IFERROR(K98*INDEX(Calculator!$E$6:$E$23,MATCH(J98,Calculator!$A$6:$A$23,0)),0))*(1+Constants!$B$23*Calculator!$C$27)/1000)*(1+Calculator!$C$45+Calculator!$C$37)*Calculator!$C$39*(1-(1-MIN(Calculator!$C$44,MIN(1,E98+Calculator!$E$6/10*Constants!$B$16+Calculator!$C$36+Calculator!$C$40+Constants!$B$24*Calculator!$C$27)))*Constants!$B$6) -> 17.844135
A99: Hero's Blade of Frost | B99: Sword | C99: ICE 100 · Power 10 | D99: 19 | E99: 0 | F99: ICE | G99: 5.5 | I99: 0 | K99: 0 | L99: =D99*(1+0.75*(IFERROR(G99*INDEX(Calculator!$E$6:$E$23,MATCH(F99,Calculator!$A$6:$A$23,0)),0)+IFERROR(I99*INDEX(Calculator!$E$6:$E$23,MATCH(H99,Calculator!$A$6:$A$23,0)),0)+IFERROR(K99*INDEX(Calculator!$E$6:$E$23,MATCH(J99,Calculator!$A$6:$A$23,0)),0))*(1+Constants!$B$23*Calculator!$C$27)/1000)*(1+Calculator!$C$45+Calculator!$C$37)*Calculator!$C$39*(1-(1-MIN(Calculator!$C$44,MIN(1,E99+Calculator!$E$6/10*Constants!$B$16+Calculator!$C$36+Calculator!$C$40+Constants!$B$24*Calculator!$C$27)))*Constants!$B$6) -> 17.844135
A100: Hero's Blade of Lightning | B100: Sword | C100: LTN 100 · Power 10 | D100: 19 | E100: 0 | F100: LTN | G100: 5.5 | I100: 0 | K100: 0 | L100: =D100*(1+0.75*(IFERROR(G100*INDEX(Calculator!$E$6:$E$23,MATCH(F100,Calculator!$A$6:$A$23,0)),0)+IFERROR(I100*INDEX(Calculator!$E$6:$E$23,MATCH(H100,Calculator!$A$6:$A$23,0)),0)+IFERROR(K100*INDEX(Calculator!$E$6:$E$23,MATCH(J100,Calculator!$A$6:$A$23,0)),0))*(1+Constants!$B$23*Calculator!$C$27)/1000)*(1+Calculator!$C$45+Calculator!$C$37)*Calculator!$C$39*(1-(1-MIN(Calculator!$C$44,MIN(1,E100+Calculator!$E$6/10*Constants!$B$16+Calculator!$C$36+Calculator!$C$40+Constants!$B$24*Calculator!$C$27)))*Constants!$B$6) -> 19.884523
A101: Hero's Blade of Shadow | B101: Sword | C101: SDW 100 · Power 10 | D101: 19 | E101: 0 | F101: SDW | G101: 5.5 | I101: 0 | K101: 0 | L101: =D101*(1+0.75*(IFERROR(G101*INDEX(Calculator!$E$6:$E$23,MATCH(F101,Calculator!$A$6:$A$23,0)),0)+IFERROR(I101*INDEX(Calculator!$E$6:$E$23,MATCH(H101,Calculator!$A$6:$A$23,0)),0)+IFERROR(K101*INDEX(Calculator!$E$6:$E$23,MATCH(J101,Calculator!$A$6:$A$23,0)),0))*(1+Constants!$B$23*Calculator!$C$27)/1000)*(1+Calculator!$C$45+Calculator!$C$37)*Calculator!$C$39*(1-(1-MIN(Calculator!$C$44,MIN(1,E101+Calculator!$E$6/10*Constants!$B$16+Calculator!$C$36+Calculator!$C$40+Constants!$B$24*Calculator!$C$27)))*Constants!$B$6) -> 17.844135
A102: Hero's Blade of Wind | B102: Sword | C102: WND 100 · Power 10 | D102: 19 | E102: 0 | F102: WND | G102: 5.5 | I102: 0 | K102: 0 | L102: =D102*(1+0.75*(IFERROR(G102*INDEX(Calculator!$E$6:$E$23,MATCH(F102,Calculator!$A$6:$A$23,0)),0)+IFERROR(I102*INDEX(Calculator!$E$6:$E$23,MATCH(H102,Calculator!$A$6:$A$23,0)),0)+IFERROR(K102*INDEX(Calculator!$E$6:$E$23,MATCH(J102,Calculator!$A$6:$A$23,0)),0))*(1+Constants!$B$23*Calculator!$C$27)/1000)*(1+Calculator!$C$45+Calculator!$C$37)*Calculator!$C$39*(1-(1-MIN(Calculator!$C$44,MIN(1,E102+Calculator!$E$6/10*Constants!$B$16+Calculator!$C$36+Calculator!$C$40+Constants!$B$24*Calculator!$C$27)))*Constants!$B$6) -> 17.844135
A103: Hivelord's Hubris | B103: Greathammer | C103: HVY 100 · STR 60 | D103: 28 | E103: 0.05 | F103: HVY | G103: 10 | I103: 0 | K103: 0 | L103: =D103*(1+0.75*(IFERROR(G103*INDEX(Calculator!$E$6:$E$23,MATCH(F103,Calculator!$A$6:$A$23,0)),0)+IFERROR(I103*INDEX(Calculator!$E$6:$E$23,MATCH(H103,Calculator!$A$6:$A$23,0)),0)+IFERROR(K103*INDEX(Calculator!$E$6:$E$23,MATCH(J103,Calculator!$A$6:$A$23,0)),0))*(1+Constants!$B$23*Calculator!$C$27)/1000)*(1+Calculator!$C$45+Calculator!$C$37)*Calculator!$C$39*(1-(1-MIN(Calculator!$C$44,MIN(1,E103+Calculator!$E$6/10*Constants!$B$16+Calculator!$C$36+Calculator!$C$40+Constants!$B$24*Calculator!$C$27)))*Constants!$B$6) -> 26.83212
A104: Hunting Bow | B104: Bow | C104: MED 20 | D104: 14 | E104: 0.05 | F104: MED | G104: 7 | I104: 0 | K104: 0 | L104: =D104*(1+0.75*(IFERROR(G104*INDEX(Calculator!$E$6:$E$23,MATCH(F104,Calculator!$A$6:$A$23,0)),0)+IFERROR(I104*INDEX(Calculator!$E$6:$E$23,MATCH(H104,Calculator!$A$6:$A$23,0)),0)+IFERROR(K104*INDEX(Calculator!$E$6:$E$23,MATCH(J104,Calculator!$A$6:$A$23,0)),0))*(1+Constants!$B$23*Calculator!$C$27)/1000)*(1+Calculator!$C$45+Calculator!$C$37)*Calculator!$C$39*(1-(1-MIN(Calculator!$C$44,MIN(1,E104+Calculator!$E$6/10*Constants!$B$16+Calculator!$C$36+Calculator!$C$40+Constants!$B$24*Calculator!$C$27)))*Constants!$B$6) -> 21.580806
A105: Icepick | B105: Rapier | C105: LHT 40 | D105: 13 | E105: 0.1 | F105: LHT | G105: 7 | I105: 0 | K105: 0 | L105: =D105*(1+0.75*(IFERROR(G105*INDEX(Calculator!$E$6:$E$23,MATCH(F105,Calculator!$A$6:$A$23,0)),0)+IFERROR(I105*INDEX(Calculator!$E$6:$E$23,MATCH(H105,Calculator!$A$6:$A$23,0)),0)+IFERROR(K105*INDEX(Calculator!$E$6:$E$23,MATCH(J105,Calculator!$A$6:$A$23,0)),0))*(1+Constants!$B$23*Calculator!$C$27)/1000)*(1+Calculator!$C$45+Calculator!$C$37)*Calculator!$C$39*(1-(1-MIN(Calculator!$C$44,MIN(1,E105+Calculator!$E$6/10*Constants!$B$16+Calculator!$C$36+Calculator!$C$40+Constants!$B$24*Calculator!$C$27)))*Constants!$B$6) -> 12.706395
A106: Ignition Deepcrusher | B106: Sword | C106: MED 40 · IRN 75 | D106: 18 | E106: 0.1 | F106: MED | G106: 3 | H106: IRN | I106: 4 | K106: 0 | L106: =D106*(1+0.75*(IFERROR(G106*INDEX(Calculator!$E$6:$E$23,MATCH(F106,Calculator!$A$6:$A$23,0)),0)+IFERROR(I106*INDEX(Calculator!$E$6:$E$23,MATCH(H106,Calculator!$A$6:$A$23,0)),0)+IFERROR(K106*INDEX(Calculator!$E$6:$E$23,MATCH(J106,Calculator!$A$6:$A$23,0)),0))*(1+Constants!$B$23*Calculator!$C$27)/1000)*(1+Calculator!$C$45+Calculator!$C$37)*Calculator!$C$39*(1-(1-MIN(Calculator!$C$44,MIN(1,E106+Calculator!$E$6/10*Constants!$B$16+Calculator!$C$36+Calculator!$C$40+Constants!$B$24*Calculator!$C$27)))*Constants!$B$6) -> 28.167497
A107: Imperator's Edge | B107: Spear | C107: MED 80 · STR 80 · FTD 80 | D107: 20 | E107: 0.2 | F107: MED | G107: 2 | H107: STR | I107: 3 | J107: FTD | K107: 4 | L107: =D107*(1+0.75*(IFERROR(G107*INDEX(Calculator!$E$6:$E$23,MATCH(F107,Calculator!$A$6:$A$23,0)),0)+IFERROR(I107*INDEX(Calculator!$E$6:$E$23,MATCH(H107,Calculator!$A$6:$A$23,0)),0)+IFERROR(K107*INDEX(Calculator!$E$6:$E$23,MATCH(J107,Calculator!$A$6:$A$23,0)),0))*(1+Constants!$B$23*Calculator!$C$27)/1000)*(1+Calculator!$C$45+Calculator!$C$37)*Calculator!$C$39*(1-(1-MIN(Calculator!$C$44,MIN(1,E107+Calculator!$E$6/10*Constants!$B$16+Calculator!$C$36+Calculator!$C$40+Constants!$B$24*Calculator!$C$27)))*Constants!$B$6) -> 27.031924
A108: Imperial Staff | B108: Staff | C108: MED 40 · STR 40 | D108: 20 | E108: 0.12 | F108: MED | G108: 5 | H108: STR | I108: 4 | K108: 0 | L108: =D108*(1+0.75*(IFERROR(G108*INDEX(Calculator!$E$6:$E$23,MATCH(F108,Calculator!$A$6:$A$23,0)),0)+IFERROR(I108*INDEX(Calculator!$E$6:$E$23,MATCH(H108,Calculator!$A$6:$A$23,0)),0)+IFERROR(K108*INDEX(Calculator!$E$6:$E$23,MATCH(J108,Calculator!$A$6:$A$23,0)),0))*(1+Constants!$B$23*Calculator!$C$27)/1000)*(1+Calculator!$C$45+Calculator!$C$37)*Calculator!$C$39*(1-(1-MIN(Calculator!$C$44,MIN(1,E108+Calculator!$E$6/10*Constants!$B$16+Calculator!$C$36+Calculator!$C$40+Constants!$B$24*Calculator!$C$27)))*Constants!$B$6) -> 29.903815
A109: Inquisitor's Greatsword | B109: Greatsword | C109: HVY 40 | D109: 23.5 | E109: 0 | F109: HVY | G109: 8.3 | I109: 0 | K109: 0 | L109: =D109*(1+0.75*(IFERROR(G109*INDEX(Calculator!$E$6:$E$23,MATCH(F109,Calculator!$A$6:$A$23,0)),0)+IFERROR(I109*INDEX(Calculator!$E$6:$E$23,MATCH(H109,Calculator!$A$6:$A$23,0)),0)+IFERROR(K109*INDEX(Calculator!$E$6:$E$23,MATCH(J109,Calculator!$A$6:$A$23,0)),0))*(1+Constants!$B$23*Calculator!$C$27)/1000)*(1+Calculator!$C$45+Calculator!$C$37)*Calculator!$C$39*(1-(1-MIN(Calculator!$C$44,MIN(1,E109+Calculator!$E$6/10*Constants!$B$16+Calculator!$C$36+Calculator!$C$40+Constants!$B$24*Calculator!$C$27)))*Constants!$B$6) -> 22.070377
A110: Inquisitor's Thorn | B110: Rapier | C110: LHT 40 | D110: 14 | E110: 0.1 | F110: LHT | G110: 7 | I110: 0 | K110: 0 | L110: =D110*(1+0.75*(IFERROR(G110*INDEX(Calculator!$E$6:$E$23,MATCH(F110,Calculator!$A$6:$A$23,0)),0)+IFERROR(I110*INDEX(Calculator!$E$6:$E$23,MATCH(H110,Calculator!$A$6:$A$23,0)),0)+IFERROR(K110*INDEX(Calculator!$E$6:$E$23,MATCH(J110,Calculator!$A$6:$A$23,0)),0))*(1+Constants!$B$23*Calculator!$C$27)/1000)*(1+Calculator!$C$45+Calculator!$C$37)*Calculator!$C$39*(1-(1-MIN(Calculator!$C$44,MIN(1,E110+Calculator!$E$6/10*Constants!$B$16+Calculator!$C$36+Calculator!$C$40+Constants!$B$24*Calculator!$C$27)))*Constants!$B$6) -> 13.68381
A111: Iron Birch | B111: Greataxe | C111: HVY 50 | D111: 26 | E111: 0 | F111: HVY | G111: 6 | I111: 0 | K111: 0 | L111: =D111*(1+0.75*(IFERROR(G111*INDEX(Calculator!$E$6:$E$23,MATCH(F111,Calculator!$A$6:$A$23,0)),0)+IFERROR(I111*INDEX(Calculator!$E$6:$E$23,MATCH(H111,Calculator!$A$6:$A$23,0)),0)+IFERROR(K111*INDEX(Calculator!$E$6:$E$23,MATCH(J111,Calculator!$A$6:$A$23,0)),0))*(1+Constants!$B$23*Calculator!$C$27)/1000)*(1+Calculator!$C$45+Calculator!$C$37)*Calculator!$C$39*(1-(1-MIN(Calculator!$C$44,MIN(1,E111+Calculator!$E$6/10*Constants!$B$16+Calculator!$C$36+Calculator!$C$40+Constants!$B$24*Calculator!$C$27)))*Constants!$B$6) -> 24.41829
A112: Iron Blunderbuss | B112: Rifle | C112: MED 75 | D112: 20 | E112: 0.1 | F112: MED | G112: 7 | I112: 0 | K112: 0 | L112: =D112*(1+0.75*(IFERROR(G112*INDEX(Calculator!$E$6:$E$23,MATCH(F112,Calculator!$A$6:$A$23,0)),0)+IFERROR(I112*INDEX(Calculator!$E$6:$E$23,MATCH(H112,Calculator!$A$6:$A$23,0)),0)+IFERROR(K112*INDEX(Calculator!$E$6:$E$23,MATCH(J112,Calculator!$A$6:$A$23,0)),0))*(1+Constants!$B$23*Calculator!$C$27)/1000)*(1+Calculator!$C$45+Calculator!$C$37)*Calculator!$C$39*(1-(1-MIN(Calculator!$C$44,MIN(1,E112+Calculator!$E$6/10*Constants!$B$16+Calculator!$C$36+Calculator!$C$40+Constants!$B$24*Calculator!$C$27)))*Constants!$B$6) -> 31.445004
A113: Iron Cestus | B113: Fist | C113: no stat requirement | D113: 13.5 | E113: 0 | F113: LHT | G113: 7.5 | I113: 0 | K113: 0 | L113: =D113*(1+0.75*(IFERROR(G113*INDEX(Calculator!$E$6:$E$23,MATCH(F113,Calculator!$A$6:$A$23,0)),0)+IFERROR(I113*INDEX(Calculator!$E$6:$E$23,MATCH(H113,Calculator!$A$6:$A$23,0)),0)+IFERROR(K113*INDEX(Calculator!$E$6:$E$23,MATCH(J113,Calculator!$A$6:$A$23,0)),0))*(1+Constants!$B$23*Calculator!$C$27)/1000)*(1+Calculator!$C$45+Calculator!$C$37)*Calculator!$C$39*(1-(1-MIN(Calculator!$C$44,MIN(1,E113+Calculator!$E$6/10*Constants!$B$16+Calculator!$C$36+Calculator!$C$40+Constants!$B$24*Calculator!$C$27)))*Constants!$B$6) -> 12.678728
A114: Iron Requiem | B114: Pistol | C114: LHT 40 · IRN 75 | D114: 21 | E114: 0 | F114: LHT | G114: 3 | H114: IRN | I114: 4 | K114: 0 | L114: =D114*(1+0.75*(IFERROR(G114*INDEX(Calculator!$E$6:$E$23,MATCH(F114,Calculator!$A$6:$A$23,0)),0)+IFERROR(I114*INDEX(Calculator!$E$6:$E$23,MATCH(H114,Calculator!$A$6:$A$23,0)),0)+IFERROR(K114*INDEX(Calculator!$E$6:$E$23,MATCH(J114,Calculator!$A$6:$A$23,0)),0))*(1+Constants!$B$23*Calculator!$C$27)/1000)*(1+Calculator!$C$45+Calculator!$C$37)*Calculator!$C$39*(1-(1-MIN(Calculator!$C$44,MIN(1,E114+Calculator!$E$6/10*Constants!$B$16+Calculator!$C$36+Calculator!$C$40+Constants!$B$24*Calculator!$C$27)))*Constants!$B$6) -> 26.432048
A115: Iron Spear | B115: Spear | C115: no stat requirement | D115: 17 | E115: 0 | F115: MED | G115: 2.5 | I115: 0 | K115: 0 | L115: =D115*(1+0.75*(IFERROR(G115*INDEX(Calculator!$E$6:$E$23,MATCH(F115,Calculator!$A$6:$A$23,0)),0)+IFERROR(I115*INDEX(Calculator!$E$6:$E$23,MATCH(H115,Calculator!$A$6:$A$23,0)),0)+IFERROR(K115*INDEX(Calculator!$E$6:$E$23,MATCH(J115,Calculator!$A$6:$A$23,0)),0))*(1+Constants!$B$23*Calculator!$C$27)/1000)*(1+Calculator!$C$45+Calculator!$C$37)*Calculator!$C$39*(1-(1-MIN(Calculator!$C$44,MIN(1,E115+Calculator!$E$6/10*Constants!$B$16+Calculator!$C$36+Calculator!$C$40+Constants!$B$24*Calculator!$C$27)))*Constants!$B$6) -> 19.435973
A116: Iron Twinblade | B116: Twinblade | C116: MED 15 | D116: 15 | E116: 0 | F116: MED | G116: 4 | I116: 0 | K116: 0 | L116: =D116*(1+0.75*(IFERROR(G116*INDEX(Calculator!$E$6:$E$23,MATCH(F116,Calculator!$A$6:$A$23,0)),0)+IFERROR(I116*INDEX(Calculator!$E$6:$E$23,MATCH(H116,Calculator!$A$6:$A$23,0)),0)+IFERROR(K116*INDEX(Calculator!$E$6:$E$23,MATCH(J116,Calculator!$A$6:$A$23,0)),0))*(1+Constants!$B$23*Calculator!$C$27)/1000)*(1+Calculator!$C$45+Calculator!$C$37)*Calculator!$C$39*(1-(1-MIN(Calculator!$C$44,MIN(1,E116+Calculator!$E$6/10*Constants!$B$16+Calculator!$C$36+Calculator!$C$40+Constants!$B$24*Calculator!$C$27)))*Constants!$B$6) -> 18.986535
...

Sheet Outfits
A1: Outfit | B1: Physical armor % | C1: Elemental armor % | D1: Durability | E1: Requirement | F1: Talents it gives
A2: Arachnid's Weave | B2: 25 | C2: 35 | D2: 2100 | E2: PWR 15 | F2: Corrosive Touch
A3: Authority Captain Uniform | B3: 30 | C3: 25 | D3: 2000
A4: Authority Commander | B4: 30 | C4: 30 | D4: 2800 | E4: PWR 15 | F4: Riot Breaker
A5: Authority Peacekeeper Armor | B5: 15 | C5: 10 | D5: 1600 | F5: Lowstride
A6: Barbarian | B6: 25 | C6: 20 | D6: 1200
A7: Black Diver | B7: 30 | C7: 30 | D7: 2600 | E7: PWR 15, WLL 10
A8: Blacksteel Attire | B8: 30 | C8: 0 | D8: 1000
A9: Bounty Hunter | B9: 20 | C9: 10 | D9: 1500 | E9: PWR 5 | F9: Lightweight
A10: Cala-Mariner | B10: 25 | C10: 35 | D10: 2200 | E10: PWR 15, WLL 5 | F10: Tidal Shock
A11: Carefree Garments | B11: 10 | C11: 15 | D11: 2000 | E11: PWR 6 | F11: Fleetfoot
A12: Celtorian Tideknight | B12: 30 | C12: 25 | D12: 2800 | E12: PWR 15 | F12: Tidekeeper
A13: Cerulean Gown | B13: 20 | C13: 25 | D13: 1500 | E13: PWR 8
A14: Cindergarb | B14: 25 | C14: 30 | D14: 3000 | E14: PWR 15, FLM 45 | F14: Repeated Propulsion, Warding Radiance
A15: Cloak of Winds | B15: 20 | C15: 30 | D15: 1200 | E15: PWR 10 | F15: Paired Soul
A16: Corsair Outlaw | B16: 15 | C16: 10 | D16: 1200 | F16: Lightweight
A17: Cutthroat Light Armor | B17: 10 | C17: 0 | D17: 1000 | E17: PWR 5 | F17: Hunter's Reflexes
A18: Darkened Bastion | B18: 30 | C18: 30 | D18: 2600 | E18: PWR 15 | F18: Withering Soul
A19: Darksteel Plate | B19: 25 | C19: 25 | D19: 2500 | E19: PWR 10, FTD 20 | F19: Unbreakable
A20: Diver Apprentice Robes | B20: 10 | C20: 15 | D20: 1000
A21: Diver Journeyman Robes | B21: 30 | C21: 20 | D21: 1000 | E21: PWR 10 | F21: Lowstride
A22: Duelist's Attire | B22: 20 | C22: 0 | D22: 1200 | E22: PWR 5
A23: Eager Tradesman | B23: 10 | C23: 5 | D23: 1000 | F23: Knack
A24: Etrean Guard | B24: 25 | C24: 20 | D24: 2000 | E24: PWR 10 | F24: Unbreakable
A25: Experienced Adventurer | B25: 10 | C25: 0 | D25: 1000 | E25: PWR 5 | F25: Looter
A26: Familiar Assassin's Armor | B26: 25 | C26: 25 | D26: 2000 | E26: PWR 15 | F26: Bane
A27: Familiar Demon's Armor | B27: 25 | C27: 25 | D27: 2500 | E27: PWR 15 | F27: Demon Step
A28: Familiar Heretic's Armor | B28: 35 | C28: 35 | D28: 4000 | E28: PWR 15 | F28: Soul Rip
A29: Familiar Knight's Armor | B29: 30 | C29: 40 | D29: 3500 | E29: PWR 15 | F29: Hyperbody
A30: Familiar Occultist's Armor | B30: 25 | C30: 25 | D30: 2000 | E30: PWR 15 | F30: Life Leech
A31: Ferryman's Coat | B31: 25 | C31: 35 | D31: 2500 | E31: PWR 12 | F31: Ferryman's Curse
A32: Flame Worshipper Armor | B32: 10 | C32: 5 | D32: 1000 | E32: PWR 5 | F32: Intrepid Flame, One With Flame
A33: Grand Pathfinder Cloak | B33: 20 | C33: 20 | D33: 2000 | E33: PWR 10 | F33: Legendary
A34: Heretic's Memento | B34: 25 | C34: 25 | D34: 2000 | E34: PWR 15 | F34: Overflow
A35: Hidden Knife Armor | B35: 25 | C35: 25 | D35: 2000 | F35: Bane
A36: Hired Mercenary | B36: 15 | C36: 15 | D36: 1000
A37: Hive Adjudicator | B37: 25 | C37: 25 | D37: 1000 | E37: PWR 15 | F37: Lowstride
A38: Hive Drone | B38: 25 | C38: 25 | D38: 1000 | E38: PWR 10 | F38: Lowstride
A39: Hive Tactician Armor | B39: 30 | C39: 20 | D39: 1200 | E39: PWR 10, AGL 25 | F39: Brunt
A40: Icebringer's Vestments | B40: 25 | C40: 30 | D40: 2600 | E40: PWR 15, ICE 45 | F40: Refreeze, Orbital Ice
A41: Ignition Deepdelver | B41: 30 | C41: 35 | D41: 3000 | E41: PWR 15 | F41: Force Your Way
A42: Ignition Trailblazer | B42: 25 | C42: 25 | D42: 1000 | E42: PWR 10 | F42: Perseverance, Strong Stern
A43: Ignition Union Uniform | B43: 22 | C43: 22 | D43: 2000 | E43: PWR 6
A44: Ignition Welder | B44: 25 | C44: 25 | D44: 3000 | E44: PWR 10, FTD 10 | F44: Master Craftsman
A45: Inquisition Light | B45: 30 | C45: 35 | D45: 3200 | E45: PWR 15 | F45: Lethal Dose
A46: Jade Vigil's Weave | B46: 30 | C46: 30 | D46: 3000 | E46: PWR 15, AGL 10 | F46: Serpent's Dance
A47: Jester's Garb | B47: 25 | C47: 35 | D47: 2500 | E47: PWR 12 | F47: Mocking Favor, Not a Scratch
A48: Justicar Neophyte | B48: 15 | C48: 15 | D48: 1500 | E48: PWR 1
A49: Justicar's Armor | B49: 30 | C49: 30 | D49: 2800 | E49: PWR 15 | F49: The Path, Unveiled
A50: Legion Centurion | B50: 30 | C50: 30 | D50: 3000 | E50: PWR 15, FTD 10 | F50: Centurion's Resolve
A51: Martial Artist | B51: 30 | C51: 20 | D51: 1200 | E51: PWR 10, STR 15 | F51: Bruiser's Mixup
A52: Merchant Robes | B52: 0 | C52: 0 | D52: 1200 | F52: Merchant's Accord
A53: Navaen Nomad Robes | B53: 10 | C53: 10 | D53: 1800 | E53: PWR 5 | F53: Fists of Navae
A54: Navaen War Chief | B54: 30 | C54: 30 | D54: 3000 | E54: PWR 15 | F54: Chief's Will
A55: Pathfinder Arch-Sorcerer | B55: 10 | C55: 25 | D55: 1500 | E55: PWR 10, INT 25 | F55: Devastating Power
A56: Pathfinder Cloak | B56: 18 | C56: 8 | D56: 1200 | E56: PWR 5 | F56: Survivalist
A57: Pathfinder Sorcerer | B57: 5 | C57: 10 | D57: 1000 | E57: INT 5 | F57: Lowstride
A58: Pathfinder Thaumaturge | B58: 10 | C58: 15 | D58: 1000 | E58: PWR 5, INT 10 | F58: Lowstride
A59: Prophet's Cloak | B59: 25 | C59: 25 | D59: 2600 | E59: PWR 15 | F59: Crippling Darkness
A60: Ringing Scholar's Garb | B60: 25 | C60: 30 | D60: 2400 | E60: PWR 15, INT 5 | F60: Lose Your Mind
A61: Royal Etrean Guard | B61: 30 | C61: 30 | D61: 3000 | E61: PWR 15 | F61: Paired Soul
A62: Sanguine Finery | B62: 25 | C62: 30 | D62: 2600 | E62: PWR 15, BLD 45 | F62: Focused Hematoma, Sheltered Grasp
A63: Scholar | B63: 8 | C63: 10 | D63: 1000 | F63: Scholar's Intuition
A64: Seamstress's Attire | B64: 25 | C64: 20 | D64: 2000 | E64: PWR 8
A65: Shadow Hunter | B65: 10 | C65: 5 | D65: 1500 | E65: AGL 10 | F65: Lowstride
A66: Shock Corps Light | B66: 30 | C66: 30 | D66: 3500 | E66: PWR 15 | F66: Battle-Hardened
A67: Skeptic Pioneer | B67: 12 | C67: 12 | D67: 1200 | F67: Apothecary
A68: Steel Plate | B68: 5 | C68: 0 | D68: 1000 | E68: PWR 5, FTD 10 | F68: Lowstride
A69: Stormchanter's Raiments | B69: 25 | C69: 30 | D69: 2600 | E69: PWR 15, LTN 45 | F69: Circuit Breaker, Kickstart
A70: Stratos' Cloak | B70: 20 | C70: 30 | D70: 2200 | F70: Breeze
A71: Summer Company Uniform | B71: 10 | C71: 5 | D71: 1500 | E71: PWR 5 | F71: Armor Piercing
A72: Summer Dragoon | B72: 30 | C72: 30 | D72: 2800 | E72: PWR 15 | F72: Sunset Ricochet
A73: Tempestmaker's Threads | B73: 25 | C73: 30 | D73: 2600 | E73: PWR 15, WND 45 | F73: Tempest Evolution, Aerogliding
A74: Titanslayer's Adornment | B74: 25 | C74: 40 | D74: 3300 | E74: PWR 15, STR 50 | F74: Primal Rage
A75: Titus's Raiment | B75: 25 | C75: 25 | D75: 3000 | E75: PWR 15, STR 30 | F75: Overwhelming Might
A76: Trickster's Habit | B76: 25 | C76: 35 | D76: 2500 | E76: PWR 12 | F76: Mocking Favor, Not a Scratch
A77: Troublemaker's Overcoat | B77: 25 | C77: 20 | D77: 2500 | E77: PWR 8
A78: Unsung | B78: 30 | C78: 0 | D78: 3000
A79: Varicosan Finery | B79: 20 | C79: 20 | D79: 1500 | E79: PWR 10 | F79: Benefactor
A80: Verdant Sniper | B80: 25 | C80: 20 | D80: 1500 | E80: PWR 10
A81: Veteran Adventurer | B81: 15 | C81: 15 | D81: 1500 | E81: PWR 10 | F81: Foolish Outburst
A82: Vigil Initiate | B82: 20 | C82: 0 | D82: 1200 | E82: PWR 5 | F82: Paired Soul
A83: Vigil Sentinel | B83: 30 | C83: 30 | D83: 2500 | E83: PWR 10, WLL 5 | F83: Vigil's Grace, Action Surge
A84: Warder's Attire | B84: 30 | C84: 35 | D84: 2750 | E84: PWR 15 | F84: Justicar's Gift
A85: Whaler Coat | B85: 25 | C85: 15 | D85: 1500 | E85: PWR 10
A86: Whaler Initiate | B86: 15 | C86: 5 | D86: 1500
A87: Windrunner Robes | B87: 25 | C87: 30 | D87: 2600 | E87: PWR 15, AGL 10 | F87: Wind Dancer

Sheet Equipment
A1: Item | B1: Slot | C1: Health | D1: Physical armor | E1: Elemental armor | F1: Pip slots (rarity) | G1: Requirement | H1: Set | I1: Talents it gives
A2: Abyss Wanderer's Plate | B2: Arms | C2: 5 | D2: 0 | E2: 0 | F2: L L L | G2: PWR 10 | H2: Abyss Wanderer | I2: Braced Collapse, Kick Off
A3: Adjudicator's Coat | B3: Arms | C3: 0 | D3: 0 | E3: 0 | F3: R R | G3: PWR 8 | I3: Unwavering Resolve
A4: Adventurer Coat | B4: Arms | C4: 0 | D4: 0 | E4: 0 | F4: R R | G4: PWR 5
A5: Aristocrat Coat | B5: Arms | C5: 6 | D5: 0 | E5: 0 | F5: R R | G5: PWR 10 | H5: Aristocrat | I5: Art of the Deal
A6: Ascended Outlaw Robes | B6: Arms | C6: 0 | D6: 0 | E6: 0 | F6: R L | G6: PWR 20 | H6: Ascended Outlaw | I6: Ether Pinpoint
A7: Assassin's Cloak | B7: Arms | C7: 6 | D7: 0 | E7: 0 | F7: R R L | G7: PWR 10 | H7: Assassin | I7: Lowstride
A8: Authority Commander Coat | B8: Arms | C8: 10 | D8: 0 | E8: 0 | F8: R R | G8: PWR 12
A9: Autumn Pauldrons | B9: Arms | C9: 0 | D9: 0 | E9: 0 | F9: R R | G9: PWR 5 | H9: Autumn
A10: Azure Sentinel Pauldrons | B10: Arms | C10: 0 | D10: 0 | E10: 0 | F10: R R L | H10: Azure Sentinel
A11: Bastions of Enmity | B11: Arms | C11: 10 | D11: 0 | E11: 0 | F11: L L L | G11: PWR 12 | H11: Enmity
A12: Blacksteel Pauldrons | B12: Arms | C12: 3 | D12: 0 | E12: 0 | F12: R | G12: PWR 8 | H12: Blacksteel
A13: Blademaster's Robe | B13: Arms | C13: 6 | D13: 0 | E13: 0 | F13: R R R | H13: Blademaster | I13: Swift Blade
A14: Bluesteel Pauldrons | B14: Arms | C14: 5 | D14: 0 | E14: 0 | F14: R R | G14: PWR 5 | H14: Bluesteel
A15: Bluestone Pauldrons | B15: Arms | C15: 5 | D15: 0 | E15: 0 | F15: R R | G15: PWR 5 | H15: Bluestone | I15: Ether Emergency
A16: Brigand's Cloak | B16: Arms | C16: 3 | D16: 0 | E16: 0 | F16: R R | G16: PWR 5 | H16: Brigand
A17: Brilliant Pauldrons | B17: Arms | C17: 5 | D17: 0 | E17: 0 | F17: R R L | H17: Brilliant
A18: Broodplate Cuirass | B18: Arms | C18: 0 | D18: 0 | E18: 0 | F18: R L | G18: PWR 10 | I18: Rotten Regeneration
A19: Celtor Commander Plate | B19: Arms | C19: 8 | D19: 0 | E19: 0 | F19: R R L | G19: PWR 10 | H19: Celtor Commander | I19: Breathing Exercise
A20: Champion's Cape | B20: Arms | C20: 0 | D20: 0 | E20: 0 | F20: R R L | G20: PWR 20 | I20: No Interruptions
A21: Crimson Terraplate Pauldrons | B21: Arms | C21: 0 | D21: 0 | E21: 0 | F21: L R R | G21: PWR 10 | I21: Cruentare
A22: Dark Owl Cloak | B22: Arms | C22: 0 | D22: 0 | E22: 0 | F22: R L | G22: PWR 8 | H22: Dark Owl | I22: Disbelief
A23: Deepwoken Cloak | B23: Arms | C23: 5 | D23: 0 | E23: 0 | F23: R R L | G23: PWR 10 | H23: Deepwoken | I23: Blade Dancer
A24: Delver's Duster | B24: Arms | C24: 5 | D24: 0 | E24: 0 | F24: L L L | G24: PWR 10 | I24: Braced Collapse, Kick Off
A25: Diver's Light Plate | B25: Arms | C25: 10 | D25: 0 | E25: 0 | F25: L L L | G25: PWR 12 | I25: Conquer your Fears
A26: Enforcer Plate | B26: Arms | C26: 0 | D26: 0 | E26: 0 | F26: R L | G26: PWR 8 | H26: Enforcer | I26: Berserker
A27: Ether Refined Mantle | B27: Arms | C27: 7 | D27: 0 | E27: 0 | F27: R L L | G27: PWR 12, INT 5 | H27: Ether Refined | I27: Sorcerer's Surge, Overflowing Dam
A28: Etrean Siege Cuirass | B28: Arms | C28: 8 | D28: 0 | E28: 0 | F28: U R L | G28: PWR 10 | H28: Etrean Siege | I28: Battle Tendency
A29: Evanspear War Plate | B29: Arms | C29: 6 | D29: 0 | E29: 0 | F29: R L | G29: PWR 10, STR 25 | H29: Evanspear War
A30: First Ranger Duster | B30: Arms | C30: 10 | D30: 0 | E30: 0 | F30: R R | G30: PWR 10
A31: Flameguard Pauldrons | B31: Arms | C31: 0 | D31: 0 | E31: 0 | F31: R | H31: Flameguard
A32: Fur Parka | B32: Arms | C32: 2 | D32: 0 | E32: 0 | F32: R | I32: Steady Footing
A33: Fur Pauldrons | B33: Arms | C33: 3 | D33: 0 | E33: 0 | F33: R | H33: Fur
A34: Gladiator Pauldrons | B34: Arms | C34: 3 | D34: 0 | E34: 0 | F34: R | G34: PWR 5 | H34: Gladiator
A35: Glassdancer Wraps | B35: Arms | C35: 2 | D35: 0 | E35: 0 | F35: R | G35: PWR 8 | I35: Lightweight
A36: Grand Authority Plate | B36: Arms | C36: 8 | D36: 0 | E36: 0 | F36: U R L | G36: PWR 10 | H36: Grand Authority | I36: Heavy Haul
A37: Grand Fisher Plate | B37: Arms | C37: 10 | D37: 0 | E37: 0 | F37: L L L | G37: PWR 12 | H37: Grand Fisher | I37: Diver's Resilience
A38: Grand Pauldrons | B38: Arms | C38: 0 | D38: 0 | E38: 0 | F38: R R | H38: Grand
A39: Guardian Pauldrons | B39: Arms | C39: 2 | D39: 0 | E39: 0 | H39: Guardian
A40: Gumshoe Longcoat | B40: Arms | C40: 2 | D40: 0 | E40: 0 | F40: R | G40: PWR 5 | H40: Gumshoe | I40: Hard Read
A41: Hardened Enforcer Plate | B41: Arms | C41: 0 | D41: 0 | E41: 0 | F41: R L | G41: PWR 8 | H41: Hardened Enforcer | I41: Berserker, Enforcer's Strength
A42: Hive Scourge Cuirass | B42: Arms | C42: 5 | D42: 0 | E42: 0 | F42: U R L | G42: PWR 12 | I42: Lowstride
A43: Ignition Gauntlets | B43: Arms | C43: 8 | D43: 0 | E43: 0 | F43: R L L | G43: PWR 12 | I43: Force Your Way
A44: Imperial Pauldrons | B44: Arms | C44: 7 | D44: 0 | E44: 0 | F44: R R | G44: PWR 8 | H44: Imperial
A45: Inquisitor's Duster | B45: Arms | C45: 0 | D45: 0 | E45: 0 | F45: R R | G45: PWR 5
A46: Iron Pauldrons | B46: Arms | C46: 0 | D46: 0 | E46: 0 | F46: R R | H46: Iron
A47: Ironsinger Heavy Plate | B47: Arms | C47: 10 | D47: 0 | E47: 0 | F47: R L L | G47: PWR 12 | I47: Stay of Execution
A48: Justicar Defender | B48: Arms | C48: 0 | D48: 0 | E48: 0 | F48: R R R R | G48: PWR 5
A49: Leather Gloves | B49: Arms | C49: 2 | D49: 0 | E49: 0 | F49: U | H49: Leather
A50: Leather Pauldrons | B50: Arms | C50: 2 | D50: 0 | E50: 0 | H50: Leather
A51: Legion Pauldrons | B51: Arms | C51: 3 | D51: 0 | E51: 0 | F51: R R | H51: Legion | I51: Polite Awakening
A52: Legion Phalanx Plate | B52: Arms | C52: 6 | D52: 0 | E52: 0 | F52: R R L | G52: PWR 12 | H52: Legion Phalanx | I52: Hoplite
A53: Megalodaunt Coat | B53: Arms | C53: 0 | D53: 0 | E53: 0 | F53: R R | G53: PWR 5
A54: Mercenary's Garb | B54: Arms | C54: 0 | D54: 0 | E54: 0 | F54: R L | H54: Mercenary | I54: Kick Off
A55: Ministry Cloak | B55: Arms | C55: 5 | D55: 0 | E55: 0 | F55: R L | G55: PWR 8
A56: Ministry Operative Cloak | B56: Arms | C56: 0 | D56: 0 | E56: 0 | F56: R R L | I56: Eureka
A57: Monastery Champion Robes | B57: Arms | C57: 8 | D57: 0 | E57: 0 | F57: R L L | G57: PWR 12 | H57: Monastery Champion | I57: Temple Guard
A58: Moonseye Gauntlets | B58: Arms | C58: 7 | D58: 0 | E58: 0 | F58: R L | G58: PWR 12
A59: Novice Brace | B59: Arms | C59: 2 | D59: 0 | E59: 0 | F59: R | H59: Novice
A60: Ossified Black Pauldrons | B60: Arms | C60: 3 | D60: 0 | E60: 0 | F60: R | H60: Ossified Blood | I60: Laminated Armor
A61: Ossified Simple Pauldrons | B61: Arms | C61: 3 | D61: 0 | E61: 0 | F61: R | I61: Simple Buff
A62: Pathfinder Elite | B62: Arms | C62: 0 | D62: 0 | E62: 0 | F62: R R L | G62: PWR 8
A63: Providence Coat | B63: Arms | C63: 5 | D63: 0 | E63: 0 | F63: R R | G63: PWR 8 | I63: Braced Collapse
A64: Ranger's Brace | B64: Arms | C64: 3 | D64: 0 | E64: 0 | F64: R R | G64: PWR 8 | H64: Ranger
A65: Redsteel Pauldrons | B65: Arms | C65: 3 | D65: 0 | E65: 0 | F65: R R | H65: Redsteel
A66: Reinforced War Plate | B66: Arms | C66: 6 | D66: 0 | E66: 0 | F66: R L | G66: PWR 20, STR 25 | H66: Reinforced War | I66: Crippling Impact
A67: Ringing Scholar's Raiments | B67: Arms | C67: 4 | D67: 0 | E67: 0 | F67: L L | G67: PWR 12 | H67: Ringing Scholar
A68: Royal Duelist | B68: Arms | C68: 0 | D68: 0 | E68: 0 | F68: R R | G68: PWR 5
A69: Royal Pathfinder | B69: Arms | C69: 6 | D69: 0 | E69: 0 | F69: R L | G69: PWR 10 | I69: Ready or Not
A70: Sailor's Fleece | B70: Arms | C70: 0 | D70: 0 | E70: 0 | F70: R
A71: Sandrunner Wraps | B71: Arms | C71: 6 | D71: 0 | E71: 0 | F71: R L | G71: PWR 8 | H71: Sandrunner | I71: Kick Off
A72: Shock Trooper Plate | B72: Arms | C72: 5 | D72: 0 | E72: 0 | F72: R R | G72: PWR 10 | H72: Shock Trooper
A73: Silver Pauldrons | B73: Arms | C73: 3 | D73: 0 | E73: 0 | F73: R R | H73: Silver Knight
A74: Simple Pauldrons | B74: Arms | C74: 2 | D74: 0 | E74: 0
A75: Smith's Gloves | B75: Arms | C75: 5 | D75: 0 | E75: 0 | F75: R R | G75: PWR 5 | H75: Smith
A76: Specialist Plate | B76: Arms | C76: 5 | D76: 0 | E76: 0 | F76: R | G76: PWR 20, LTN 30, WND 30 | H76: Specialist | I76: Stormcall
A77: Star Duster | B77: Arms | C77: 5 | D77: 0 | E77: 0 | F77: R R L | G77: PWR 10 | H77: Star | I77: Star Duster
A78: Steel Pauldrons | B78: Arms | C78: 2 | D78: 0 | E78: 0 | F78: U
A79: Summer Scarf | B79: Arms | C79: 5 | D79: 0 | E79: 0 | F79: L | G79: PWR 5
A80: Terraplate Pauldrons | B80: Arms | C80: 0 | D80: 0 | E80: 0 | F80: R R L | G80: PWR 10 | I80: Terrapod Tracer
A81: Titus's Cape | B81: Arms | C81: 0 | D81: 0 | E81: 0 | F81: R R L | G81: PWR 15
A82: Tracker's Brace | B82: Arms | C82: 3 | D82: 0 | E82: 0 | F82: R R | G82: PWR 8 | H82: Tracker
A83: Trimmed Overcoat | B83: Arms | C83: 3 | D83: 0 | E83: 0 | F83: R
A84: Vanguard Brace | B84: Arms | C84: 3 | D84: 0 | E84: 0 | F84: R R | G84: PWR 10 | H84: Vanguard | I84: Replenishing Knockout
A85: Warden Pauldrons | B85: Arms | C85: 10 | D85: 0 | E85: 0 | F85: L | G85: PWR 12
A86: Warlock's Mantle | B86: Arms | C86: 7 | D86: 0 | E86: 0 | F86: R L L | G86: PWR 12, INT 5 | H86: Warlock | I86: Overflowing Dam
A87: Western Outlaw Robes | B87: Arms | C87: 0 | D87: 0 | E87: 0 | F87: R L | G87: PWR 10 | H87: Western Outlaw
A88: Winter Corps Parka | B88: Arms | C88: 6 | D88: 0 | E88: 0 | F88: R R | G88: PWR 10 | H88: Winter Corps | I88: Winter's Protection
A89: Woodland Pauldrons | B89: Arms | C89: 2 | D89: 0 | E89: 0 | F89: R | H89: Woodland | I89: Polite Awakening
A90: Dark Pearls | B90: Earrings | C90: 2 | D90: 0 | E90: 0 | G90: PWR 10, SDW 40 | I90: Inky Pearls
A91: Ember Scorch Earrings | B91: Earrings | C91: 0 | D91: 0 | E91: 0 | F91: C R | I91: Smoldering Touch
A92: Ether Empowered Earrings | B92: Earrings | C92: 0 | D92: 0 | E92: 0 | F92: R R | I92: Ether Adeptness
A93: Ether Imbued Earrings | B93: Earrings | C93: 0 | D93: 0 | E93: 0 | F93: R R | I93: Ether Tension
A94: Frost Crystal Earrings | B94: Earrings | C94: 0 | D94: 0 | E94: 0 | F94: R R | G94: PWR 5 | I94: Instant Nucleation
A95: Gale Enhanced Earrings | B95: Earrings | C95: 0 | D95: 0 | E95: 0 | F95: C R | G95: PWR 5 | H95: Gale Enhanced | I95: Way of the Wind
A96: Ossified Blood Earrings | B96: Earrings | C96: 0 | D96: 0 | E96: 0 | F96: R R | I96: Sharpened Dagger
A97: Regenerative Earrings | B97: Earrings | C97: 0 | D97: 0 | E97: 0 | F97: R | G97: PWR 8 | H97: Regenerative | I97: Blood Convergence
A98: Shiva's Pendant Earrings | B98: Earrings | C98: 0 | D98: 0 | E98: 0 | F98: C R | H98: Shiva | I98: Skillful Recovery
A99: Ascended Outlaw Mask | B99: Face | C99: 0 | D99: 0 | E99: 0 | F99: C | H99: Ascended Outlaw | I99: Destructive Yell
A100: Authority Voltspark Mask | B100: Face | C100: 0 | D100: 0 | E100: 0 | F100: C | I100: Volt Reflex
...

Sheet Enchants
A1: Enchant | B1: Always-on hit multiplier | C1: Added PEN | D1: Sometimes (shown, not counted) | E1: Extra damage trigger | F1: What it does
A2: None
A3: Deferred | B3: 1.07 | F3: +7% weapon damage, dealt over time (10% every 0.5s).
A4: Curse of the Bloodthirsty | B4: 1.1 | F4: +10% damage on strike; drains your blood when you miss.
A5: Chilling | B5: 1.04 | F5: M1s deal +4% as a separate Frostdraw hit (+10% after Chilling procs). Bottom Freeze every 3/4/5 hits.
A6: Sear | C6: 0.05 | F6: +5% PEN. Cauterize stacks add more PEN per hit (up to +40%, past the cap); drains thirst.
A7: Heroism | D7: 0.2 | F7: +4% damage per 5% health above 75% or below 25%: up to +20% at full or near-zero health.
A8: Grim | D8: 0.25 | F8: After 4/5/5 hits the target takes +25% damage and +50% posture damage from everything.
A9: Storm | E9: Thundercall hit on strike (5s cooldown), doubled in rain | F9: On strike: 16.5% of weapon damage as Thundercall (5s cooldown), 33% in rain.
A10: Stormbreaker | E10: Thundercall hit on strike (5s cooldown) | F10: Same strike proc as Storm; your critical becomes a weapon throw for 40 + 30 flat Thundercall damage.
A11: Umbral Knight | E11: parryable follow-up (5s cooldown) | F11: On strike: the Umbral Knight hits for 20% of weapon damage after 0.25s (5s cooldown).
A12: Bluster | E12: explosion after a 10s countdown | F12: After 3/4/5 hits, a countdown ends in an explosion: 27.5 + 0.25 × weapon stat (max 52.5).
A13: Detonation | E13: typeless AoE every 3/4/5 hits | F13: After 3/4/5 hits, a 10 damage explosion that auto-grips humanoids.
A14: Stone | E14: true damage when a weapon hit guardbreaks | F14: +0.25 true damage per weapon point when your weapon attacks guardbreak.
A15: Wild | E15: AoE to other enemies (not your target) | F15: 85% of scaled damage hits others nearby as typeless AoE.
A16: Astral | F16: +20% weapon damage in PvE only (bypasses the PvE cap). Stars on criticals and after 3 parries.
A17: Curse of the Covetous | F17: Base damage −7.5%, +0.01% per Note held: break-even at 7.5k Notes, +7.5% at 15k.
A18: Blazing | F18: Sets enemies ablaze after 1/2/3 hits (Heavy/Medium/Light) for 5 seconds.
A19: Windswept | F19: Applies Winded (slower swings) after 1/2/3 hits; lasts 0.08s per weapon point.
A20: Obfuscation | F20: Adds chip damage: 25% Heavy, 20% Medium, 15% Light.
A21: Vampirism | F21: 15% of damage dealt comes back as temporary health.
A22: Nemesis | F22: Basic attacks mark enemies; your critical teleports to all marked targets for 25 damage.
A23: Kyrsan Chill | F23: Criticals apply a stacking slow; full Freeze at 5 stacks.
A24: Suffocated | F24: Criticals, uppercuts, flourishes and offhand hits apply Suffocation.
A25: Elastic | F25: Every M1 pulls enemies toward you.
A26: Erebus | F26: Criticals put one of the opponent's mantras on a 1 minute cooldown.
A27: Harrowing | F27: Hides the opponent's health, posture and armor bars for 12 seconds.
... A41: Parasol's Blight | F41: Players who die while blighted explode into a random monster.

Sheet Oaths
A1: Oath | B1: Requirement | C1: Stat options (any one) | D1: Note
A2: None
A3: Oathless | B3: no stat requirement | C3: none | D3: Quest only.
A4: Blindseer | B4: WLL 40 · after Breathing Exercise, Conquer your Fears, Disbelief | C4: WLL 40 | D4: Needs the three Mental Fortress talents.
A5: Visionshaper | B5: CHA 50 | C5: CHA 50
A6: Starkindred | B6: STR 40 | C6: STR 40 | D6: Can't be re-obtained if broken.
A7: Arcwarder | B7: FTD 20 · FLM 20 · LTN 20 | C7: FTD 20 · FLM 20 · LTN 20 | D7: Can't be re-obtained if broken.
A8: Jetstriker | B8: AGL 50 | C8: AGL 50 | D8: Beat Alirian in a race.
A9: Linkstrider | B9: no stat requirement | C9: none | D9: Quest only.
A10: Dawnwalker | B10: Power 10 | C10: none | D10: Needs 30 Medallions.
A11: Contractor | B11: after Oath: Contractor | C11: none | D11: Quest only. Can't be re-obtained if broken.
A12: Silentheart | B12: STR 25 · (AGL 25 or CHA 25) · 75 combined weapon | C12: 75 combined weapon · STR 25 · AGL 25 OR 75 combined weapon · STR 25 · CHA 25 | D12: Weapon stat requirements on weapons are 25 lower. Can't be re-obtained if broken.
A13: Fadetrimmer | B13: Power 12 | C13: none | D13: Change your appearance 12 times.
A14: Saltchemist | B14: INT 75 | C14: INT 75 | D14: Re-obtainable if broken.
A15: Chainwarden | B15: 40 combined STR+FTD+WLL | C15: 40 combined STR+FTD+WLL | D15: Can't be re-obtained if broken.
A16: Bladeharper | B16: (AGL 25 or STR 25 or MED 75) · 90 combined weapon | C16: MED 75 OR 90 combined weapon · STR 25 OR 90 combined weapon · AGL 25 | D16: Re-obtainable if broken.
A17: Saintsworn | B17: FLM 15 · ICE 15 · WND 15 · LTN 15 · SDW 15 | C17: FLM 15 · ICE 15 · WND 15 · LTN 15 · SDW 15 | D17: Talk to all 5 Obelisks. Can't be re-obtained if broken.
... A19: Blightsurger | B19: 80 combined STR+FTD+AGL · 40 combined WND+LTN | C19: 80 combined STR+FTD+AGL · 40 combined WND+LTN | D19: Progression can't be skipped with Knowledge.

Sheet Presets
A1: Preset | B1: Description | C1: Oath | D1: Weapon target | E1: Attunements | F1: Before shrine | G1: After shrine
A2: Clean Slate | B2: 0 in everything · no oath, weapon, attunement, talents or equipment | C2: None | D2: MED 0 | E2: {} | F2: {} | G2: {}
A3: Bossraid | B3: FTD 75 + WLL 50 before the shrine (it brings FTD down) · Heavy 90 | C3: Silentheart | D3: HVY 90 | E3: {} | F3: {"FTD":75,"WLL":50} | G3: {}
A4: Bossraid Mage | B4: FTD 75 + WLL 50 + INT 40 before the shrine · attunement 100 of your choice, no weapon | C4: Saintsworn | D4: MED 0 | E4: {"ICE":100} | F4: {"FTD":75,"WLL":50,"INT":40} | G4: {}
A5: Elder / Enmity | B5: Bladeharper Ironsing: CHA 40 before (shrinks down) · INT 1 before, 90 after · STR 25 · Ironsing 80, Shadowcast 20 · Shattered Katana | C5: Bladeharper | D5: MED 90 | E5: {"IRN":80,"SDW":20} | F5: {"CHA":40} | G5: {"INT":90,"STR":25}
A6: Brick Wall Dawnwalker | B6: FTD 100 + WLL 100 before (Brick Wall), shrine brings them to 75 · Frostdraw 80 + Flamecharm 40, steam path · Gran Sudaruska | C6: Dawnwalker | D6: HVY 40 | E6: {"ICE":80,"FLM":40} | F6: {"FTD":100,"WLL":100} | G6: {"FTD":75,"WLL":75}
A7: Chime | B7: STR 40 + AGL 40 + WLL 30 before · FTD 50 after (1 before) | C7: Bladeharper | D7: MED 80 | E7: {} | F7: {"STR":40,"AGL":40,"WLL":30} | G7: {"FTD":50}
A8: High Charisma | B8: CHA 75 + AGL 40 before · FTD 50 after (1 before) | C8: Soulbreaker | D8: LHT 75 | E8: {} | F8: {"CHA":75,"AGL":40} | G8: {"FTD":50}
A9: High Strength | B9: STR 100 + AGL 40 before · FTD 50 after (1 before) | C9: Silentheart | D9: MED 90 | E9: {} | F9: {"STR":100,"AGL":40} | G9: {"FTD":50}
A10: Jetstriker Agility | B10: AGL 75 + STR 40 before · AGL 50, FTD 50 after | C10: Jetstriker | D10: LHT 80 | E10: {} | F10: {"AGL":75,"STR":40} | G10: {"FTD":50,"AGL":50}
A11: Willpower Tank | B11: WLL 100 + FTD 100 before · the shrine brings FTD down to about 75 | C11: Dawnwalker | D11: MED 60 | E11: {} | F11: {"WLL":100,"FTD":100} | G11: {"FTD":75}
A12: High Intelligence | B12: INT 90 + AGL 40 before · FTD 50 after (1 before) | C12: Saltchemist | D12: LHT 60 | E12: {} | F12: {"INT":90,"AGL":40} | G12: {"FTD":50}
... A15: No Willpower | B15: CHA 35 + AGL 40 before · FTD 50 after (1 before) · WLL 0 | C15: Jetstriker | D15: LHT 85 | E15: {} | F15: {"CHA":35,"AGL":40} | G15: {"FTD":50}

Sheet Constants
A1: Name | B1: Value | C1: Meaning
A2: BUDGET | B2: 330 | C2: Stat points a Power 20 character has (330).
A3: SHRINE_POWER | B3: 8 | C3: The Shrine of Order can only be used at Power 8 or higher.
A4: SHRINE_POINTS | B4: 135 | C4: Points invested to reach Power 8: 15*8+15.
A5: SHRINE_MAX_DROP | B5: 25 | C5: Shrine of Order: an attribute never ends more than 25 below its pre-shrine value (attunements are exempt).
A6: ARMOR | B6: 0.3 | C6: Generic target armor used for damage numbers: hits are multiplied by 1-(1-PEN)*ARMOR.
A7: PEN_PHYS | B7: 35 | C7: Physical penetration assumed against your armor (%) when computing your resistance.
A8: PEN_ELE | B8: 20 | C8: Elemental penetration assumed against your armor (%).
A9: BASE_HP | B9: 220 | C9: Base health before Power and Fortitude.
A10: HP_PER_POWER | B10: 4 | C10: Health per Power level (Power 20 assumed for gear).
A11: HP_PER_FTD_TO_50 | B11: 0.5 | C11: Health per Fortitude point up to 50.
A12: HP_PER_FTD_PAST_50 | B12: 0.25 | C12: Health per Fortitude point above 50.
A13: DMG_SOFTCAP | B13: 0.25 | C13: Talent damage bonus counts in full up to +25%, half past it.
... A30: COMBO_PTS | B30: 10 | C30: Value of a true mantra combo in the optimizer.
A32: Equipment pip values (health / physical / elemental per pip, by slot and rarity)
A33: Slot | B33: Pip stat | C33: Common / Uncommon / Rare / Legendary
A34: Head | B34: Health | C34: U:4 / R:4 / L:5
A35: Head | B35: Physical armor | C35: R:2 / L:4
A36: Head | B36: Elemental armor | C36: R:3 / L:4
A37: Arms | B37: Health | C37: C:3 / U:4 / R:4 / L:5
A38: Arms | B38: Physical armor | C38: R:2 / L:4
A39: Arms | B39: Elemental armor | C39: R:3 / L:4
A40: Legs | B40: Health | C40: U:4 / R:4 / L:5
A41: Torso | B41: Health | C41: U:3 / R:4 / L:5
A42: Ring | B42: Health | C42: U:2 / R:3 / L:4
